Workbook

Sheet Sheet2
A1: Data returned for Sum of Revenue, Groceries (First 1000 rows).
A3: tblOrders[OrderID] | B3: tblOrders[OrderDate] | C3: tblOrders[CustomerName] | D3: tblOrders[Region] | E3: tblOrders[City] | F3: tblOrders[Category] | G3: tblOrders[Product] | H3: tblOrders[Channel] | I3: tblOrders[Quantity] | J3: tblOrders[UnitPrice] | K3: tblOrders[Discount] | L3: tblOrders[PaymentMethod] | M3: tblOrders[OrderStatus] | N3: tblOrders[SalesRep] | O3: tblOrders[Notes] | P3: tblOrders[CustomerName_Clean] | Q3: tblOrders[Region_Clean] | R3: tblOrders[Category_Clean] | S3: tblOrders[Channel_Clean] | T3: tblOrders[PaymentMethod_Clean] | U3: tblOrders[OrderStatus_Cleaned] | V3: tblOrders[Quantity_Clean] | W3: tblOrders[UnitPrice_Clean] | X3: tblOrders[OrderDate_Clean] | Y3: tblOrders[Discount_Clean] | Z3: tblOrders[Notes_Clean] | AA3: tblOrders[HighValueFlag] | AB3: tblOrders[Revenue] | AC3: tblOrders[OrderID_Key] | AD3: tblOrders[OrderNumber] | AE3: tblOrders[MonthLabel] | AF3: tblOrders[MonthEndDate] | AG3: tblOrders[FirstName] | AH3: tblOrders[Column1]
A4: ORD-1217 | B4: 2024-12-22 | C4: GRACE FAROOQ | D4: EAST | E4: Sialkot | F4: groceries | G4: Basmati Rice 5kg | H4: Online | I4: 8 | J4: $474.88 | K4: 0.1 | L4: Bank Transfer | M4: PENDING | N4: E. Tanaka | O4: Follow up needed | P4: Grace Farooq | Q4: East | R4: Groceries | S4: Online | T4: Bank Transfer | U4: Pending | V4: 8 | W4: 474.88 | X4: 45648 | Y4: 0.1 | Z4: Follow up needed | AA4: High Value | AB4: 3799.04 | AC4: ORD-1217 | AD4: 1217 | AE4: Dec-2024 | AF4: 45657 | AG4: Grace
A5: ORD-1143 | B5: 24/03/2024 | C5: Bilal Hussain | D5: South | E5: Karachi | F5: groceries | G5: Almonds 500g | H5: Online | I5: 5 | J5: $330.74 | L5: Credit card | M5: Refunded | N5: A. Malik | P5: Bilal Hussain | Q5: South | R5: Groceries | S5: Online | T5: Credit Card | U5: Refunded | V5: 5 | W5: 330.74 | X5: 45375 | Y5: 0 | AA5: High Value | AB5: 1653.7 | AC5: ORD-1143 | AD5: 1143 | AE5: Mar-2024 | AF5: 45382 | AG5: bilal
A6: ORD-1099 | B6: 25/09/2024 | C6: Grace Khan | D6: west | E6: Quetta | F6: groceries | G6: Olive Oil 1L | H6: In-store | J6: $286.14 | K6: 0.1 | L6: debit card | M6: PENDING | N6: E. Tanaka | O6: Follow up needed | P6: Grace Khan | Q6: West | R6: Groceries | S6: In-Store | T6: Debit Card | U6: Pending | W6: 286.14 | X6: 45560 | Y6: 0.1 | Z6: Follow up needed | AA6: Review | AB6: 0 | AC6: ORD-1099 | AD6: 1099 | AE6: Sep-2024 | AF6: 45565 | AG6: Grace
A7: ORD-1060 | B7: 28-Feb-24 | C7: Grace Taylor | D7: Nort | E7: Lahore | F7: groceries | G7: Green Tea Pack | H7: In-store | I7: 6 | J7: $256.17 | K7: 0 | L7: debit card | M7: PENDING | N7: C. Osei | O7: VIP customer | P7: Grace Taylor | Q7: North | R7: Groceries | S7: In-Store | T7: Debit Card | U7: Pending | V7: 6 | W7: 256.17 | X7: 45350 | Y7: 0 | Z7: VIP customer | AA7: High Value | AB7: 1537.02 | AC7: ORD-1060 | AD7: 1060 | AE7: Feb-2024 | AF7: 45351 | AG7: Grace
A8: ORD-1153 | B8: 12/09/2024 | C8: Sarah Malik | D8: west | F8: groceries | G8: Green Tea Pack | H8: Online | I8: 3 | J8: $225.78 | K8: 20% | L8: Credit card | M8: PENDING | N8: C. Osei | O8: Bulk order - business account | P8: Sarah Malik | Q8: West | R8: Groceries | S8: Online | T8: Credit Card | U8: Pending | V8: 3 | W8: 225.78 | X8: 45635 | Y8: 20% | Z8: Bulk order - business account | AA8: Standard | AB8: 677.34 | AC8: ORD-1153 | AD8: 1153 | AE8: Dec-2024 | AF8: 45657 | AG8: sarah
A9: ORD-1027 | B9: July 20, 2024 | C9: MARIA ANDERSON | D9: South | E9: Karachi | F9: groceries | G9: Almonds 500g | H9: In-store | I9: 11 | J9: $205.14 | K9: 0.05 | L9: cash | M9: PENDING | N9: A. Malik | O9: Gift wrap requested | P9: Maria Anderson | Q9: South | R9: Groceries | S9: In-Store | T9: Cash | U9: Pending | V9: 11 | W9: 205.14 | X9: 45493 | Y9: 0.05 | Z9: Gift wrap requested | AA9: High Value | AB9: 2256.54 | AC9: ORD-1027 | AD9: 1027 | AE9: Jul-2024 | AF9: 45504 | AG9: maria
A10: ORD-1027 | B10: July 20, 2024 | C10: MARIA ANDERSON | D10: South | E10: Karachi | F10: groceries | G10: Almonds 500g | H10: In-store | I10: 11 | J10: $205.14 | K10: 0.05 | L10: cash | M10: PENDING | N10: A. Malik | O10: Gift wrap requested | P10: Maria Anderson | Q10: South | R10: Groceries | S10: In-Store | T10: Cash | U10: Pending | V10: 11 | W10: 205.14 | X10: 45493 | Y10: 0.05 | Z10: Gift wrap requested | AA10: High Value | AB10: 2256.54 | AC10: ORD-1027 | AD10: 1027 | AE10: Jul-2024 | AF10: 45504 | AG10: maria
A11: ORD-1033 | B11: August 30, 2024 | C11: Grace Smith | D11: South | E11: Karachi | F11: groceries | G11: Almonds 500g | H11: instore | I11: 8 | J11: 51.06 | K11: 10% | L11: cash | M11: PENDING | N11: C. Osei | O11: Bulk order - business account | P11: Grace Smith | Q11: South | R11: Groceries | S11: In-Store | T11: Cash | U11: Pending | V11: 8 | W11: 51.06 | X11: 45534 | Y11: 10% | Z11: Bulk order - business account | AA11: Standard | AB11: 408.48 | AC11: ORD-1033 | AD11: 1033 | AE11: Aug-2024 | AF11: 45535 | AG11: Grace
A12: ORD-1032 | B12: May 23, 2024 | C12: olivia lewis | D12: EAST | E12: Multan | F12: groceries | G12: Almonds 500g | H12: In Store | J12: 426.22 | L12: Bank Transfer | M12: cancelled | N12: C. Osei | O12: Leave at front desk | P12: Olivia Lewis | Q12: East | R12: Groceries | S12: In-Store | T12: Bank Transfer | U12: Cancelled | W12: 426.22 | X12: 45435 | Y12: 0 | Z12: Leave at front desk | AA12: Review | AB12: 0 | AC12: ORD-1032 | AD12: 1032 | AE12: May-2024 | AF12: 45443 | AG12: OLIVIA
A13: ORD-1136 | B13: 2024-05-20 | C13: Nida Taylor | D13: north | E13: Islamabad | F13: groceries | G13: Basmati Rice 5kg | H13: Online | I13: 8 | J13: 495.96 | K13: 0.05 | L13: cash | M13: cancelled | N13: B. Fernandes | P13: Nida Taylor | Q13: North | R13: Groceries | S13: Online | T13: Cash | U13: Cancelled | V13: 8 | W13: 495.96 | X13: 45432 | Y13: 0.05 | AA13: High Value | AB13: 3967.68 | AC13: ORD-1136 | AD13: 1136 | AE13: May-2024 | AF13: 45443 | AG13: Nida
A14: ORD-1175 | B14: 03-Aug-24 | C14: Yusuf Sheikh | D14: EAST | E14: Multan | F14: groceries | G14: Green Tea Pack | H14: In-store | I14: 3 | J14: 450.3 | L14: Credit card | M14: Refunded | N14: C. Osei | P14: Yusuf Sheikh | Q14: East | R14: Groceries | S14: In-Store | T14: Credit Card | U14: Refunded | V14: 3 | W14: 450.3 | X14: 45507 | Y14: 0 | AA14: High Value | AB14: 1350.9 | AC14: ORD-1175 | AD14: 1175 | AE14: Aug-2024 | AF14: 45535 | AG14: Yusuf
A15: ORD-1164 | B15: 13-Feb-24 | C15: MICHAEL FAROOQ | D15: South | E15: Hyderabad | F15: groceries | G15: Green Tea Pack | H15: instore | I15: 8 | J15: 419.35 | L15: Bank Transfer | M15: PENDING | N15: A. Malik | O15: Bulk order - business account | P15: Michael Farooq | Q15: South | R15: Groceries | S15: In-Store | T15: Bank Transfer | U15: Pending | V15: 8 | W15: 419.35 | X15: 45335 | Y15: 0 | Z15: Bulk order - business account | AA15: High Value | AB15: 3354.8 | AC15: ORD-1164 | AD15: 1164 | AE15: Feb-2024 | AF15: 45351 | AG15: Michael
A16: ORD-1031 | B16: 02/10/2024 | C16: Grace Hussain | D16: EAST | F16: groceries | G16: Basmati Rice 5kg | H16: In Store | I16: 6 | J16: 415.21 | K16: 0.2 | L16: cash | M16: cancelled | N16: E. Tanaka | O16: Damaged on arrival - replaced | P16: Grace Hussain | Q16: East | R16: Groceries | S16: In-Store | T16: Cash | U16: Cancelled | V16: 6 | W16: 415.21 | X16: 45332 | Y16: 0.2 | Z16: Damaged on arrival - replaced | AA16: High Value | AB16: 2491.26 | AC16: ORD-1031 | AD16: 1031 | AE16: Feb-2024 | AF16: 45351 | AG16: Grace
A17: ORD-1092 | B17: 09-Nov-24 | C17: chen sheikh | D17: EAST | E17: Multan | F17: groceries | G17: Basmati Rice 5kg | H17: Online | I17: 3 | J17: 402.96 | L17: cash | M17: COMPLETED | N17: C. Osei | O17: Follow up needed | P17: Chen Sheikh | Q17: East | R17: Groceries | S17: Online | T17: Cash | U17: Completed | V17: 3 | W17: 402.96 | X17: 45605 | Y17: 0 | Z17: Follow up needed | AA17: High Value | AB17: 1208.88 | AC17: ORD-1092 | AD17: 1092 | AE17: Nov-2024 | AF17: 45626 | AG17: Chen
A18: ORD-1073 | B18: 11-Mar-24 | C18: daniel qureshi | D18: west | E18: Quetta | F18: groceries | G18: Green Tea Pack | H18: instore | I18: 8 | J18: 390.17 | K18: 0.05 | L18: Credit card | M18: Refunded | N18: E. Tanaka | O18: Gift wrap requested | P18: Daniel Qureshi | Q18: West | R18: Groceries | S18: In-Store | T18: Credit Card | U18: Refunded | V18: 8 | W18: 390.17 | X18: 45362 | Y18: 0.05 | Z18: Gift wrap requested | AA18: High Value | AB18: 3121.36 | AC18: ORD-1073 | AD18: 1073 | AE18: Mar-2024 | AF18: 45382 | AG18: daniel
A19: ORD-1104 | B19: 04-Aug-24 | C19: MICHAEL CLARK | D19: Nort | E19: Islamabad | F19: groceries | G19: Honey Jar | H19: instore | I19: 11 | J19: 363.02 | K19: 0.05 | L19: cash | M19: COMPLETED | N19: A. Malik | O19: Customer called twice | P19: Michael Clark | Q19: North | R19: Groceries | S19: In-Store | T19: Cash | U19: Completed | V19: 11 | W19: 363.02 | X19: 45508 | Y19: 0.05 | Z19: Customer called twice | AA19: High Value | AB19: 3993.22 | AC19: ORD-1104 | AD19: 1104 | AE19: Aug-2024 | AF19: 45535 | AG19: Michael
A20: ORD-1052 | B20: 2024-08-29 | C20: Daniel Johnson | D20: South | E20: Hyderabad | F20: groceries | G20: Green Tea Pack | H20: In-store | I20: 2 | J20: 338.05 | K20: 10% | L20: Credit card | M20: PENDING | N20: B. Fernandes | O20: Bulk order - business account | P20: Daniel Johnson | Q20: South | R20: Groceries | S20: In-Store | T20: Credit Card | U20: Pending | V20: 2 | W20: 338.05 | X20: 45533 | Y20: 10% | Z20: Bulk order - business account | AA20: Standard | AB20: 676.1 | AC20: ORD-1052 | AD20: 1052 | AE20: Aug-2024 | AF20: 45535 | AG20: daniel
A21: ORD-1011 | B21: 26/03/2024 | C21: Ahmed Garcia | D21: west | E21: Peshawar | F21: groceries | G21: Basmati Rice 5kg | H21: instore | I21: 9 | J21: 327.81 | L21: Credit card | M21: Refunded | N21: B. Fernandes | O21: Damaged on arrival - replaced | P21: Ahmed Garcia | Q21: West | R21: Groceries | S21: In-Store | T21: Credit Card | U21: Refunded | V21: 9 | W21: 327.81 | X21: 45377 | Y21: 0 | Z21: Damaged on arrival - replaced | AA21: High Value | AB21: 2950.29 | AC21: ORD-1011 | AD21: 1011 | AE21: Mar-2024 | AF21: 45382 | AG21: Ahmed
A22: ORD-1085 | B22: November 23, 2024 | C22: Daniel Farooq | D22: north | E22: Lahore | F22: groceries | G22: Almonds 500g | H22: Online | I22: 3 | J22: 322.96 | K22: 10% | L22: Credit card | M22: Refunded | N22: E. Tanaka | O22: Follow up needed | P22: Daniel Farooq | Q22: North | R22: Groceries | S22: Online | T22: Credit Card | U22: Refunded | V22: 3 | W22: 322.96 | X22: 45619 | Y22: 10% | Z22: Follow up needed | AA22: Standard | AB22: 968.88 | AC22: ORD-1085 | AD22: 1085 | AE22: Nov-2024 | AF22: 45626 | AG22: daniel
A23: ORD-1166 | B23: July 22, 2024 | C23: Emily Lee | D23: South | E23: Karachi | F23: groceries | G23: Almonds 500g | H23: Online | I23: 11 | J23: 299.55 | K23: 0 | L23: Credit card | M23: Canceled | N23: E. Tanaka | P23: Emily Lee | Q23: South | R23: Groceries | S23: Online | T23: Credit Card | U23: Cancelled | V23: 11 | W23: 299.55 | X23: 45495 | Y23: 0 | AA23: High Value | AB23: 3295.05 | AC23: ORD-1166 | AD23: 1166 | AE23: Jul-2024 | AF23: 45504 | AG23: EMILY
A24: ORD-1077 | B24: 23/01/2024 | C24: BILAL BROWN | D24: west | E24: Peshawar | F24: groceries | G24: Basmati Rice 5kg | H24: In-store | I24: 6 | J24: 265.4 | K24: 0.2 | L24: Credit card | M24: Canceled | N24: D. Iqbal | P24: Bilal Brown | Q24: West | R24: Groceries | S24: In-Store | T24: Credit Card | U24: Cancelled | V24: 6 | W24: 265.4 | X24: 45314 | Y24: 0.2 | AA24: High Value | AB24: 1592.4 | AC24: ORD-1077 | AD24: 1077 | AE24: Jan-2024 | AF24: 45322 | AG24: bilal
A25: ORD-1151 | B25: 2024-03-12 | C25: Ahmed Taylor | D25: north | E25: Islamabad | F25: groceries | G25: Green Tea Pack | H25: In-store | J25: 205.17 | K25: 0.05 | L25: Credit card | M25: cancelled | N25: A. Malik | O25: Gift wrap requested | P25: Ahmed Taylor | Q25: North | R25: Groceries | S25: In-Store | T25: Credit Card | U25: Cancelled | W25: 205.17 | X25: 45363 | Y25: 0.05 | Z25: Gift wrap requested | AA25: Review | AB25: 0 | AC25: ORD-1151 | AD25: 1151 | AE25: Mar-2024 | AF25: 45382 | AG25: Ahmed
A26: ORD-1132 | B26: April 17, 2024 | C26: UMAR FAROOQ | D26: north | E26: Lahore | F26: groceries | G26: Olive Oil 1L | H26: In-store | I26: 1 | J26: 177.55 | K26: 0 | L26: Bank Transfer | M26: Refunded | N26: B. Fernandes | P26: Umar Farooq | Q26: North | R26: Groceries | S26: In-Store | T26: Bank Transfer | U26: Refunded | V26: 1 | W26: 177.55 | X26: 45399 | Y26: 0 | AA26: Standard | AB26: 177.55 | AC26: ORD-1132 | AD26: 1132 | AE26: Apr-2024 | AF26: 45412 | AG26: UMAR
A27: ORD-1106 | B27: August 02, 2024 | C27: Chen Clark | D27: South | E27: Karachi | F27: groceries | G27: Honey Jar | H27: In Store | I27: 4 | J27: 176.35 | K27: 0 | L27: Credit card | M27: Refunded | O27: Gift wrap requested | P27: Chen Clark | Q27: South | R27: Groceries | S27: In-Store | T27: Credit Card | U27: Refunded | V27: 4 | W27: 176.35 | X27: 45506 | Y27: 0 | Z27: Gift wrap requested | AA27: Standard | AB27: 705.4 | AC27: ORD-1106 | AD27: 1106 | AE27: Aug-2024 | AF27: 45535 | AG27: Chen
A28: ORD-1210 | B28: 03/25/2024 | C28: NOAH MALIK | D28: west | E28: Quetta | F28: groceries | G28: Honey Jar | H28: In Store | I28: 6 | J28: 175.79 | K28: 0 | L28: cash | M28: COMPLETED | N28: D. Iqbal | O28: Customer called twice | P28: Noah Malik | Q28: West | R28: Groceries | S28: In-Store | T28: Cash | U28: Completed | V28: 6 | W28: 175.79 | X28: 45376 | Y28: 0 | Z28: Customer called twice | AA28: High Value | AB28: 1054.74 | AC28: ORD-1210 | AD28: 1210 | AE28: Mar-2024 | AF28: 45382 | AG28: Noah
A29: ORD-1122 | B29: 20/11/2024 | C29: MARIA SMITH | D29: East | E29: Sialkot | F29: groceries | G29: Green Tea Pack | H29: In-store | I29: 10 | J29: 104.42 | K29: 0.1 | L29: CC | M29: Refunded | O29: VIP customer | P29: Maria Smith | Q29: East | R29: Groceries | S29: In-Store | T29: Credit Card | U29: Refunded | V29: 10 | W29: 104.42 | X29: 45616 | Y29: 0.1 | Z29: VIP customer | AA29: High Value | AB29: 1044.2 | AC29: ORD-1122 | AD29: 1122 | AE29: Nov-2024 | AF29: 45626 | AG29: maria
A30: ORD-1122 | B30: 20/11/2024 | C30: MARIA SMITH | D30: East | E30: Sialkot | F30: groceries | G30: Green Tea Pack | H30: In-store | I30: 10 | J30: 104.42 | K30: 0.1 | L30: CC | M30: Refunded | O30: VIP customer | P30: Maria Smith | Q30: East | R30: Groceries | S30: In-Store | T30: Credit Card | U30: Refunded | V30: 10 | W30: 104.42 | X30: 45616 | Y30: 0.1 | Z30: VIP customer | AA30: High Value | AB30: 1044.2 | AC30: ORD-1122 | AD30: 1122 | AE30: Nov-2024 | AF30: 45626 | AG30: maria
A31: ORD-1190 | B31: 2024-06-22 | C31: Fatima Raza | D31: EAST | E31: Multan | F31: groceries | G31: Almonds 500g | H31: Online | I31: 5 | J31: 97.83 | K31: 0.15 | L31: Bank Transfer | M31: Complete | P31: Fatima Raza | Q31: East | R31: Groceries | S31: Online | T31: Bank Transfer | U31: Completed | V31: 5 | W31: 97.83 | X31: 45465 | Y31: 0.15 | AA31: Standard | AB31: 489.15 | AC31: ORD-1190 | AD31: 1190 | AE31: Jun-2024 | AF31: 45473 | AG31: Fatima
A32: ORD-1206 | B32: 2024-11-16 | C32: Bilal Hussain | D32: EAST | E32: Sialkot | F32: groceries | G32: Green Tea Pack | H32: In-store | I32: 8 | J32: 92.01 | K32: 0.05 | L32: cash | M32: Complete | N32: C. Osei | O32: Customer called twice | P32: Bilal Hussain | Q32: East | R32: Groceries | S32: In-Store | T32: Cash | U32: Completed | V32: 8 | W32: 92.01 | X32: 45612 | Y32: 0.05 | Z32: Customer called twice | AA32: Standard | AB32: 736.08 | AC32: ORD-1206 | AD32: 1206 | AE32: Nov-2024 | AF32: 45626 | AG32: bilal
A33: ORD-1129 | B33: 17/07/2024 | C33: Tom Taylor | D33: west | E33: Quetta | F33: groceries | G33: Green Tea Pack | H33: Online | I33: 11 | J33: 63.34 | L33: Bank Transfer | M33: COMPLETED | N33: E. Tanaka | O33: Follow up needed | P33: Tom Taylor | Q33: West | R33: Groceries | S33: Online | T33: Bank Transfer | U33: Completed | V33: 11 | W33: 63.34 | X33: 45490 | Y33: 0 | Z33: Follow up needed | AA33: Standard | AB33: 696.74 | AC33: ORD-1129 | AD33: 1129 | AE33: Jul-2024 | AF33: 45504 | AG33: tom
A34: ORD-1181 | B34: 2024-11-12 | C34: BILAL ALI | D34: west | E34: Quetta | F34: groceries | G34: Olive Oil 1L | H34: Online | I34: 5 | J34: 54.99 | K34: 5% | L34: debit card | M34: COMPLETED | N34: E. Tanaka | O34: Leave at front desk | P34: Bilal Ali | Q34: West | R34: Groceries | S34: Online | T34: Debit Card | U34: Completed | V34: 5 | W34: 54.99 | X34: 45608 | Y34: 5% | Z34: Leave at front desk | AA34: Standard | AB34: 274.95 | AC34: ORD-1181 | AD34: 1181 | AE34: Nov-2024 | AF34: 45626 | AG34: bilal
A35: ORD-1090 | B35: 25/02/2024 | C35: AISHA CLARK | D35: west | F35: groceries | G35: Olive Oil 1L | H35: Online | I35: 10 | J35: 30.02 | K35: 0.15 | L35: CC | M35: PENDING | N35: A. Malik | O35: Follow up needed | P35: Aisha Clark | Q35: West | R35: Groceries | S35: Online | T35: Credit Card | U35: Pending | V35: 10 | W35: 30.02 | X35: 45347 | Y35: 0.15 | Z35: Follow up needed | AA35: Standard | AB35: 300.2 | AC35: ORD-1090 | AD35: 1090 | AE35: Feb-2024 | AF35: 45351 | AG35: Aisha
A36: ORD-1188 | B36: November 05, 2024 | C36: Kate Ahmed | D36: west | E36: Peshawar | F36: groceries | G36: Green Tea Pack | H36: Online | I36: 8 | J36: 13.8 | L36: cash | M36: COMPLETED | N36: A. Malik | O36: Leave at front desk | P36: Kate Ahmed | Q36: West | R36: Groceries | S36: Online | T36: Cash | U36: Completed | V36: 8 | W36: 13.8 | X36: 45601 | Y36: 0 | Z36: Leave at front desk | AA36: Standard | AB36: 110.4 | AC36: ORD-1188 | AD36: 1188 | AE36: Nov-2024 | AF36: 45626 | AG36: Kate
A37: ORD-1119 | B37: 05/04/2024 | C37: michael qureshi | D37: South | E37: Karachi | F37: groceries | G37: Almonds 500g | H37: In-store | I37: 6 | J37: 7.57 | K37: 0.1 | L37: Credit card | M37: COMPLETED | N37: A. Malik | O37: Damaged on arrival - replaced | P37: Michael Qureshi | Q37: South | R37: Groceries | S37: In-Store | T37: Credit Card | U37: Completed | V37: 6 | W37: 7.57 | X37: 45416 | Y37: 0.1 | Z37: Damaged on arrival - replaced | AA37: Standard | AB37: 45.42 | AC37: ORD-1119 | AD37: 1119 | AE37: May-2024 | AF37: 45443 | AG37: Michael
A38: ORD-1135 | B38: 10/22/2024 | C38: Aisha Tayloris | D38: north | E38: Islamabad | F38: Grocery | G38: Basmati Rice 5kg | H38: In-store | I38: 7 | J38: 217.67 | L38: CC | M38: cancelled | N38: E. Tanaka | O38: Damaged on arrival - replaced | P38: Aisha Tayloris | Q38: North | R38: Groceries | S38: In-Store | T38: Credit Card | U38: Cancelled | V38: 7 | W38: 217.67 | X38: 45587 | Y38: 0 | Z38: Damaged on arrival - replaced | AA38: High Value | AB38: 1523.69 | AC38: ORD-1135 | AD38: 1135 | AE38: Oct-2024 | AF38: 45596 | AG38: Aisha
A39: ORD-1135 | B39: 10/22/2024 | C39: AISHA TAYLOR | D39: north | E39: Islamabad | F39: Grocery | G39: Basmati Rice 5kg | H39: In-store | I39: 7 | J39: 217.67 | L39: CC | M39: cancelled | N39: E. Tanaka | O39: Damaged on arrival - replaced | P39: Aisha Taylor | Q39: North | R39: Groceries | S39: In-Store | T39: Credit Card | U39: Cancelled | V39: 7 | W39: 217.67 | X39: 45587 | Y39: 0 | Z39: Damaged on arrival - replaced | AA39: High Value | AB39: 1523.69 | AC39: ORD-1135 | AD39: 1135 | AE39: Oct-2024 | AF39: 45596 | AG39: Aisha
A40: ORD-1229 | B40: 06/24/2024 | C40: priya raza | D40: East | E40: Sialkot | F40: Grocery | G40: Almonds 500g | H40: Online | I40: 3 | J40: 464.64 | K40: 15% | L40: Credit card | M40: COMPLETED | N40: B. Fernandes | P40: Priya Raza | Q40: East | R40: Groceries | S40: Online | T40: Credit Card | U40: Completed | V40: 3 | W40: 464.64 | X40: 45467 | Y40: 15% | AA40: High Value | AB40: 1393.92 | AC40: ORD-1229 | AD40: 1229 | AE40: Jun-2024 | AF40: 45473 | AG40: Priya
A41: ORD-1012 | B41: 2024-04-21 | C41: AISHA GARCIA | D41: north | F41: Grocery | G41: Almonds 500g | H41: In-store | I41: 7 | J41: 366.6 | K41: 15% | L41: Credit card | M41: Complete | N41: C. Osei | O41: Bulk order - business account | P41: Aisha Garcia | Q41: North | R41: Groceries | S41: In-Store | T41: Credit Card | U41: Completed | V41: 7 | W41: 366.6 | X41: 45403 | Y41: 15% | Z41: Bulk order - business account | AA41: High Value | AB41: 2566.2 | AC41: ORD-1012 | AD41: 1012 | AE41: Apr-2024 | AF41: 45412 | AG41: Aisha
A42: ORD-1155 | B42: 17-Jul-24 | C42: Robert Qureshi | D42: north | E42: Islamabad | F42: Grocery | G42: Honey Jar | H42: Online | I42: 3 | J42: 330.15 | K42: 0 | L42: Bank Transfer | M42: Complete | N42: E. Tanaka | O42: Follow up needed | P42: Robert Qureshi | Q42: North | R42: Groceries | S42: Online | T42: Bank Transfer | U42: Completed | V42: 3 | W42: 330.15 | X42: 45490 | Y42: 0 | Z42: Follow up needed | AA42: Standard | AB42: 990.45 | AC42: ORD-1155 | AD42: 1155 | AE42: Jul-2024 | AF42: 45504 | AG42: Robert
A43: ORD-1130 | B43: October 14, 2024 | C43: Noah Anderson | D43: South | E43: Karachi | F43: Grocery | G43: Olive Oil 1L | H43: Online | I43: 6 | J43: 311.61 | K43: 0.15 | L43: Credit card | M43: Complete | N43: D. Iqbal | O43: Damaged on arrival - replaced | P43: Noah Anderson | Q43: South | R43: Groceries | S43: Online | T43: Credit Card | U43: Completed | V43: 6 | W43: 311.61 | X43: 45579 | Y43: 0.15 | Z43: Damaged on arrival - replaced | AA43: High Value | AB43: 1869.66 | AC43: ORD-1130 | AD43: 1130 | AE43: Oct-2024 | AF43: 45596 | AG43: Noah
A44: ORD-1158 | B44: 18-Dec-24 | C44: Robert Raza | D44: South | E44: Hyderabad | F44: Grocery | G44: Olive Oil 1L | H44: In-store | I44: 12 | J44: 308.79 | K44: 5% | L44: debit card | M44: cancelled | O44: Follow up needed | P44: Robert Raza | Q44: South | R44: Groceries | S44: In-Store | T44: Debit Card | U44: Cancelled | V44: 12 | W44: 308.79 | X44: 45644 | Y44: 5% | Z44: Follow up needed | AA44: High Value | AB44: 3705.48 | AC44: ORD-1158 | AD44: 1158 | AE44: Dec-2024 | AF44: 45657 | AG44: Robert
A45: ORD-1205 | B45: 06/09/2024 | C45: Hina Ahmed | D45: EAST | E45: Multan | F45: Grocery | G45: Honey Jar | H45: In-store | I45: 12 | J45: 284.95 | L45: debit card | M45: COMPLETED | N45: A. Malik | O45: VIP customer | P45: Hina Ahmed | Q45: East | R45: Groceries | S45: In-Store | T45: Debit Card | U45: Completed | V45: 12 | W45: 284.95 | X45: 45452 | Y45: 0 | Z45: VIP customer | AA45: High Value | AB45: 3419.4 | AC45: ORD-1205 | AD45: 1205 | AE45: Jun-2024 | AF45: 45473 | AG45: HINA
A46: ORD-1088 | B46: 12-Jun-24 | C46: aisha farooq | D46: East | E46: Multan | F46: Grocery | G46: Almonds 500g | H46: Online | J46: 222.6 | L46: cash | M46: COMPLETED | N46: C. Osei | P46: Aisha Farooq | Q46: East | R46: Groceries | S46: Online | T46: Cash | U46: Completed | W46: 222.6 | X46: 45455 | Y46: 0 | AA46: Review | AB46: 0 | AC46: ORD-1088 | AD46: 1088 | AE46: Jun-2024 | AF46: 45473 | AG46: Aisha
A47: ORD-1121 | B47: 2024-08-22 | C47: david wilson | D47: East | E47: Multan | F47: Grocery | G47: Almonds 500g | H47: In-store | I47: 8 | J47: 183.76 | K47: 0.15 | L47: cash | M47: PENDING | N47: B. Fernandes | O47: Follow up needed | P47: David Wilson | Q47: East | R47: Groceries | S47: In-Store | T47: Cash | U47: Pending | V47: 8 | W47: 183.76 | X47: 45526 | Y47: 0.15 | Z47: Follow up needed | AA47: High Value | AB47: 1470.08 | AC47: ORD-1121 | AD47: 1121 | AE47: Aug-2024 | AF47: 45535 | AG47: David
A48: ORD-1041 | B48: 04/10/2024 | C48: Fatima Hussain | D48: EAST | E48: Multan | F48: Grocery | G48: Almonds 500g | H48: In-store | I48: 1 | J48: 160.69 | K48: 0.15 | L48: cash | M48: COMPLETED | P48: Fatima Hussain | Q48: East | R48: Groceries | S48: In-Store | T48: Cash | U48: Completed | V48: 1 | W48: 160.69 | X48: 45392 | Y48: 0.15 | AA48: Standard | AB48: 160.69 | AC48: ORD-1041 | AD48: 1041 | AE48: Apr-2024 | AF48: 45412 | AG48: Fatima
A49: ORD-1100 | B49: August 06, 2024 | C49: LIAM CLARK | D49: EAST | E49: Multan | F49: Grocery | G49: Olive Oil 1L | H49: Online | I49: 12 | J49: 151.04 | L49: cash | M49: PENDING | N49: D. Iqbal | P49: Liam Clark | Q49: East | R49: Groceries | S49: Online | T49: Cash | U49: Pending | V49: 12 | W49: 151.04 | X49: 45510 | Y49: 0 | AA49: High Value | AB49: 1812.48 | AC49: ORD-1100 | AD49: 1100 | AE49: Aug-2024 | AF49: 45535 | AG49: Liam
A50: ORD-1125 | B50: 19/07/2024 | C50: Emily Ahmed | D50: EAST | E50: Multan | F50: Grocery | G50: Almonds 500g | H50: Online | I50: 1 | J50: 114.89 | K50: 20% | L50: Credit card | M50: cancelled | N50: C. Osei | O50: Bulk order - business account | P50: Emily Ahmed | Q50: East | R50: Groceries | S50: Online | T50: Credit Card | U50: Cancelled | V50: 1 | W50: 114.89 | X50: 45492 | Y50: 20% | Z50: Bulk order - business account | AA50: Standard | AB50: 114.89 | AC50: ORD-1125 | AD50: 1125 | AE50: Jul-2024 | AF50: 45504 | AG50: EMILY
A51: ORD-1037 | B51: 05/02/2024 | C51: UMAR CLARK | D51: west | E51: Peshawar | F51: Grocery | G51: Honey Jar | H51: Online | I51: 10 | J51: 54.12 | K51: 10% | L51: cash | M51: COMPLETED | N51: B. Fernandes | O51: Bulk order - business account | P51: Umar Clark | Q51: West | R51: Groceries | S51: Online | T51: Cash | U51: Completed | V51: 10 | W51: 54.12 | X51: 45414 | Y51: 10% | Z51: Bulk order - business account | AA51: Standard | AB51: 541.2 | AC51: ORD-1037 | AD51: 1037 | AE51: May-2024 | AF51: 45443 | AG51: UMAR
A52: ORD-1174 | B52: April 23, 2024 | C52: Kevin Ahmed | D52: west | E52: Quetta | F52: Grocery | G52: Green Tea Pack | H52: In Store | I52: 7 | J52: 22.48 | K52: 5% | L52: debit card | M52: Refunded | O52: Damaged on arrival - replaced | P52: Kevin Ahmed | Q52: West | R52: Groceries | S52: In-Store | T52: Debit Card | U52: Refunded | V52: 7 | W52: 22.48 | X52: 45405 | Y52: 5% | Z52: Damaged on arrival - replaced | AA52: Standard | AB52: 157.36 | AC52: ORD-1174 | AD52: 1174 | AE52: Apr-2024 | AF52: 45412 | AG52: Kevin

Sheet Pivot_RevenueByCategory
A3: Sum of Revenue | B3: Column Labels
A4: Row Labels | B4: In-Store | C4: Online
A5: Furniture | B5: 33823.73 | C5: 53959.13
A6: Clothing | B6: 50919.96 | C6: 29750.89
A7: Stationery | B7: 35566.63 | C7: 37437.71
A8: Groceries | B8: 45323.09 | C8: 24164.61
A9: Electronics | B9: 52611.52 | C9: 16397.65
A10: Grand Total | B10: 218244.93 | C10: 161709.99

Sheet Pivot_RegionSummary
A3: Row Labels | B3: Order Count | C3: Average Order Value
A4: East | B4: 72 | C4: 1702.2501
A5: North | B5: 58 | C5: 1405.2457
A6: South | B6: 52 | C6: 1796.5035
A7: West | B7: 62 | C7: 1330.169
A8: Grand Total | B8: 244 | C8: 1557.1923

Sheet Pivot_PaymentMethod
A1: OrderStatus_Cleaned | B1: Completed
A3: Row Labels | B3: Sum of Revenue
A4: CREDIT CARD | B4: 31328.87
A5: cash | B5: 28938.38
A6: debit card | B6: 19855.3
A7: Cash | B7: 14903.96
A8: Bank Transfer | B8: 13382.45
A9: CC | B9: 10555.29
A10: Credit card | B10: 6195.98
A11: Grand Total | B11: 125160.23

Sheet Pivot_MonthlyTrend
A3: Row Labels | B3: Sum of Revenue | C3: OrderCount
A4: 2024 | B4: 379954.92 | C4: 244
A5: Jan | B5: 17245.77 | C5: 10
A6: Feb | B6: 31669.22 | C6: 17
A7: Mar | B7: 40626.09 | C7: 23
A8: Apr | B8: 24408.01 | C8: 20
A9: May | B9: 26801.61 | C9: 24
A10: Jun | B10: 32460.67 | C10: 22
A11: Jul | B11: 42306.64 | C11: 23
A12: Aug | B12: 60793.1 | C12: 28
A13: Sep | B13: 24267.75 | C13: 14
A14: Oct | B14: 24898.75 | C14: 23
A15: Nov | B15: 15474.37 | C15: 16
... A17: Grand Total | B17: 379954.92 | C17: 244

Sheet Sparklines_Practice
A1: SalesRep | B1: 45292 | C1: 45323 | D1: 45352 | E1: 45383 | F1: 45413 | G1: 45444 | H1: 45474 | I1: 45505 | J1: 45536 | K1: 45566 | L1: 45597 | M1: 45627 | N1: Trend
A2: {=_xlfn._xlws.SORT(_xlfn.UNIQUE(_xlfn._xlws.FILTER(tblOrders[SalesRep],tblOrders[SalesRep]<>"")))} -> A. Malik | B2: =SUMIFS(Orders_Raw!$AB$2:$AB$245,Orders_Raw!$N$2:$N$245,$A2,Orders_Raw!$AE$2:$AE$245,TEXT(B$1,"mmm-yyyy")) -> 1381.65 | C2: =SUMIFS(Orders_Raw!$AB$2:$AB$245,Orders_Raw!$N$2:$N$245,$A2,Orders_Raw!$AE$2:$AE$245,TEXT(C$1,"mmm-yyyy")) -> 9588.01 | D2: =SUMIFS(Orders_Raw!$AB$2:$AB$245,Orders_Raw!$N$2:$N$245,$A2,Orders_Raw!$AE$2:$AE$245,TEXT(D$1,"mmm-yyyy")) -> 9914.5 | E2: =SUMIFS(Orders_Raw!$AB$2:$AB$245,Orders_Raw!$N$2:$N$245,$A2,Orders_Raw!$AE$2:$AE$245,TEXT(E$1,"mmm-yyyy")) -> 0 | F2: =SUMIFS(Orders_Raw!$AB$2:$AB$245,Orders_Raw!$N$2:$N$245,$A2,Orders_Raw!$AE$2:$AE$245,TEXT(F$1,"mmm-yyyy")) -> 5807.2 | G2: =SUMIFS(Orders_Raw!$AB$2:$AB$245,Orders_Raw!$N$2:$N$245,$A2,Orders_Raw!$AE$2:$AE$245,TEXT(G$1,"mmm-yyyy")) -> 5442.18 | H2: =SUMIFS(Orders_Raw!$AB$2:$AB$245,Orders_Raw!$N$2:$N$245,$A2,Orders_Raw!$AE$2:$AE$245,TEXT(H$1,"mmm-yyyy")) -> 10755.06 | I2: =SUMIFS(Orders_Raw!$AB$2:$AB$245,Orders_Raw!$N$2:$N$245,$A2,Orders_Raw!$AE$2:$AE$245,TEXT(I$1,"mmm-yyyy")) -> 5151.58 | ... M2: =SUMIFS(Orders_Raw!$AB$2:$AB$245,Orders_Raw!$N$2:$N$245,$A2,Orders_Raw!$AE$2:$AE$245,TEXT(M$1,"mmm-yyyy")) -> 2232
A3: B. Fernandes | B3: =SUMIFS(Orders_Raw!$AB$2:$AB$245,Orders_Raw!$N$2:$N$245,$A3,Orders_Raw!$AE$2:$AE$245,TEXT(B$1,"mmm-yyyy")) -> 4630.91 | C3: =SUMIFS(Orders_Raw!$AB$2:$AB$245,Orders_Raw!$N$2:$N$245,$A3,Orders_Raw!$AE$2:$AE$245,TEXT(C$1,"mmm-yyyy")) -> 2023.26 | D3: =SUMIFS(Orders_Raw!$AB$2:$AB$245,Orders_Raw!$N$2:$N$245,$A3,Orders_Raw!$AE$2:$AE$245,TEXT(D$1,"mmm-yyyy")) -> 9445.6 | E3: =SUMIFS(Orders_Raw!$AB$2:$AB$245,Orders_Raw!$N$2:$N$245,$A3,Orders_Raw!$AE$2:$AE$245,TEXT(E$1,"mmm-yyyy")) -> 4572.05 | F3: =SUMIFS(Orders_Raw!$AB$2:$AB$245,Orders_Raw!$N$2:$N$245,$A3,Orders_Raw!$AE$2:$AE$245,TEXT(F$1,"mmm-yyyy")) -> 10664.14 | G3: =SUMIFS(Orders_Raw!$AB$2:$AB$245,Orders_Raw!$N$2:$N$245,$A3,Orders_Raw!$AE$2:$AE$245,TEXT(G$1,"mmm-yyyy")) -> 1393.92 | H3: =SUMIFS(Orders_Raw!$AB$2:$AB$245,Orders_Raw!$N$2:$N$245,$A3,Orders_Raw!$AE$2:$AE$245,TEXT(H$1,"mmm-yyyy")) -> 1767.5 | I3: =SUMIFS(Orders_Raw!$AB$2:$AB$245,Orders_Raw!$N$2:$N$245,$A3,Orders_Raw!$AE$2:$AE$245,TEXT(I$1,"mmm-yyyy")) -> 2541.45 | ... M3: =SUMIFS(Orders_Raw!$AB$2:$AB$245,Orders_Raw!$N$2:$N$245,$A3,Orders_Raw!$AE$2:$AE$245,TEXT(M$1,"mmm-yyyy")) -> 3953.16
A4: C. Osei | B4: =SUMIFS(Orders_Raw!$AB$2:$AB$245,Orders_Raw!$N$2:$N$245,$A4,Orders_Raw!$AE$2:$AE$245,TEXT(B$1,"mmm-yyyy")) -> 0 | C4: =SUMIFS(Orders_Raw!$AB$2:$AB$245,Orders_Raw!$N$2:$N$245,$A4,Orders_Raw!$AE$2:$AE$245,TEXT(C$1,"mmm-yyyy")) -> 1950.03 | D4: =SUMIFS(Orders_Raw!$AB$2:$AB$245,Orders_Raw!$N$2:$N$245,$A4,Orders_Raw!$AE$2:$AE$245,TEXT(D$1,"mmm-yyyy")) -> 7267.12 | E4: =SUMIFS(Orders_Raw!$AB$2:$AB$245,Orders_Raw!$N$2:$N$245,$A4,Orders_Raw!$AE$2:$AE$245,TEXT(E$1,"mmm-yyyy")) -> 7615.4 | F4: =SUMIFS(Orders_Raw!$AB$2:$AB$245,Orders_Raw!$N$2:$N$245,$A4,Orders_Raw!$AE$2:$AE$245,TEXT(F$1,"mmm-yyyy")) -> 583.64 | G4: =SUMIFS(Orders_Raw!$AB$2:$AB$245,Orders_Raw!$N$2:$N$245,$A4,Orders_Raw!$AE$2:$AE$245,TEXT(G$1,"mmm-yyyy")) -> 1963.2 | H4: =SUMIFS(Orders_Raw!$AB$2:$AB$245,Orders_Raw!$N$2:$N$245,$A4,Orders_Raw!$AE$2:$AE$245,TEXT(H$1,"mmm-yyyy")) -> 4404.68 | I4: =SUMIFS(Orders_Raw!$AB$2:$AB$245,Orders_Raw!$N$2:$N$245,$A4,Orders_Raw!$AE$2:$AE$245,TEXT(I$1,"mmm-yyyy")) -> 20851.11 | ... M4: =SUMIFS(Orders_Raw!$AB$2:$AB$245,Orders_Raw!$N$2:$N$245,$A4,Orders_Raw!$AE$2:$AE$245,TEXT(M$1,"mmm-yyyy")) -> 8104.84
A5: D. Iqbal | B5: =SUMIFS(Orders_Raw!$AB$2:$AB$245,Orders_Raw!$N$2:$N$245,$A5,Orders_Raw!$AE$2:$AE$245,TEXT(B$1,"mmm-yyyy")) -> 3509.43 | C5: =SUMIFS(Orders_Raw!$AB$2:$AB$245,Orders_Raw!$N$2:$N$245,$A5,Orders_Raw!$AE$2:$AE$245,TEXT(C$1,"mmm-yyyy")) -> 4329.61 | D5: =SUMIFS(Orders_Raw!$AB$2:$AB$245,Orders_Raw!$N$2:$N$245,$A5,Orders_Raw!$AE$2:$AE$245,TEXT(D$1,"mmm-yyyy")) -> 5993.34 | E5: =SUMIFS(Orders_Raw!$AB$2:$AB$245,Orders_Raw!$N$2:$N$245,$A5,Orders_Raw!$AE$2:$AE$245,TEXT(E$1,"mmm-yyyy")) -> 1896.03 | F5: =SUMIFS(Orders_Raw!$AB$2:$AB$245,Orders_Raw!$N$2:$N$245,$A5,Orders_Raw!$AE$2:$AE$245,TEXT(F$1,"mmm-yyyy")) -> 4217.37 | G5: =SUMIFS(Orders_Raw!$AB$2:$AB$245,Orders_Raw!$N$2:$N$245,$A5,Orders_Raw!$AE$2:$AE$245,TEXT(G$1,"mmm-yyyy")) -> 6663.1 | H5: =SUMIFS(Orders_Raw!$AB$2:$AB$245,Orders_Raw!$N$2:$N$245,$A5,Orders_Raw!$AE$2:$AE$245,TEXT(H$1,"mmm-yyyy")) -> 5673.96 | I5: =SUMIFS(Orders_Raw!$AB$2:$AB$245,Orders_Raw!$N$2:$N$245,$A5,Orders_Raw!$AE$2:$AE$245,TEXT(I$1,"mmm-yyyy")) -> 7491.19 | ... M5: =SUMIFS(Orders_Raw!$AB$2:$AB$245,Orders_Raw!$N$2:$N$245,$A5,Orders_Raw!$AE$2:$AE$245,TEXT(M$1,"mmm-yyyy")) -> 7976.01
A6: E. Tanaka | B6: =SUMIFS(Orders_Raw!$AB$2:$AB$245,Orders_Raw!$N$2:$N$245,$A6,Orders_Raw!$AE$2:$AE$245,TEXT(B$1,"mmm-yyyy")) -> 7723.78 | C6: =SUMIFS(Orders_Raw!$AB$2:$AB$245,Orders_Raw!$N$2:$N$245,$A6,Orders_Raw!$AE$2:$AE$245,TEXT(C$1,"mmm-yyyy")) -> 4282.38 | D6: =SUMIFS(Orders_Raw!$AB$2:$AB$245,Orders_Raw!$N$2:$N$245,$A6,Orders_Raw!$AE$2:$AE$245,TEXT(D$1,"mmm-yyyy")) -> 6252.38 | E6: =SUMIFS(Orders_Raw!$AB$2:$AB$245,Orders_Raw!$N$2:$N$245,$A6,Orders_Raw!$AE$2:$AE$245,TEXT(E$1,"mmm-yyyy")) -> 4045.13 | F6: =SUMIFS(Orders_Raw!$AB$2:$AB$245,Orders_Raw!$N$2:$N$245,$A6,Orders_Raw!$AE$2:$AE$245,TEXT(F$1,"mmm-yyyy")) -> 4209.77 | G6: =SUMIFS(Orders_Raw!$AB$2:$AB$245,Orders_Raw!$N$2:$N$245,$A6,Orders_Raw!$AE$2:$AE$245,TEXT(G$1,"mmm-yyyy")) -> 11035.68 | H6: =SUMIFS(Orders_Raw!$AB$2:$AB$245,Orders_Raw!$N$2:$N$245,$A6,Orders_Raw!$AE$2:$AE$245,TEXT(H$1,"mmm-yyyy")) -> 10756.58 | I6: =SUMIFS(Orders_Raw!$AB$2:$AB$245,Orders_Raw!$N$2:$N$245,$A6,Orders_Raw!$AE$2:$AE$245,TEXT(I$1,"mmm-yyyy")) -> 9685.67 | ... M6: =SUMIFS(Orders_Raw!$AB$2:$AB$245,Orders_Raw!$N$2:$N$245,$A6,Orders_Raw!$AE$2:$AE$245,TEXT(M$1,"mmm-yyyy")) -> 7998.78
J15: =COUNTIFS(tblOrders[SalesRep],$A2,tblOrders[MonthLabel],B$1) -> 1

Sheet Pivot_AvgDiscount
A3: Row Labels | B3: Average of Discount_Clean
A4: Stationery | B4: 0.060869565
A5: Furniture | B5: 0.059302326
A6: Electronics | B6: 0.05625
A7: Groceries | B7: 0.052631579
A8: Clothing | B8: 0.04893617
A9: Grand Total | B9: 0.055582524

Sheet Pivot_SalesRepCount
A1: OrderStatus_Cleaned | B1: (Multiple Items)
A3: Row Labels | B3: Count of OrderID
A4: A. Malik | B4: 31
A5: B. Fernandes | B5: 29
A6: C. Osei | B6: 32
A7: D. Iqbal | B7: 27
A8: E. Tanaka | B8: 35
A9: (blank) | B9: 26
A10: Grand Total | B10: 180

Sheet Pivot_RegionCategory
A3: Row Labels | B3: Sum of Revenue
A4: East | B4: 122562.01
A5: Clothing | B5: 48513.41
A6: Electronics | B6: 18793.25
A7: Furniture | B7: 11400.92
A8: Groceries | B8: 20535.17
A9: Stationery | B9: 23319.26
A10: North | B10: 81504.25
A11: Clothing | B11: 10126.17
A12: Electronics | B12: 21763.41
A13: Furniture | B13: 16882.46
A14: Groceries | B14: 17248.38
A15: Stationery | B15: 15483.83
... A28: Grand Total | B28: 379954.92

Sheet Sheet1
A1: Region_Clean | B1: (All)
A3: Row Labels | B3: Sum of Revenue
A4: In-Store | B4: 218244.93
A5: Online | B5: 161709.99
A6: Grand Total | B6: 379954.92

Sheet Pivot_SalesRepRevenue
A3: Row Labels | B3: Sum of Revenue
A4: E. Tanaka | B4: 76962.02
A5: (blank) | B5: 70422.16
A6: C. Osei | B6: 65661.72
A7: A. Malik | B7: 61591.62
A8: D. Iqbal | B8: 58939.54
A9: B. Fernandes | B9: 46377.86
A10: Grand Total | B10: 379954.92

Sheet Pivot_StatusCount
A1: Channel_Clean | B1: Online
A3: Row Labels | B3: Count of OrderID
A4: Cancelled | B4: 22
A5: Completed | B5: 35
A6: Pending | B6: 27
A7: Refunded | B7: 20
A8: Grand Total | B8: 104

Sheet Pivot_RevenueDiscount
A3: Row Labels | B3: Sum of Revenue | C3: Average of Discount_Numeric
A4: In-Store | B4: 218244.93 | C4: 0.061071429
A5: Online | B5: 161709.99 | C5: 0.069711538
A6: Grand Total | B6: 379954.92 | C6: 0.064754098

Sheet Category_Sparklines
A1: Category | B1: 45292 | C1: 45323 | D1: 45352 | E1: 45383 | F1: 45413 | G1: 45444 | H1: 45474 | I1: 45505 | J1: 45536 | K1: 45566 | L1: 45597 | M1: 45627 | N1: Trend
A2: Electronics | B2: =SUMIFS(Orders_Raw!$AB$2:$AB$245,Orders_Raw!$R$2:$R$245,$A2,Orders_Raw!$AE$2:$AE$245,B$1) -> 4818.3 | C2: =SUMIFS(Orders_Raw!$AB$2:$AB$245,Orders_Raw!$R$2:$R$245,$A2,Orders_Raw!$AE$2:$AE$245,C$1) -> 7378.98 | D2: =SUMIFS(Orders_Raw!$AB$2:$AB$245,Orders_Raw!$R$2:$R$245,$A2,Orders_Raw!$AE$2:$AE$245,D$1) -> 6274.95 | E2: =SUMIFS(Orders_Raw!$AB$2:$AB$245,Orders_Raw!$R$2:$R$245,$A2,Orders_Raw!$AE$2:$AE$245,E$1) -> 9618.08 | F2: =SUMIFS(Orders_Raw!$AB$2:$AB$245,Orders_Raw!$R$2:$R$245,$A2,Orders_Raw!$AE$2:$AE$245,F$1) -> 141.82 | G2: =SUMIFS(Orders_Raw!$AB$2:$AB$245,Orders_Raw!$R$2:$R$245,$A2,Orders_Raw!$AE$2:$AE$245,G$1) -> 2831.64 | H2: =SUMIFS(Orders_Raw!$AB$2:$AB$245,Orders_Raw!$R$2:$R$245,$A2,Orders_Raw!$AE$2:$AE$245,H$1) -> 6060.7 | I2: =SUMIFS(Orders_Raw!$AB$2:$AB$245,Orders_Raw!$R$2:$R$245,$A2,Orders_Raw!$AE$2:$AE$245,I$1) -> 5259.06 | ... M2: =SUMIFS(Orders_Raw!$AB$2:$AB$245,Orders_Raw!$R$2:$R$245,$A2,Orders_Raw!$AE$2:$AE$245,M$1) -> 14844.93
A3: Furniture | B3: =SUMIFS(Orders_Raw!$AB$2:$AB$245,Orders_Raw!$R$2:$R$245,$A3,Orders_Raw!$AE$2:$AE$245,B$1) -> 4069.35 | C3: =SUMIFS(Orders_Raw!$AB$2:$AB$245,Orders_Raw!$R$2:$R$245,$A3,Orders_Raw!$AE$2:$AE$245,C$1) -> 6317.43 | D3: =SUMIFS(Orders_Raw!$AB$2:$AB$245,Orders_Raw!$R$2:$R$245,$A3,Orders_Raw!$AE$2:$AE$245,D$1) -> 13376.87 | E3: =SUMIFS(Orders_Raw!$AB$2:$AB$245,Orders_Raw!$R$2:$R$245,$A3,Orders_Raw!$AE$2:$AE$245,E$1) -> 978.65 | F3: =SUMIFS(Orders_Raw!$AB$2:$AB$245,Orders_Raw!$R$2:$R$245,$A3,Orders_Raw!$AE$2:$AE$245,F$1) -> 7946.7 | G3: =SUMIFS(Orders_Raw!$AB$2:$AB$245,Orders_Raw!$R$2:$R$245,$A3,Orders_Raw!$AE$2:$AE$245,G$1) -> 4700.62 | H3: =SUMIFS(Orders_Raw!$AB$2:$AB$245,Orders_Raw!$R$2:$R$245,$A3,Orders_Raw!$AE$2:$AE$245,H$1) -> 5616.64 | I3: =SUMIFS(Orders_Raw!$AB$2:$AB$245,Orders_Raw!$R$2:$R$245,$A3,Orders_Raw!$AE$2:$AE$245,I$1) -> 17151.18 | ... M3: =SUMIFS(Orders_Raw!$AB$2:$AB$245,Orders_Raw!$R$2:$R$245,$A3,Orders_Raw!$AE$2:$AE$245,M$1) -> 5789.61
A4: Clothing | B4: =SUMIFS(Orders_Raw!$AB$2:$AB$245,Orders_Raw!$R$2:$R$245,$A4,Orders_Raw!$AE$2:$AE$245,B$1) -> 94.52 | C4: =SUMIFS(Orders_Raw!$AB$2:$AB$245,Orders_Raw!$R$2:$R$245,$A4,Orders_Raw!$AE$2:$AE$245,C$1) -> 652.6 | D4: =SUMIFS(Orders_Raw!$AB$2:$AB$245,Orders_Raw!$R$2:$R$245,$A4,Orders_Raw!$AE$2:$AE$245,D$1) -> 10307.76 | E4: =SUMIFS(Orders_Raw!$AB$2:$AB$245,Orders_Raw!$R$2:$R$245,$A4,Orders_Raw!$AE$2:$AE$245,E$1) -> 3625.76 | F4: =SUMIFS(Orders_Raw!$AB$2:$AB$245,Orders_Raw!$R$2:$R$245,$A4,Orders_Raw!$AE$2:$AE$245,F$1) -> 4625.76 | G4: =SUMIFS(Orders_Raw!$AB$2:$AB$245,Orders_Raw!$R$2:$R$245,$A4,Orders_Raw!$AE$2:$AE$245,G$1) -> 13994.53 | H4: =SUMIFS(Orders_Raw!$AB$2:$AB$245,Orders_Raw!$R$2:$R$245,$A4,Orders_Raw!$AE$2:$AE$245,H$1) -> 12641.68 | I4: =SUMIFS(Orders_Raw!$AB$2:$AB$245,Orders_Raw!$R$2:$R$245,$A4,Orders_Raw!$AE$2:$AE$245,I$1) -> 25647.32 | ... M4: =SUMIFS(Orders_Raw!$AB$2:$AB$245,Orders_Raw!$R$2:$R$245,$A4,Orders_Raw!$AE$2:$AE$245,M$1) -> 5591.58
A5: Groceries | B5: =SUMIFS(Orders_Raw!$AB$2:$AB$245,Orders_Raw!$R$2:$R$245,$A5,Orders_Raw!$AE$2:$AE$245,B$1) -> 1592.4 | C5: =SUMIFS(Orders_Raw!$AB$2:$AB$245,Orders_Raw!$R$2:$R$245,$A5,Orders_Raw!$AE$2:$AE$245,C$1) -> 7683.28 | D5: =SUMIFS(Orders_Raw!$AB$2:$AB$245,Orders_Raw!$R$2:$R$245,$A5,Orders_Raw!$AE$2:$AE$245,D$1) -> 8780.09 | E5: =SUMIFS(Orders_Raw!$AB$2:$AB$245,Orders_Raw!$R$2:$R$245,$A5,Orders_Raw!$AE$2:$AE$245,E$1) -> 3061.8 | F5: =SUMIFS(Orders_Raw!$AB$2:$AB$245,Orders_Raw!$R$2:$R$245,$A5,Orders_Raw!$AE$2:$AE$245,F$1) -> 4554.3 | G5: =SUMIFS(Orders_Raw!$AB$2:$AB$245,Orders_Raw!$R$2:$R$245,$A5,Orders_Raw!$AE$2:$AE$245,G$1) -> 5302.47 | H5: =SUMIFS(Orders_Raw!$AB$2:$AB$245,Orders_Raw!$R$2:$R$245,$A5,Orders_Raw!$AE$2:$AE$245,H$1) -> 9610.21 | I5: =SUMIFS(Orders_Raw!$AB$2:$AB$245,Orders_Raw!$R$2:$R$245,$A5,Orders_Raw!$AE$2:$AE$245,I$1) -> 10416.66 | ... M5: =SUMIFS(Orders_Raw!$AB$2:$AB$245,Orders_Raw!$R$2:$R$245,$A5,Orders_Raw!$AE$2:$AE$245,M$1) -> 8181.86
A6: Stationery | B6: =SUMIFS(Orders_Raw!$AB$2:$AB$245,Orders_Raw!$R$2:$R$245,$A6,Orders_Raw!$AE$2:$AE$245,B$1) -> 6671.2 | C6: =SUMIFS(Orders_Raw!$AB$2:$AB$245,Orders_Raw!$R$2:$R$245,$A6,Orders_Raw!$AE$2:$AE$245,C$1) -> 9636.93 | D6: =SUMIFS(Orders_Raw!$AB$2:$AB$245,Orders_Raw!$R$2:$R$245,$A6,Orders_Raw!$AE$2:$AE$245,D$1) -> 1886.42 | E6: =SUMIFS(Orders_Raw!$AB$2:$AB$245,Orders_Raw!$R$2:$R$245,$A6,Orders_Raw!$AE$2:$AE$245,E$1) -> 7123.72 | F6: =SUMIFS(Orders_Raw!$AB$2:$AB$245,Orders_Raw!$R$2:$R$245,$A6,Orders_Raw!$AE$2:$AE$245,F$1) -> 9533.03 | G6: =SUMIFS(Orders_Raw!$AB$2:$AB$245,Orders_Raw!$R$2:$R$245,$A6,Orders_Raw!$AE$2:$AE$245,G$1) -> 5631.41 | H6: =SUMIFS(Orders_Raw!$AB$2:$AB$245,Orders_Raw!$R$2:$R$245,$A6,Orders_Raw!$AE$2:$AE$245,H$1) -> 8377.41 | I6: =SUMIFS(Orders_Raw!$AB$2:$AB$245,Orders_Raw!$R$2:$R$245,$A6,Orders_Raw!$AE$2:$AE$245,I$1) -> 2318.88 | ... M6: =SUMIFS(Orders_Raw!$AB$2:$AB$245,Orders_Raw!$R$2:$R$245,$A6,Orders_Raw!$AE$2:$AE$245,M$1) -> 4594.96

Sheet Orders_Raw
A1: OrderID | B1: OrderDate | C1: CustomerName | D1: Region | E1: City | F1: Category | G1: Product | H1: Channel | I1: Quantity | J1: UnitPrice | K1: Discount | L1: PaymentMethod | M1: OrderStatus | N1: SalesRep | O1: Notes | P1: CustomerName_Clean | Q1: Region_Clean | R1: Category_Clean | S1: Channel_Clean | T1: PaymentMethod_Clean | U1: OrderStatus_Cleaned | V1: Quantity_Clean | W1: UnitPrice_Clean | X1: OrderDate_Clean | Y1: Discount_Clean | Z1: Notes_Clean | AA1: HighValueFlag | AB1: Revenue | AC1: OrderID_Key | AD1: OrderNumber | AE1: MonthLabel | AF1: MonthEndDate | AG1: FirstName | AH1: Discount_Numeric
A2: ORD-1109 | B2: 10/02/2024 | C2: Chen Malik | D2: west | E2: Quetta | F2: Furniture | G2: Office Chair | H2: In-store | I2: 7 | J2: $280.86 | L2: Credit card | M2: cancelled | P2: =PROPER(TRIM(C2)) -> Chen Malik | Q2: =IF(OR(PROPER(TRIM(tblOrders[[#This Row],[Region]]))="Nort",PROPER(TRIM(tblOrders[[#This Row],[Region]]))="Northh"),"North",PROPER(TRIM(tblOrders[[#This Row],[Region]]))) -> West | R2: =IF(PROPER(TRIM(F2))="Cloth Ing","Clothing",IF(PROPER(TRIM(F2))="Electronic","Electronics",IF(PROPER(TRIM(F2))="Grocery","Groceries",SUBSTITUTE(PROPER(TRIM(F2)),"Stationary","Stationery")))) -> Furniture | S2: =IF(LOWER(TRIM(H2))="online","Online",IF(OR(LOWER(TRIM(H2))="in-store",LOWER(TRIM(H2))="in store",LOWER(TRIM(H2))="instore"),"In-Store",PROPER(TRIM(H2)))) -> In-Store | T2: =IF(UPPER(TRIM(L2))="CC","Credit Card",PROPER(TRIM(L2))) -> Credit Card | U2: =IF(PROPER(TRIM(M2))="Complete","Completed",IF(PROPER(TRIM(M2))="Canceled","Cancelled",PROPER(TRIM(M2)))) -> Cancelled | V2: =IFERROR(VALUE(TRIM(I2)),"") -> 7 | W2: =IFERROR(VALUE(SUBSTITUTE(TRIM(J2),"$","")),"") -> 280.86 | X2: =IFERROR(IF(ISNUMBER(tblOrders[[#This Row],[OrderDate]]),tblOrders[[#This Row],[OrderDate]],IFERROR(DATEVALUE(tblOrders[[#This Row],[OrderDate]]),DATE(IF(LEN(TRIM(tblOrders[[#This Row],[OrderDate]]))=8,2000+VALUE(RIGHT(TRIM(tblOrders[[#This Row],[OrderDate]]),2)),VALUE(RIGHT(TRIM(tblOrders[[#This Row],[OrderDate]]),4))),VALUE(MID(TRIM(tblOrders[[#This Row],[OrderDate]]),4,2)),VALUE(LEFT(TRIM(tblOrders[[#This Row],[OrderDate]]),2))))),"CHECK MANUALLY") -> 45567 | Y2: =IF(K2="",0,K2) -> 0 | Z2: =TRIM(CLEAN(tblOrders[[#This Row],[Notes]])) | AA2: =IF(OR(V2="",W2=""),"Review",IF(V2*W2>=1000,"High Value","Standard")) -> High Value | AB2: =IF(OR(tblOrders[[#This Row],[Quantity_Clean]]="",tblOrders[[#This Row],[UnitPrice_Clean]]=""),0,tblOrders[[#This Row],[Quantity_Clean]]*tblOrders[[#This Row],[UnitPrice_Clean]]) -> 1966.02 | AC2: =UPPER(TRIM(tblOrders[[#This Row],[OrderID]])) -> ORD-1109 | AD2: =VALUE(RIGHT(tblOrders[[#This Row],[OrderID]],4)) -> 1109 | AE2: =TEXT(tblOrders[[#This Row],[OrderDate_Clean]],"mmm-yyyy") -> Oct-2024 | AF2: =EOMONTH(tblOrders[[#This Row],[OrderDate_Clean]],0) -> 45596 | AG2: Chen | AH2: =IF(tblOrders[[#This Row],[Discount]]="",0,IF(ISNUMBER(tblOrders[[#This Row],[Discount]]),tblOrders[[#This Row],[Discount]],VALUE(SUBSTITUTE(TRIM(tblOrders[[#This Row],[Discount]]),"%",""))/100)) -> 0
A3: ORD-1105 | B3: 03/01/2024 | C3: Grace Khan | D3: West | E3: Peshawar | F3: Furniture | G3: Bookshelf | H3: In Store | I3: 8 | J3: 453.85 | K3: 20% | L3: CREDIT CARD | M3: PENDING | N3: C. Osei | O3: Bulk order - business account | P3: =PROPER(TRIM(C3)) -> Grace Khan | Q3: =IF(OR(PROPER(TRIM(tblOrders[[#This Row],[Region]]))="Nort",PROPER(TRIM(tblOrders[[#This Row],[Region]]))="Northh"),"North",PROPER(TRIM(tblOrders[[#This Row],[Region]]))) -> West | R3: =IF(PROPER(TRIM(F3))="Cloth Ing","Clothing",IF(PROPER(TRIM(F3))="Electronic","Electronics",IF(PROPER(TRIM(F3))="Grocery","Groceries",SUBSTITUTE(PROPER(TRIM(F3)),"Stationary","Stationery")))) -> Furniture | S3: =IF(LOWER(TRIM(H3))="online","Online",IF(OR(LOWER(TRIM(H3))="in-store",LOWER(TRIM(H3))="in store",LOWER(TRIM(H3))="instore"),"In-Store",PROPER(TRIM(H3)))) -> In-Store | T3: =IF(UPPER(TRIM(L3))="CC","Credit Card",PROPER(TRIM(L3))) -> Credit Card | U3: =IF(PROPER(TRIM(M3))="Complete","Completed",IF(PROPER(TRIM(M3))="Canceled","Cancelled",PROPER(TRIM(M3)))) -> Pending | V3: =IFERROR(VALUE(TRIM(I3)),"") -> 8 | W3: =IFERROR(VALUE(SUBSTITUTE(TRIM(J3),"$","")),"") -> 453.85 | X3: =IFERROR(IF(ISNUMBER(tblOrders[[#This Row],[OrderDate]]),tblOrders[[#This Row],[OrderDate]],IFERROR(DATEVALUE(tblOrders[[#This Row],[OrderDate]]),DATE(IF(LEN(TRIM(tblOrders[[#This Row],[OrderDate]]))=8,2000+VALUE(RIGHT(TRIM(tblOrders[[#This Row],[OrderDate]]),2)),VALUE(RIGHT(TRIM(tblOrders[[#This Row],[OrderDate]]),4))),VALUE(MID(TRIM(tblOrders[[#This Row],[OrderDate]]),4,2)),VALUE(LEFT(TRIM(tblOrders[[#This Row],[OrderDate]]),2))))),"CHECK MANUALLY") -> 45352 | Y3: =IF(K3="",0,K3) -> 20% | Z3: =TRIM(CLEAN(tblOrders[[#This Row],[Notes]])) -> Bulk order - business account | AA3: =IF(OR(V3="",W3=""),"Review",IF(V3*W3>=1000,"High Value","Standard")) -> High Value | AB3: =IF(OR(tblOrders[[#This Row],[Quantity_Clean]]="",tblOrders[[#This Row],[UnitPrice_Clean]]=""),0,tblOrders[[#This Row],[Quantity_Clean]]*tblOrders[[#This Row],[UnitPrice_Clean]]) -> 3630.8 | AC3: =UPPER(TRIM(tblOrders[[#This Row],[OrderID]])) -> ORD-1105 | AD3: =VALUE(RIGHT(tblOrders[[#This Row],[OrderID]],4)) -> 1105 | AE3: =TEXT(tblOrders[[#This Row],[OrderDate_Clean]],"mmm-yyyy") -> Mar-2024 | AF3: =EOMONTH(tblOrders[[#This Row],[OrderDate_Clean]],0) -> 45382 | AG3: Grace | AH3: =IF(tblOrders[[#This Row],[Discount]]="",0,IF(ISNUMBER(tblOrders[[#This Row],[Discount]]),tblOrders[[#This Row],[Discount]],VALUE(SUBSTITUTE(TRIM(tblOrders[[#This Row],[Discount]]),"%",""))/100)) -> 0.2
A4: ORD-1200 | B4: 13/01/2024 | C4: Grace Smith | D4: north | E4: Faisalabad | F4: Furniture | G4: Office Chair | H4: Online | I4: 9 | J4: 439.93 | K4: 0 | L4: Bank Transfer | M4: PENDING | N4: B. Fernandes | P4: =PROPER(TRIM(C4)) -> Grace Smith | Q4: =IF(OR(PROPER(TRIM(tblOrders[[#This Row],[Region]]))="Nort",PROPER(TRIM(tblOrders[[#This Row],[Region]]))="Northh"),"North",PROPER(TRIM(tblOrders[[#This Row],[Region]]))) -> North | R4: =IF(PROPER(TRIM(F4))="Cloth Ing","Clothing",IF(PROPER(TRIM(F4))="Electronic","Electronics",IF(PROPER(TRIM(F4))="Grocery","Groceries",SUBSTITUTE(PROPER(TRIM(F4)),"Stationary","Stationery")))) -> Furniture | S4: =IF(LOWER(TRIM(H4))="online","Online",IF(OR(LOWER(TRIM(H4))="in-store",LOWER(TRIM(H4))="in store",LOWER(TRIM(H4))="instore"),"In-Store",PROPER(TRIM(H4)))) -> Online | T4: =IF(UPPER(TRIM(L4))="CC","Credit Card",PROPER(TRIM(L4))) -> Bank Transfer | U4: =IF(PROPER(TRIM(M4))="Complete","Completed",IF(PROPER(TRIM(M4))="Canceled","Cancelled",PROPER(TRIM(M4)))) -> Pending | V4: =IFERROR(VALUE(TRIM(I4)),"") -> 9 | W4: =IFERROR(VALUE(SUBSTITUTE(TRIM(J4),"$","")),"") -> 439.93 | X4: =IFERROR(IF(ISNUMBER(tblOrders[[#This Row],[OrderDate]]),tblOrders[[#This Row],[OrderDate]],IFERROR(DATEVALUE(tblOrders[[#This Row],[OrderDate]]),DATE(IF(LEN(TRIM(tblOrders[[#This Row],[OrderDate]]))=8,2000+VALUE(RIGHT(TRIM(tblOrders[[#This Row],[OrderDate]]),2)),VALUE(RIGHT(TRIM(tblOrders[[#This Row],[OrderDate]]),4))),VALUE(MID(TRIM(tblOrders[[#This Row],[OrderDate]]),4,2)),VALUE(LEFT(TRIM(tblOrders[[#This Row],[OrderDate]]),2))))),"CHECK MANUALLY") -> 45304 | Y4: =IF(K4="",0,K4) -> 0 | Z4: =TRIM(CLEAN(tblOrders[[#This Row],[Notes]])) | AA4: =IF(OR(V4="",W4=""),"Review",IF(V4*W4>=1000,"High Value","Standard")) -> High Value | AB4: =IF(OR(tblOrders[[#This Row],[Quantity_Clean]]="",tblOrders[[#This Row],[UnitPrice_Clean]]=""),0,tblOrders[[#This Row],[Quantity_Clean]]*tblOrders[[#This Row],[UnitPrice_Clean]]) -> 3959.37 | AC4: =UPPER(TRIM(tblOrders[[#This Row],[OrderID]])) -> ORD-1200 | AD4: =VALUE(RIGHT(tblOrders[[#This Row],[OrderID]],4)) -> 1200 | AE4: =TEXT(tblOrders[[#This Row],[OrderDate_Clean]],"mmm-yyyy") -> Jan-2024 | AF4: =EOMONTH(tblOrders[[#This Row],[OrderDate_Clean]],0) -> 45322 | AG4: Grace | AH4: =IF(tblOrders[[#This Row],[Discount]]="",0,IF(ISNUMBER(tblOrders[[#This Row],[Discount]]),tblOrders[[#This Row],[Discount]],VALUE(SUBSTITUTE(TRIM(tblOrders[[#This Row],[Discount]]),"%",""))/100)) -> 0
A5: ORD-1212 | B5: 03/28/2024 | C5: David Clark | D5: South | E5: Karachi | F5: Furniture | G5: Sofa Set | H5: Online | I5: 12 | J5: 411.55 | L5: cash | M5: CANCELLED | N5: D. Iqbal | P5: =PROPER(TRIM(C5)) -> David Clark | Q5: =IF(OR(PROPER(TRIM(tblOrders[[#This Row],[Region]]))="Nort",PROPER(TRIM(tblOrders[[#This Row],[Region]]))="Northh"),"North",PROPER(TRIM(tblOrders[[#This Row],[Region]]))) -> South | R5: =IF(PROPER(TRIM(F5))="Cloth Ing","Clothing",IF(PROPER(TRIM(F5))="Electronic","Electronics",IF(PROPER(TRIM(F5))="Grocery","Groceries",SUBSTITUTE(PROPER(TRIM(F5)),"Stationary","Stationery")))) -> Furniture | S5: =IF(LOWER(TRIM(H5))="online","Online",IF(OR(LOWER(TRIM(H5))="in-store",LOWER(TRIM(H5))="in store",LOWER(TRIM(H5))="instore"),"In-Store",PROPER(TRIM(H5)))) -> Online | T5: =IF(UPPER(TRIM(L5))="CC","Credit Card",PROPER(TRIM(L5))) -> Cash | U5: =IF(PROPER(TRIM(M5))="Complete","Completed",IF(PROPER(TRIM(M5))="Canceled","Cancelled",PROPER(TRIM(M5)))) -> Cancelled | V5: =IFERROR(VALUE(TRIM(I5)),"") -> 12 | W5: =IFERROR(VALUE(SUBSTITUTE(TRIM(J5),"$","")),"") -> 411.55 | X5: =IFERROR(IF(ISNUMBER(tblOrders[[#This Row],[OrderDate]]),tblOrders[[#This Row],[OrderDate]],IFERROR(DATEVALUE(tblOrders[[#This Row],[OrderDate]]),DATE(IF(LEN(TRIM(tblOrders[[#This Row],[OrderDate]]))=8,2000+VALUE(RIGHT(TRIM(tblOrders[[#This Row],[OrderDate]]),2)),VALUE(RIGHT(TRIM(tblOrders[[#This Row],[OrderDate]]),4))),VALUE(MID(TRIM(tblOrders[[#This Row],[OrderDate]]),4,2)),VALUE(LEFT(TRIM(tblOrders[[#This Row],[OrderDate]]),2))))),"CHECK MANUALLY") -> 45379 | Y5: =IF(K5="",0,K5) -> 0 | Z5: =TRIM(CLEAN(tblOrders[[#This Row],[Notes]])) | AA5: =IF(OR(V5="",W5=""),"Review",IF(V5*W5>=1000,"High Value","Standard")) -> High Value | AB5: =IF(OR(tblOrders[[#This Row],[Quantity_Clean]]="",tblOrders[[#This Row],[UnitPrice_Clean]]=""),0,tblOrders[[#This Row],[Quantity_Clean]]*tblOrders[[#This Row],[UnitPrice_Clean]]) -> 4938.6 | AC5: =UPPER(TRIM(tblOrders[[#This Row],[OrderID]])) -> ORD-1212 | AD5: =VALUE(RIGHT(tblOrders[[#This Row],[OrderID]],4)) -> 1212 | AE5: =TEXT(tblOrders[[#This Row],[OrderDate_Clean]],"mmm-yyyy") -> Mar-2024 | AF5: =EOMONTH(tblOrders[[#This Row],[OrderDate_Clean]],0) -> 45382 | AG5: David | AH5: =IF(tblOrders[[#This Row],[Discount]]="",0,IF(ISNUMBER(tblOrders[[#This Row],[Discount]]),tblOrders[[#This Row],[Discount]],VALUE(SUBSTITUTE(TRIM(tblOrders[[#This Row],[Discount]]),"%",""))/100)) -> 0
A6: ORD-1018 | B6: 25/02/2024 | C6: UMAR FAROOQ | D6: south | E6: Karachi | F6: Furniture | G6: Office Chair | H6: ONLINE | I6: 12 | J6: 392.28 | K6: 5% | L6: CC | M6: COMPLETED | O6: Gift wrap requested | P6: =PROPER(TRIM(C6)) -> Umar Farooq | Q6: =IF(OR(PROPER(TRIM(tblOrders[[#This Row],[Region]]))="Nort",PROPER(TRIM(tblOrders[[#This Row],[Region]]))="Northh"),"North",PROPER(TRIM(tblOrders[[#This Row],[Region]]))) -> South | R6: =IF(PROPER(TRIM(F6))="Cloth Ing","Clothing",IF(PROPER(TRIM(F6))="Electronic","Electronics",IF(PROPER(TRIM(F6))="Grocery","Groceries",SUBSTITUTE(PROPER(TRIM(F6)),"Stationary","Stationery")))) -> Furniture | S6: =IF(LOWER(TRIM(H6))="online","Online",IF(OR(LOWER(TRIM(H6))="in-store",LOWER(TRIM(H6))="in store",LOWER(TRIM(H6))="instore"),"In-Store",PROPER(TRIM(H6)))) -> Online | T6: =IF(UPPER(TRIM(L6))="CC","Credit Card",PROPER(TRIM(L6))) -> Credit Card | U6: =IF(PROPER(TRIM(M6))="Complete","Completed",IF(PROPER(TRIM(M6))="Canceled","Cancelled",PROPER(TRIM(M6)))) -> Completed | V6: =IFERROR(VALUE(TRIM(I6)),"") -> 12 | W6: =IFERROR(VALUE(SUBSTITUTE(TRIM(J6),"$","")),"") -> 392.28 | X6: =IFERROR(IF(ISNUMBER(tblOrders[[#This Row],[OrderDate]]),tblOrders[[#This Row],[OrderDate]],IFERROR(DATEVALUE(tblOrders[[#This Row],[OrderDate]]),DATE(IF(LEN(TRIM(tblOrders[[#This Row],[OrderDate]]))=8,2000+VALUE(RIGHT(TRIM(tblOrders[[#This Row],[OrderDate]]),2)),VALUE(RIGHT(TRIM(tblOrders[[#This Row],[OrderDate]]),4))),VALUE(MID(TRIM(tblOrders[[#This Row],[OrderDate]]),4,2)),VALUE(LEFT(TRIM(tblOrders[[#This Row],[OrderDate]]),2))))),"CHECK MANUALLY") -> 45347 | Y6: =IF(K6="",0,K6) -> 5% | Z6: =TRIM(CLEAN(tblOrders[[#This Row],[Notes]])) -> Gift wrap requested | AA6: =IF(OR(V6="",W6=""),"Review",IF(V6*W6>=1000,"High Value","Standard")) -> High Value | AB6: =IF(OR(tblOrders[[#This Row],[Quantity_Clean]]="",tblOrders[[#This Row],[UnitPrice_Clean]]=""),0,tblOrders[[#This Row],[Quantity_Clean]]*tblOrders[[#This Row],[UnitPrice_Clean]]) -> 4707.36 | AC6: =UPPER(TRIM(tblOrders[[#This Row],[OrderID]])) -> ORD-1018 | AD6: =VALUE(RIGHT(tblOrders[[#This Row],[OrderID]],4)) -> 1018 | AE6: =TEXT(tblOrders[[#This Row],[OrderDate_Clean]],"mmm-yyyy") -> Feb-2024 | AF6: =EOMONTH(tblOrders[[#This Row],[OrderDate_Clean]],0) -> 45351 | AG6: UMAR | AH6: =IF(tblOrders[[#This Row],[Discount]]="",0,IF(ISNUMBER(tblOrders[[#This Row],[Discount]]),tblOrders[[#This Row],[Discount]],VALUE(SUBSTITUTE(TRIM(tblOrders[[#This Row],[Discount]]),"%",""))/100)) -> 0.05
A7: ORD-1095 | B7: 06-May-24 | C7: Kevin Garcia | D7: East | E7: Sialkot | F7: Furniture | G7: Sofa Set | H7: in-store | I7: 9 | J7: 387.13 | K7: 10% | L7: cash | M7: CANCELLED | N7: B. Fernandes | O7: Bulk order - business account | P7: =PROPER(TRIM(C7)) -> Kevin Garcia | Q7: =IF(OR(PROPER(TRIM(tblOrders[[#This Row],[Region]]))="Nort",PROPER(TRIM(tblOrders[[#This Row],[Region]]))="Northh"),"North",PROPER(TRIM(tblOrders[[#This Row],[Region]]))) -> East | R7: =IF(PROPER(TRIM(F7))="Cloth Ing","Clothing",IF(PROPER(TRIM(F7))="Electronic","Electronics",IF(PROPER(TRIM(F7))="Grocery","Groceries",SUBSTITUTE(PROPER(TRIM(F7)),"Stationary","Stationery")))) -> Furniture | S7: =IF(LOWER(TRIM(H7))="online","Online",IF(OR(LOWER(TRIM(H7))="in-store",LOWER(TRIM(H7))="in store",LOWER(TRIM(H7))="instore"),"In-Store",PROPER(TRIM(H7)))) -> In-Store | T7: =IF(UPPER(TRIM(L7))="CC","Credit Card",PROPER(TRIM(L7))) -> Cash | U7: =IF(PROPER(TRIM(M7))="Complete","Completed",IF(PROPER(TRIM(M7))="Canceled","Cancelled",PROPER(TRIM(M7)))) -> Cancelled | V7: =IFERROR(VALUE(TRIM(I7)),"") -> 9 | W7: =IFERROR(VALUE(SUBSTITUTE(TRIM(J7),"$","")),"") -> 387.13 | X7: =IFERROR(IF(ISNUMBER(tblOrders[[#This Row],[OrderDate]]),tblOrders[[#This Row],[OrderDate]],IFERROR(DATEVALUE(tblOrders[[#This Row],[OrderDate]]),DATE(IF(LEN(TRIM(tblOrders[[#This Row],[OrderDate]]))=8,2000+VALUE(RIGHT(TRIM(tblOrders[[#This Row],[OrderDate]]),2)),VALUE(RIGHT(TRIM(tblOrders[[#This Row],[OrderDate]]),4))),VALUE(MID(TRIM(tblOrders[[#This Row],[OrderDate]]),4,2)),VALUE(LEFT(TRIM(tblOrders[[#This Row],[OrderDate]]),2))))),"CHECK MANUALLY") -> 45418 | Y7: =IF(K7="",0,K7) -> 10% | Z7: =TRIM(CLEAN(tblOrders[[#This Row],[Notes]])) -> Bulk order - business account | AA7: =IF(OR(V7="",W7=""),"Review",IF(V7*W7>=1000,"High Value","Standard")) -> High Value | AB7: =IF(OR(tblOrders[[#This Row],[Quantity_Clean]]="",tblOrders[[#This Row],[UnitPrice_Clean]]=""),0,tblOrders[[#This Row],[Quantity_Clean]]*tblOrders[[#This Row],[UnitPrice_Clean]]) -> 3484.17 | AC7: =UPPER(TRIM(tblOrders[[#This Row],[OrderID]])) -> ORD-1095 | AD7: =VALUE(RIGHT(tblOrders[[#This Row],[OrderID]],4)) -> 1095 | AE7: =TEXT(tblOrders[[#This Row],[OrderDate_Clean]],"mmm-yyyy") -> May-2024 | AF7: =EOMONTH(tblOrders[[#This Row],[OrderDate_Clean]],0) -> 45443 | AG7: Kevin | AH7: =IF(tblOrders[[#This Row],[Discount]]="",0,IF(ISNUMBER(tblOrders[[#This Row],[Discount]]),tblOrders[[#This Row],[Discount]],VALUE(SUBSTITUTE(TRIM(tblOrders[[#This Row],[Discount]]),"%",""))/100)) -> 0.1
A8: ORD-1227 | B8: 2024-07-22 | C8: Liam Anderson | D8: south | E8: Hyderabad | F8: Furniture | G8: Filing Cabinet | H8: ONLINE | I8: 11 | J8: 361.68 | L8: Cash | M8: pending | N8: A. Malik | O8: Follow up needed | P8: =PROPER(TRIM(C8)) -> Liam Anderson | Q8: =IF(OR(PROPER(TRIM(tblOrders[[#This Row],[Region]]))="Nort",PROPER(TRIM(tblOrders[[#This Row],[Region]]))="Northh"),"North",PROPER(TRIM(tblOrders[[#This Row],[Region]]))) -> South | R8: =IF(PROPER(TRIM(F8))="Cloth Ing","Clothing",IF(PROPER(TRIM(F8))="Electronic","Electronics",IF(PROPER(TRIM(F8))="Grocery","Groceries",SUBSTITUTE(PROPER(TRIM(F8)),"Stationary","Stationery")))) -> Furniture | S8: =IF(LOWER(TRIM(H8))="online","Online",IF(OR(LOWER(TRIM(H8))="in-store",LOWER(TRIM(H8))="in store",LOWER(TRIM(H8))="instore"),"In-Store",PROPER(TRIM(H8)))) -> Online | T8: =IF(UPPER(TRIM(L8))="CC","Credit Card",PROPER(TRIM(L8))) -> Cash | U8: =IF(PROPER(TRIM(M8))="Complete","Completed",IF(PROPER(TRIM(M8))="Canceled","Cancelled",PROPER(TRIM(M8)))) -> Pending | V8: =IFERROR(VALUE(TRIM(I8)),"") -> 11 | W8: =IFERROR(VALUE(SUBSTITUTE(TRIM(J8),"$","")),"") -> 361.68 | X8: =IFERROR(IF(ISNUMBER(tblOrders[[#This Row],[OrderDate]]),tblOrders[[#This Row],[OrderDate]],IFERROR(DATEVALUE(tblOrders[[#This Row],[OrderDate]]),DATE(IF(LEN(TRIM(tblOrders[[#This Row],[OrderDate]]))=8,2000+VALUE(RIGHT(TRIM(tblOrders[[#This Row],[OrderDate]]),2)),VALUE(RIGHT(TRIM(tblOrders[[#This Row],[OrderDate]]),4))),VALUE(MID(TRIM(tblOrders[[#This Row],[OrderDate]]),4,2)),VALUE(LEFT(TRIM(tblOrders[[#This Row],[OrderDate]]),2))))),"CHECK MANUALLY") -> 45495 | Y8: =IF(K8="",0,K8) -> 0 | Z8: =TRIM(CLEAN(tblOrders[[#This Row],[Notes]])) -> Follow up needed | AA8: =IF(OR(V8="",W8=""),"Review",IF(V8*W8>=1000,"High Value","Standard")) -> High Value | AB8: =IF(OR(tblOrders[[#This Row],[Quantity_Clean]]="",tblOrders[[#This Row],[UnitPrice_Clean]]=""),0,tblOrders[[#This Row],[Quantity_Clean]]*tblOrders[[#This Row],[UnitPrice_Clean]]) -> 3978.48 | AC8: =UPPER(TRIM(tblOrders[[#This Row],[OrderID]])) -> ORD-1227 | AD8: =VALUE(RIGHT(tblOrders[[#This Row],[OrderID]],4)) -> 1227 | AE8: =TEXT(tblOrders[[#This Row],[OrderDate_Clean]],"mmm-yyyy") -> Jul-2024 | AF8: =EOMONTH(tblOrders[[#This Row],[OrderDate_Clean]],0) -> 45504 | AG8: Liam | AH8: =IF(tblOrders[[#This Row],[Discount]]="",0,IF(ISNUMBER(tblOrders[[#This Row],[Discount]]),tblOrders[[#This Row],[Discount]],VALUE(SUBSTITUTE(TRIM(tblOrders[[#This Row],[Discount]]),"%",""))/100)) -> 0
A9: ORD-1147 | B9: 04-Oct-24 | C9: daniel smith | D9: SOUTH | E9: Hyderabad | F9: Furniture | G9: Bookshelf | H9: instore | I9: 4 | J9: 275.55 | L9: debit card | M9: Completed | N9: B. Fernandes | O9: Gift wrap requested | P9: =PROPER(TRIM(C9)) -> Daniel Smith | Q9: =IF(OR(PROPER(TRIM(tblOrders[[#This Row],[Region]]))="Nort",PROPER(TRIM(tblOrders[[#This Row],[Region]]))="Northh"),"North",PROPER(TRIM(tblOrders[[#This Row],[Region]]))) -> South | R9: =IF(PROPER(TRIM(F9))="Cloth Ing","Clothing",IF(PROPER(TRIM(F9))="Electronic","Electronics",IF(PROPER(TRIM(F9))="Grocery","Groceries",SUBSTITUTE(PROPER(TRIM(F9)),"Stationary","Stationery")))) -> Furniture | S9: =IF(LOWER(TRIM(H9))="online","Online",IF(OR(LOWER(TRIM(H9))="in-store",LOWER(TRIM(H9))="in store",LOWER(TRIM(H9))="instore"),"In-Store",PROPER(TRIM(H9)))) -> In-Store | T9: =IF(UPPER(TRIM(L9))="CC","Credit Card",PROPER(TRIM(L9))) -> Debit Card | U9: =IF(PROPER(TRIM(M9))="Complete","Completed",IF(PROPER(TRIM(M9))="Canceled","Cancelled",PROPER(TRIM(M9)))) -> Completed | V9: =IFERROR(VALUE(TRIM(I9)),"") -> 4 | W9: =IFERROR(VALUE(SUBSTITUTE(TRIM(J9),"$","")),"") -> 275.55 | X9: =IFERROR(IF(ISNUMBER(tblOrders[[#This Row],[OrderDate]]),tblOrders[[#This Row],[OrderDate]],IFERROR(DATEVALUE(tblOrders[[#This Row],[OrderDate]]),DATE(IF(LEN(TRIM(tblOrders[[#This Row],[OrderDate]]))=8,2000+VALUE(RIGHT(TRIM(tblOrders[[#This Row],[OrderDate]]),2)),VALUE(RIGHT(TRIM(tblOrders[[#This Row],[OrderDate]]),4))),VALUE(MID(TRIM(tblOrders[[#This Row],[OrderDate]]),4,2)),VALUE(LEFT(TRIM(tblOrders[[#This Row],[OrderDate]]),2))))),"CHECK MANUALLY") -> 45569 | Y9: =IF(K9="",0,K9) -> 0 | Z9: =TRIM(CLEAN(tblOrders[[#This Row],[Notes]])) -> Gift wrap requested | AA9: =IF(OR(V9="",W9=""),"Review",IF(V9*W9>=1000,"High Value","Standard")) -> High Value | AB9: =IF(OR(tblOrders[[#This Row],[Quantity_Clean]]="",tblOrders[[#This Row],[UnitPrice_Clean]]=""),0,tblOrders[[#This Row],[Quantity_Clean]]*tblOrders[[#This Row],[UnitPrice_Clean]]) -> 1102.2 | AC9: =UPPER(TRIM(tblOrders[[#This Row],[OrderID]])) -> ORD-1147 | AD9: =VALUE(RIGHT(tblOrders[[#This Row],[OrderID]],4)) -> 1147 | AE9: =TEXT(tblOrders[[#This Row],[OrderDate_Clean]],"mmm-yyyy") -> Oct-2024 | AF9: =EOMONTH(tblOrders[[#This Row],[OrderDate_Clean]],0) -> 45596 | AG9: daniel | AH9: =IF(tblOrders[[#This Row],[Discount]]="",0,IF(ISNUMBER(tblOrders[[#This Row],[Discount]]),tblOrders[[#This Row],[Discount]],VALUE(SUBSTITUTE(TRIM(tblOrders[[#This Row],[Discount]]),"%",""))/100)) -> 0
A10: ORD-1045 | B10: September 14, 2024 | C10: UMAR FAROOQ | D10: WEST | E10: Quetta | F10: Furniture | G10: Study Desk | H10: In Store | I10: 1 | J10: 239.12 | K10: 0.05 | L10: Debit card | M10: Completed | N10: B. Fernandes | P10: =PROPER(TRIM(C10)) -> Umar Farooq | Q10: =IF(OR(PROPER(TRIM(tblOrders[[#This Row],[Region]]))="Nort",PROPER(TRIM(tblOrders[[#This Row],[Region]]))="Northh"),"North",PROPER(TRIM(tblOrders[[#This Row],[Region]]))) -> West | R10: =IF(PROPER(TRIM(F10))="Cloth Ing","Clothing",IF(PROPER(TRIM(F10))="Electronic","Electronics",IF(PROPER(TRIM(F10))="Grocery","Groceries",SUBSTITUTE(PROPER(TRIM(F10)),"Stationary","Stationery")))) -> Furniture | S10: =IF(LOWER(TRIM(H10))="online","Online",IF(OR(LOWER(TRIM(H10))="in-store",LOWER(TRIM(H10))="in store",LOWER(TRIM(H10))="instore"),"In-Store",PROPER(TRIM(H10)))) -> In-Store | T10: =IF(UPPER(TRIM(L10))="CC","Credit Card",PROPER(TRIM(L10))) -> Debit Card | U10: =IF(PROPER(TRIM(M10))="Complete","Completed",IF(PROPER(TRIM(M10))="Canceled","Cancelled",PROPER(TRIM(M10)))) -> Completed | V10: =IFERROR(VALUE(TRIM(I10)),"") -> 1 | W10: =IFERROR(VALUE(SUBSTITUTE(TRIM(J10),"$","")),"") -> 239.12 | X10: =IFERROR(IF(ISNUMBER(tblOrders[[#This Row],[OrderDate]]),tblOrders[[#This Row],[OrderDate]],IFERROR(DATEVALUE(tblOrders[[#This Row],[OrderDate]]),DATE(IF(LEN(TRIM(tblOrders[[#This Row],[OrderDate]]))=8,2000+VALUE(RIGHT(TRIM(tblOrders[[#This Row],[OrderDate]]),2)),VALUE(RIGHT(TRIM(tblOrders[[#This Row],[OrderDate]]),4))),VALUE(MID(TRIM(tblOrders[[#This Row],[OrderDate]]),4,2)),VALUE(LEFT(TRIM(tblOrders[[#This Row],[OrderDate]]),2))))),"CHECK MANUALLY") -> 45549 | Y10: =IF(K10="",0,K10) -> 0.05 | Z10: =TRIM(CLEAN(tblOrders[[#This Row],[Notes]])) | AA10: =IF(OR(V10="",W10=""),"Review",IF(V10*W10>=1000,"High Value","Standard")) -> Standard | AB10: =IF(OR(tblOrders[[#This Row],[Quantity_Clean]]="",tblOrders[[#This Row],[UnitPrice_Clean]]=""),0,tblOrders[[#This Row],[Quantity_Clean]]*tblOrders[[#This Row],[UnitPrice_Clean]]) -> 239.12 | AC10: =UPPER(TRIM(tblOrders[[#This Row],[OrderID]])) -> ORD-1045 | AD10: =VALUE(RIGHT(tblOrders[[#This Row],[OrderID]],4)) -> 1045 | AE10: =TEXT(tblOrders[[#This Row],[OrderDate_Clean]],"mmm-yyyy") -> Sep-2024 | AF10: =EOMONTH(tblOrders[[#This Row],[OrderDate_Clean]],0) -> 45565 | AG10: UMAR | AH10: =IF(tblOrders[[#This Row],[Discount]]="",0,IF(ISNUMBER(tblOrders[[#This Row],[Discount]]),tblOrders[[#This Row],[Discount]],VALUE(SUBSTITUTE(TRIM(tblOrders[[#This Row],[Discount]]),"%",""))/100)) -> 0.05
A11: ORD-1046 | B11: 13-Jul-24 | C11: LIAM ALI | D11: North | F11: Furniture | G11: Study Desk | H11: online | I11: 8 | J11: 136.19 | K11: 0 | L11: Debit Card | M11: PENDING | N11: E. Tanaka | O11: Damaged on arrival - replaced | P11: =PROPER(TRIM(C11)) -> Liam Ali | Q11: =IF(OR(PROPER(TRIM(tblOrders[[#This Row],[Region]]))="Nort",PROPER(TRIM(tblOrders[[#This Row],[Region]]))="Northh"),"North",PROPER(TRIM(tblOrders[[#This Row],[Region]]))) -> North | R11: =IF(PROPER(TRIM(F11))="Cloth Ing","Clothing",IF(PROPER(TRIM(F11))="Electronic","Electronics",IF(PROPER(TRIM(F11))="Grocery","Groceries",SUBSTITUTE(PROPER(TRIM(F11)),"Stationary","Stationery")))) -> Furniture | S11: =IF(LOWER(TRIM(H11))="online","Online",IF(OR(LOWER(TRIM(H11))="in-store",LOWER(TRIM(H11))="in store",LOWER(TRIM(H11))="instore"),"In-Store",PROPER(TRIM(H11)))) -> Online | T11: =IF(UPPER(TRIM(L11))="CC","Credit Card",PROPER(TRIM(L11))) -> Debit Card | U11: =IF(PROPER(TRIM(M11))="Complete","Completed",IF(PROPER(TRIM(M11))="Canceled","Cancelled",PROPER(TRIM(M11)))) -> Pending | V11: =IFERROR(VALUE(TRIM(I11)),"") -> 8 | W11: =IFERROR(VALUE(SUBSTITUTE(TRIM(J11),"$","")),"") -> 136.19 | X11: =IFERROR(IF(ISNUMBER(tblOrders[[#This Row],[OrderDate]]),tblOrders[[#This Row],[OrderDate]],IFERROR(DATEVALUE(tblOrders[[#This Row],[OrderDate]]),DATE(IF(LEN(TRIM(tblOrders[[#This Row],[OrderDate]]))=8,2000+VALUE(RIGHT(TRIM(tblOrders[[#This Row],[OrderDate]]),2)),VALUE(RIGHT(TRIM(tblOrders[[#This Row],[OrderDate]]),4))),VALUE(MID(TRIM(tblOrders[[#This Row],[OrderDate]]),4,2)),VALUE(LEFT(TRIM(tblOrders[[#This Row],[OrderDate]]),2))))),"CHECK MANUALLY") -> 45486 | Y11: =IF(K11="",0,K11) -> 0 | Z11: =TRIM(CLEAN(tblOrders[[#This Row],[Notes]])) -> Damaged on arrival - replaced | AA11: =IF(OR(V11="",W11=""),"Review",IF(V11*W11>=1000,"High Value","Standard")) -> High Value | AB11: =IF(OR(tblOrders[[#This Row],[Quantity_Clean]]="",tblOrders[[#This Row],[UnitPrice_Clean]]=""),0,tblOrders[[#This Row],[Quantity_Clean]]*tblOrders[[#This Row],[UnitPrice_Clean]]) -> 1089.52 | AC11: =UPPER(TRIM(tblOrders[[#This Row],[OrderID]])) -> ORD-1046 | AD11: =VALUE(RIGHT(tblOrders[[#This Row],[OrderID]],4)) -> 1046 | AE11: =TEXT(tblOrders[[#This Row],[OrderDate_Clean]],"mmm-yyyy") -> Jul-2024 | AF11: =EOMONTH(tblOrders[[#This Row],[OrderDate_Clean]],0) -> 45504 | AG11: LIAM | AH11: =IF(tblOrders[[#This Row],[Discount]]="",0,IF(ISNUMBER(tblOrders[[#This Row],[Discount]]),tblOrders[[#This Row],[Discount]],VALUE(SUBSTITUTE(TRIM(tblOrders[[#This Row],[Discount]]),"%",""))/100)) -> 0
A12: ORD-1148 | B12: 2024-08-22 | C12: Robert Smith | D12: WEST | E12: Quetta | F12: Furniture | G12: Filing Cabinet | H12: Online | I12: 3 | J12: 51.05 | K12: 0.2 | L12: debit card | M12: Refunded | N12: C. Osei | O12: Customer called twice | P12: =PROPER(TRIM(C12)) -> Robert Smith | Q12: =IF(OR(PROPER(TRIM(tblOrders[[#This Row],[Region]]))="Nort",PROPER(TRIM(tblOrders[[#This Row],[Region]]))="Northh"),"North",PROPER(TRIM(tblOrders[[#This Row],[Region]]))) -> West | R12: =IF(PROPER(TRIM(F12))="Cloth Ing","Clothing",IF(PROPER(TRIM(F12))="Electronic","Electronics",IF(PROPER(TRIM(F12))="Grocery","Groceries",SUBSTITUTE(PROPER(TRIM(F12)),"Stationary","Stationery")))) -> Furniture | S12: =IF(LOWER(TRIM(H12))="online","Online",IF(OR(LOWER(TRIM(H12))="in-store",LOWER(TRIM(H12))="in store",LOWER(TRIM(H12))="instore"),"In-Store",PROPER(TRIM(H12)))) -> Online | T12: =IF(UPPER(TRIM(L12))="CC","Credit Card",PROPER(TRIM(L12))) -> Debit Card | U12: =IF(PROPER(TRIM(M12))="Complete","Completed",IF(PROPER(TRIM(M12))="Canceled","Cancelled",PROPER(TRIM(M12)))) -> Refunded | V12: =IFERROR(VALUE(TRIM(I12)),"") -> 3 | W12: =IFERROR(VALUE(SUBSTITUTE(TRIM(J12),"$","")),"") -> 51.05 | X12: =IFERROR(IF(ISNUMBER(tblOrders[[#This Row],[OrderDate]]),tblOrders[[#This Row],[OrderDate]],IFERROR(DATEVALUE(tblOrders[[#This Row],[OrderDate]]),DATE(IF(LEN(TRIM(tblOrders[[#This Row],[OrderDate]]))=8,2000+VALUE(RIGHT(TRIM(tblOrders[[#This Row],[OrderDate]]),2)),VALUE(RIGHT(TRIM(tblOrders[[#This Row],[OrderDate]]),4))),VALUE(MID(TRIM(tblOrders[[#This Row],[OrderDate]]),4,2)),VALUE(LEFT(TRIM(tblOrders[[#This Row],[OrderDate]]),2))))),"CHECK MANUALLY") -> 45526 | Y12: =IF(K12="",0,K12) -> 0.2 | Z12: =TRIM(CLEAN(tblOrders[[#This Row],[Notes]])) -> Customer called twice | AA12: =IF(OR(V12="",W12=""),"Review",IF(V12*W12>=1000,"High Value","Standard")) -> Standard | AB12: =IF(OR(tblOrders[[#This Row],[Quantity_Clean]]="",tblOrders[[#This Row],[UnitPrice_Clean]]=""),0,tblOrders[[#This Row],[Quantity_Clean]]*tblOrders[[#This Row],[UnitPrice_Clean]]) -> 153.15 | AC12: =UPPER(TRIM(tblOrders[[#This Row],[OrderID]])) -> ORD-1148 | AD12: =VALUE(RIGHT(tblOrders[[#This Row],[OrderID]],4)) -> 1148 | AE12: =TEXT(tblOrders[[#This Row],[OrderDate_Clean]],"mmm-yyyy") -> Aug-2024 | AF12: =EOMONTH(tblOrders[[#This Row],[OrderDate_Clean]],0) -> 45535 | AG12: Robert | AH12: =IF(tblOrders[[#This Row],[Discount]]="",0,IF(ISNUMBER(tblOrders[[#This Row],[Discount]]),tblOrders[[#This Row],[Discount]],VALUE(SUBSTITUTE(TRIM(tblOrders[[#This Row],[Discount]]),"%",""))/100)) -> 0.2
A13: ORD-1080 | B13: 2024-02-22 | C13: EMILY SHEIKH | D13: West | E13: Peshawar | F13: Furniture | G13: Filing Cabinet | H13: in-store | I13: 9 | J13: 45.89 | K13: 0.05 | L13: Cash | M13: Cancelled | N13: C. Osei | P13: =PROPER(TRIM(C13)) -> Emily Sheikh | Q13: =IF(OR(PROPER(TRIM(tblOrders[[#This Row],[Region]]))="Nort",PROPER(TRIM(tblOrders[[#This Row],[Region]]))="Northh"),"North",PROPER(TRIM(tblOrders[[#This Row],[Region]]))) -> West | R13: =IF(PROPER(TRIM(F13))="Cloth Ing","Clothing",IF(PROPER(TRIM(F13))="Electronic","Electronics",IF(PROPER(TRIM(F13))="Grocery","Groceries",SUBSTITUTE(PROPER(TRIM(F13)),"Stationary","Stationery")))) -> Furniture | S13: =IF(LOWER(TRIM(H13))="online","Online",IF(OR(LOWER(TRIM(H13))="in-store",LOWER(TRIM(H13))="in store",LOWER(TRIM(H13))="instore"),"In-Store",PROPER(TRIM(H13)))) -> In-Store | T13: =IF(UPPER(TRIM(L13))="CC","Credit Card",PROPER(TRIM(L13))) -> Cash | U13: =IF(PROPER(TRIM(M13))="Complete","Completed",IF(PROPER(TRIM(M13))="Canceled","Cancelled",PROPER(TRIM(M13)))) -> Cancelled | V13: =IFERROR(VALUE(TRIM(I13)),"") -> 9 | W13: =IFERROR(VALUE(SUBSTITUTE(TRIM(J13),"$","")),"") -> 45.89 | X13: =IFERROR(IF(ISNUMBER(tblOrders[[#This Row],[OrderDate]]),tblOrders[[#This Row],[OrderDate]],IFERROR(DATEVALUE(tblOrders[[#This Row],[OrderDate]]),DATE(IF(LEN(TRIM(tblOrders[[#This Row],[OrderDate]]))=8,2000+VALUE(RIGHT(TRIM(tblOrders[[#This Row],[OrderDate]]),2)),VALUE(RIGHT(TRIM(tblOrders[[#This Row],[OrderDate]]),4))),VALUE(MID(TRIM(tblOrders[[#This Row],[OrderDate]]),4,2)),VALUE(LEFT(TRIM(tblOrders[[#This Row],[OrderDate]]),2))))),"CHECK MANUALLY") -> 45344 | Y13: =IF(K13="",0,K13) -> 0.05 | Z13: =TRIM(CLEAN(tblOrders[[#This Row],[Notes]])) | AA13: =IF(OR(V13="",W13=""),"Review",IF(V13*W13>=1000,"High Value","Standard")) -> Standard | AB13: =IF(OR(tblOrders[[#This Row],[Quantity_Clean]]="",tblOrders[[#This Row],[UnitPrice_Clean]]=""),0,tblOrders[[#This Row],[Quantity_Clean]]*tblOrders[[#This Row],[UnitPrice_Clean]]) -> 413.01 | AC13: =UPPER(TRIM(tblOrders[[#This Row],[OrderID]])) -> ORD-1080 | AD13: =VALUE(RIGHT(tblOrders[[#This Row],[OrderID]],4)) -> 1080 | AE13: =TEXT(tblOrders[[#This Row],[OrderDate_Clean]],"mmm-yyyy") -> Feb-2024 | AF13: =EOMONTH(tblOrders[[#This Row],[OrderDate_Clean]],0) -> 45351 | AG13: EMILY | AH13: =IF(tblOrders[[#This Row],[Discount]]="",0,IF(ISNUMBER(tblOrders[[#This Row],[Discount]]),tblOrders[[#This Row],[Discount]],VALUE(SUBSTITUTE(TRIM(tblOrders[[#This Row],[Discount]]),"%",""))/100)) -> 0.05
A14: ORD-1137 | B14: 2024-06-24 | C14: james johnson | D14: South | E14: Hyderabad | F14: Furniture | G14: Office Chair | H14: online | I14: 1 | J14: 43.58 | K14: 0.15 | L14: Credit Card | M14: Completed | P14: =PROPER(TRIM(C14)) -> James Johnson | Q14: =IF(OR(PROPER(TRIM(tblOrders[[#This Row],[Region]]))="Nort",PROPER(TRIM(tblOrders[[#This Row],[Region]]))="Northh"),"North",PROPER(TRIM(tblOrders[[#This Row],[Region]]))) -> South | R14: =IF(PROPER(TRIM(F14))="Cloth Ing","Clothing",IF(PROPER(TRIM(F14))="Electronic","Electronics",IF(PROPER(TRIM(F14))="Grocery","Groceries",SUBSTITUTE(PROPER(TRIM(F14)),"Stationary","Stationery")))) -> Furniture | S14: =IF(LOWER(TRIM(H14))="online","Online",IF(OR(LOWER(TRIM(H14))="in-store",LOWER(TRIM(H14))="in store",LOWER(TRIM(H14))="instore"),"In-Store",PROPER(TRIM(H14)))) -> Online | T14: =IF(UPPER(TRIM(L14))="CC","Credit Card",PROPER(TRIM(L14))) -> Credit Card | U14: =IF(PROPER(TRIM(M14))="Complete","Completed",IF(PROPER(TRIM(M14))="Canceled","Cancelled",PROPER(TRIM(M14)))) -> Completed | V14: =IFERROR(VALUE(TRIM(I14)),"") -> 1 | W14: =IFERROR(VALUE(SUBSTITUTE(TRIM(J14),"$","")),"") -> 43.58 | X14: =IFERROR(IF(ISNUMBER(tblOrders[[#This Row],[OrderDate]]),tblOrders[[#This Row],[OrderDate]],IFERROR(DATEVALUE(tblOrders[[#This Row],[OrderDate]]),DATE(IF(LEN(TRIM(tblOrders[[#This Row],[OrderDate]]))=8,2000+VALUE(RIGHT(TRIM(tblOrders[[#This Row],[OrderDate]]),2)),VALUE(RIGHT(TRIM(tblOrders[[#This Row],[OrderDate]]),4))),VALUE(MID(TRIM(tblOrders[[#This Row],[OrderDate]]),4,2)),VALUE(LEFT(TRIM(tblOrders[[#This Row],[OrderDate]]),2))))),"CHECK MANUALLY") -> 45467 | Y14: =IF(K14="",0,K14) -> 0.15 | Z14: =TRIM(CLEAN(tblOrders[[#This Row],[Notes]])) | AA14: =IF(OR(V14="",W14=""),"Review",IF(V14*W14>=1000,"High Value","Standard")) -> Standard | AB14: =IF(OR(tblOrders[[#This Row],[Quantity_Clean]]="",tblOrders[[#This Row],[UnitPrice_Clean]]=""),0,tblOrders[[#This Row],[Quantity_Clean]]*tblOrders[[#This Row],[UnitPrice_Clean]]) -> 43.58 | AC14: =UPPER(TRIM(tblOrders[[#This Row],[OrderID]])) -> ORD-1137 | AD14: =VALUE(RIGHT(tblOrders[[#This Row],[OrderID]],4)) -> 1137 | AE14: =TEXT(tblOrders[[#This Row],[OrderDate_Clean]],"mmm-yyyy") -> Jun-2024 | AF14: =EOMONTH(tblOrders[[#This Row],[OrderDate_Clean]],0) -> 45473 | AG14: james | AH14: =IF(tblOrders[[#This Row],[Discount]]="",0,IF(ISNUMBER(tblOrders[[#This Row],[Discount]]),tblOrders[[#This Row],[Discount]],VALUE(SUBSTITUTE(TRIM(tblOrders[[#This Row],[Discount]]),"%",""))/100)) -> 0.15
A15: ORD-1084 | B15: July 03, 2024 | C15: Sofia Lee | D15: EAST | E15: Multan | F15: Cloth ing | G15: Denim Jacket | H15: ONLINE | I15: 6 | J15: 65.07 | L15: bank transfer | M15: CANCELLED | N15: A. Malik | P15: =PROPER(TRIM(C15)) -> Sofia Lee | Q15: =IF(OR(PROPER(TRIM(tblOrders[[#This Row],[Region]]))="Nort",PROPER(TRIM(tblOrders[[#This Row],[Region]]))="Northh"),"North",PROPER(TRIM(tblOrders[[#This Row],[Region]]))) -> East | R15: =IF(PROPER(TRIM(F15))="Cloth Ing","Clothing",IF(PROPER(TRIM(F15))="Electronic","Electronics",IF(PROPER(TRIM(F15))="Grocery","Groceries",SUBSTITUTE(PROPER(TRIM(F15)),"Stationary","Stationery")))) -> Clothing | S15: =IF(LOWER(TRIM(H15))="online","Online",IF(OR(LOWER(TRIM(H15))="in-store",LOWER(TRIM(H15))="in store",LOWER(TRIM(H15))="instore"),"In-Store",PROPER(TRIM(H15)))) -> Online | T15: =IF(UPPER(TRIM(L15))="CC","Credit Card",PROPER(TRIM(L15))) -> Bank Transfer | U15: =IF(PROPER(TRIM(M15))="Complete","Completed",IF(PROPER(TRIM(M15))="Canceled","Cancelled",PROPER(TRIM(M15)))) -> Cancelled | V15: =IFERROR(VALUE(TRIM(I15)),"") -> 6 | W15: =IFERROR(VALUE(SUBSTITUTE(TRIM(J15),"$","")),"") -> 65.07 | X15: =IFERROR(IF(ISNUMBER(tblOrders[[#This Row],[OrderDate]]),tblOrders[[#This Row],[OrderDate]],IFERROR(DATEVALUE(tblOrders[[#This Row],[OrderDate]]),DATE(IF(LEN(TRIM(tblOrders[[#This Row],[OrderDate]]))=8,2000+VALUE(RIGHT(TRIM(tblOrders[[#This Row],[OrderDate]]),2)),VALUE(RIGHT(TRIM(tblOrders[[#This Row],[OrderDate]]),4))),VALUE(MID(TRIM(tblOrders[[#This Row],[OrderDate]]),4,2)),VALUE(LEFT(TRIM(tblOrders[[#This Row],[OrderDate]]),2))))),"CHECK MANUALLY") -> 45476 | Y15: =IF(K15="",0,K15) -> 0 | Z15: =TRIM(CLEAN(tblOrders[[#This Row],[Notes]])) | AA15: =IF(OR(V15="",W15=""),"Review",IF(V15*W15>=1000,"High Value","Standard")) -> Standard | AB15: =IF(OR(tblOrders[[#This Row],[Quantity_Clean]]="",tblOrders[[#This Row],[UnitPrice_Clean]]=""),0,tblOrders[[#This Row],[Quantity_Clean]]*tblOrders[[#This Row],[UnitPrice_Clean]]) -> 390.42 | AC15: =UPPER(TRIM(tblOrders[[#This Row],[OrderID]])) -> ORD-1084 | AD15: =VALUE(RIGHT(tblOrders[[#This Row],[OrderID]],4)) -> 1084 | AE15: =TEXT(tblOrders[[#This Row],[OrderDate_Clean]],"mmm-yyyy") -> Jul-2024 | AF15: =EOMONTH(tblOrders[[#This Row],[OrderDate_Clean]],0) -> 45504 | AG15: Sofia | AH15: =IF(tblOrders[[#This Row],[Discount]]="",0,IF(ISNUMBER(tblOrders[[#This Row],[Discount]]),tblOrders[[#This Row],[Discount]],VALUE(SUBSTITUTE(TRIM(tblOrders[[#This Row],[Discount]]),"%",""))/100)) -> 0
A16: ORD-1198 | B16: 08/16/2024 | C16: GRACE ANDERSON | D16: east | E16: Multan | F16: Cloth ing | G16: Formal Shirt | H16: Online | I16: 10 | J16: 498.33 | K16: 0 | L16: credit card | M16: PENDING | N16: C. Osei | O16: VIP customer | P16: =PROPER(TRIM(C16)) -> Grace Anderson | Q16: =IF(OR(PROPER(TRIM(tblOrders[[#This Row],[Region]]))="Nort",PROPER(TRIM(tblOrders[[#This Row],[Region]]))="Northh"),"North",PROPER(TRIM(tblOrders[[#This Row],[Region]]))) -> East | R16: =IF(PROPER(TRIM(F16))="Cloth Ing","Clothing",IF(PROPER(TRIM(F16))="Electronic","Electronics",IF(PROPER(TRIM(F16))="Grocery","Groceries",SUBSTITUTE(PROPER(TRIM(F16)),"Stationary","Stationery")))) -> Clothing | S16: =IF(LOWER(TRIM(H16))="online","Online",IF(OR(LOWER(TRIM(H16))="in-store",LOWER(TRIM(H16))="in store",LOWER(TRIM(H16))="instore"),"In-Store",PROPER(TRIM(H16)))) -> Online | T16: =IF(UPPER(TRIM(L16))="CC","Credit Card",PROPER(TRIM(L16))) -> Credit Card | U16: =IF(PROPER(TRIM(M16))="Complete","Completed",IF(PROPER(TRIM(M16))="Canceled","Cancelled",PROPER(TRIM(M16)))) -> Pending | V16: =IFERROR(VALUE(TRIM(I16)),"") -> 10 | W16: =IFERROR(VALUE(SUBSTITUTE(TRIM(J16),"$","")),"") -> 498.33 | X16: =IFERROR(IF(ISNUMBER(tblOrders[[#This Row],[OrderDate]]),tblOrders[[#This Row],[OrderDate]],IFERROR(DATEVALUE(tblOrders[[#This Row],[OrderDate]]),DATE(IF(LEN(TRIM(tblOrders[[#This Row],[OrderDate]]))=8,2000+VALUE(RIGHT(TRIM(tblOrders[[#This Row],[OrderDate]]),2)),VALUE(RIGHT(TRIM(tblOrders[[#This Row],[OrderDate]]),4))),VALUE(MID(TRIM(tblOrders[[#This Row],[OrderDate]]),4,2)),VALUE(LEFT(TRIM(tblOrders[[#This Row],[OrderDate]]),2))))),"CHECK MANUALLY") -> 45520 | Y16: =IF(K16="",0,K16) -> 0 | Z16: =TRIM(CLEAN(tblOrders[[#This Row],[Notes]])) -> VIP customer | AA16: =IF(OR(V16="",W16=""),"Review",IF(V16*W16>=1000,"High Value","Standard")) -> High Value | AB16: =IF(OR(tblOrders[[#This Row],[Quantity_Clean]]="",tblOrders[[#This Row],[UnitPrice_Clean]]=""),0,tblOrders[[#This Row],[Quantity_Clean]]*tblOrders[[#This Row],[UnitPrice_Clean]]) -> 4983.3 | AC16: =UPPER(TRIM(tblOrders[[#This Row],[OrderID]])) -> ORD-1198 | AD16: =VALUE(RIGHT(tblOrders[[#This Row],[OrderID]],4)) -> 1198 | AE16: =TEXT(tblOrders[[#This Row],[OrderDate_Clean]],"mmm-yyyy") -> Aug-2024 | AF16: =EOMONTH(tblOrders[[#This Row],[OrderDate_Clean]],0) -> 45535 | AG16: GRACE | AH16: =IF(tblOrders[[#This Row],[Discount]]="",0,IF(ISNUMBER(tblOrders[[#This Row],[Discount]]),tblOrders[[#This Row],[Discount]],VALUE(SUBSTITUTE(TRIM(tblOrders[[#This Row],[Discount]]),"%",""))/100)) -> 0
A17: ORD-1198 | B17: 08/16/2024 | C17: Grace Anderson | D17: east | E17: Multan | F17: Cloth ing | G17: Formal Shirt | H17: Online | I17: 10 | J17: 498.33 | K17: 0 | L17: credit card | M17: PENDING | N17: C. Osei | O17: VIP customer | P17: =PROPER(TRIM(C17)) -> Grace Anderson | Q17: =IF(OR(PROPER(TRIM(tblOrders[[#This Row],[Region]]))="Nort",PROPER(TRIM(tblOrders[[#This Row],[Region]]))="Northh"),"North",PROPER(TRIM(tblOrders[[#This Row],[Region]]))) -> East | R17: =IF(PROPER(TRIM(F17))="Cloth Ing","Clothing",IF(PROPER(TRIM(F17))="Electronic","Electronics",IF(PROPER(TRIM(F17))="Grocery","Groceries",SUBSTITUTE(PROPER(TRIM(F17)),"Stationary","Stationery")))) -> Clothing | S17: =IF(LOWER(TRIM(H17))="online","Online",IF(OR(LOWER(TRIM(H17))="in-store",LOWER(TRIM(H17))="in store",LOWER(TRIM(H17))="instore"),"In-Store",PROPER(TRIM(H17)))) -> Online | T17: =IF(UPPER(TRIM(L17))="CC","Credit Card",PROPER(TRIM(L17))) -> Credit Card | U17: =IF(PROPER(TRIM(M17))="Complete","Completed",IF(PROPER(TRIM(M17))="Canceled","Cancelled",PROPER(TRIM(M17)))) -> Pending | V17: =IFERROR(VALUE(TRIM(I17)),"") -> 10 | W17: =IFERROR(VALUE(SUBSTITUTE(TRIM(J17),"$","")),"") -> 498.33 | X17: =IFERROR(IF(ISNUMBER(tblOrders[[#This Row],[OrderDate]]),tblOrders[[#This Row],[OrderDate]],IFERROR(DATEVALUE(tblOrders[[#This Row],[OrderDate]]),DATE(IF(LEN(TRIM(tblOrders[[#This Row],[OrderDate]]))=8,2000+VALUE(RIGHT(TRIM(tblOrders[[#This Row],[OrderDate]]),2)),VALUE(RIGHT(TRIM(tblOrders[[#This Row],[OrderDate]]),4))),VALUE(MID(TRIM(tblOrders[[#This Row],[OrderDate]]),4,2)),VALUE(LEFT(TRIM(tblOrders[[#This Row],[OrderDate]]),2))))),"CHECK MANUALLY") -> 45520 | Y17: =IF(K17="",0,K17) -> 0 | Z17: =TRIM(CLEAN(tblOrders[[#This Row],[Notes]])) -> VIP customer | AA17: =IF(OR(V17="",W17=""),"Review",IF(V17*W17>=1000,"High Value","Standard")) -> High Value | AB17: =IF(OR(tblOrders[[#This Row],[Quantity_Clean]]="",tblOrders[[#This Row],[UnitPrice_Clean]]=""),0,tblOrders[[#This Row],[Quantity_Clean]]*tblOrders[[#This Row],[UnitPrice_Clean]]) -> 4983.3 | AC17: =UPPER(TRIM(tblOrders[[#This Row],[OrderID]])) -> ORD-1198 | AD17: =VALUE(RIGHT(tblOrders[[#This Row],[OrderID]],4)) -> 1198 | AE17: =TEXT(tblOrders[[#This Row],[OrderDate_Clean]],"mmm-yyyy") -> Aug-2024 | AF17: =EOMONTH(tblOrders[[#This Row],[OrderDate_Clean]],0) -> 45535 | AG17: Grace | AH17: =IF(tblOrders[[#This Row],[Discount]]="",0,IF(ISNUMBER(tblOrders[[#This Row],[Discount]]),tblOrders[[#This Row],[Discount]],VALUE(SUBSTITUTE(TRIM(tblOrders[[#This Row],[Discount]]),"%",""))/100)) -> 0
A18: ORD-1173 | B18: 06/01/2024 | C18: Daniel Raza | D18: West | E18: Quetta | F18: Cloth ing | G18: Formal Shirt | H18: online | I18: 8 | J18: 494.24 | K18: 0.1 | L18: Cash | M18: Refunded | O18: Follow up needed | P18: =PROPER(TRIM(C18)) -> Daniel Raza | Q18: =IF(OR(PROPER(TRIM(tblOrders[[#This Row],[Region]]))="Nort",PROPER(TRIM(tblOrders[[#This Row],[Region]]))="Northh"),"North",PROPER(TRIM(tblOrders[[#This Row],[Region]]))) -> West | R18: =IF(PROPER(TRIM(F18))="Cloth Ing","Clothing",IF(PROPER(TRIM(F18))="Electronic","Electronics",IF(PROPER(TRIM(F18))="Grocery","Groceries",SUBSTITUTE(PROPER(TRIM(F18)),"Stationary","Stationery")))) -> Clothing | S18: =IF(LOWER(TRIM(H18))="online","Online",IF(OR(LOWER(TRIM(H18))="in-store",LOWER(TRIM(H18))="in store",LOWER(TRIM(H18))="instore"),"In-Store",PROPER(TRIM(H18)))) -> Online | T18: =IF(UPPER(TRIM(L18))="CC","Credit Card",PROPER(TRIM(L18))) -> Cash | U18: =IF(PROPER(TRIM(M18))="Complete","Completed",IF(PROPER(TRIM(M18))="Canceled","Cancelled",PROPER(TRIM(M18)))) -> Refunded | V18: =IFERROR(VALUE(TRIM(I18)),"") -> 8 | W18: =IFERROR(VALUE(SUBSTITUTE(TRIM(J18),"$","")),"") -> 494.24 | X18: =IFERROR(IF(ISNUMBER(tblOrders[[#This Row],[OrderDate]]),tblOrders[[#This Row],[OrderDate]],IFERROR(DATEVALUE(tblOrders[[#This Row],[OrderDate]]),DATE(IF(LEN(TRIM(tblOrders[[#This Row],[OrderDate]]))=8,2000+VALUE(RIGHT(TRIM(tblOrders[[#This Row],[OrderDate]]),2)),VALUE(RIGHT(TRIM(tblOrders[[#This Row],[OrderDate]]),4))),VALUE(MID(TRIM(tblOrders[[#This Row],[OrderDate]]),4,2)),VALUE(LEFT(TRIM(tblOrders[[#This Row],[OrderDate]]),2))))),"CHECK MANUALLY") -> 45444 | Y18: =IF(K18="",0,K18) -> 0.1 | Z18: =TRIM(CLEAN(tblOrders[[#This Row],[Notes]])) -> Follow up needed | AA18: =IF(OR(V18="",W18=""),"Review",IF(V18*W18>=1000,"High Value","Standard")) -> High Value | AB18: =IF(OR(tblOrders[[#This Row],[Quantity_Clean]]="",tblOrders[[#This Row],[UnitPrice_Clean]]=""),0,tblOrders[[#This Row],[Quantity_Clean]]*tblOrders[[#This Row],[UnitPrice_Clean]]) -> 3953.92 | AC18: =UPPER(TRIM(tblOrders[[#This Row],[OrderID]])) -> ORD-1173 | AD18: =VALUE(RIGHT(tblOrders[[#This Row],[OrderID]],4)) -> 1173 | AE18: =TEXT(tblOrders[[#This Row],[OrderDate_Clean]],"mmm-yyyy") -> Jun-2024 | AF18: =EOMONTH(tblOrders[[#This Row],[OrderDate_Clean]],0) -> 45473 | AG18: Daniel | AH18: =IF(tblOrders[[#This Row],[Discount]]="",0,IF(ISNUMBER(tblOrders[[#This Row],[Discount]]),tblOrders[[#This Row],[Discount]],VALUE(SUBSTITUTE(TRIM(tblOrders[[#This Row],[Discount]]),"%",""))/100)) -> 0.1
A19: ORD-1224 | B19: 04/08/2024 | C19: Emily Johnson | D19: West | E19: Quetta | F19: Cloth ing | G19: Running Shoes | H19: In-Store | I19: 8 | J19: 383.31 | K19: 0.2 | L19: CREDIT CARD | M19: Completed | N19: E. Tanaka | O19: Bulk order - business account | P19: =PROPER(TRIM(C19)) -> Emily Johnson | Q19: =IF(OR(PROPER(TRIM(tblOrders[[#This Row],[Region]]))="Nort",PROPER(TRIM(tblOrders[[#This Row],[Region]]))="Northh"),"North",PROPER(TRIM(tblOrders[[#This Row],[Region]]))) -> West | R19: =IF(PROPER(TRIM(F19))="Cloth Ing","Clothing",IF(PROPER(TRIM(F19))="Electronic","Electronics",IF(PROPER(TRIM(F19))="Grocery","Groceries",SUBSTITUTE(PROPER(TRIM(F19)),"Stationary","Stationery")))) -> Clothing | S19: =IF(LOWER(TRIM(H19))="online","Online",IF(OR(LOWER(TRIM(H19))="in-store",LOWER(TRIM(H19))="in store",LOWER(TRIM(H19))="instore"),"In-Store",PROPER(TRIM(H19)))) -> In-Store | T19: =IF(UPPER(TRIM(L19))="CC","Credit Card",PROPER(TRIM(L19))) -> Credit Card | U19: =IF(PROPER(TRIM(M19))="Complete","Completed",IF(PROPER(TRIM(M19))="Canceled","Cancelled",PROPER(TRIM(M19)))) -> Completed | V19: =IFERROR(VALUE(TRIM(I19)),"") -> 8 | W19: =IFERROR(VALUE(SUBSTITUTE(TRIM(J19),"$","")),"") -> 383.31 | X19: =IFERROR(IF(ISNUMBER(tblOrders[[#This Row],[OrderDate]]),tblOrders[[#This Row],[OrderDate]],IFERROR(DATEVALUE(tblOrders[[#This Row],[OrderDate]]),DATE(IF(LEN(TRIM(tblOrders[[#This Row],[OrderDate]]))=8,2000+VALUE(RIGHT(TRIM(tblOrders[[#This Row],[OrderDate]]),2)),VALUE(RIGHT(TRIM(tblOrders[[#This Row],[OrderDate]]),4))),VALUE(MID(TRIM(tblOrders[[#This Row],[OrderDate]]),4,2)),VALUE(LEFT(TRIM(tblOrders[[#This Row],[OrderDate]]),2))))),"CHECK MANUALLY") -> 45390 | Y19: =IF(K19="",0,K19) -> 0.2 | Z19: =TRIM(CLEAN(tblOrders[[#This Row],[Notes]])) -> Bulk order - business account | AA19: =IF(OR(V19="",W19=""),"Review",IF(V19*W19>=1000,"High Value","Standard")) -> High Value | AB19: =IF(OR(tblOrders[[#This Row],[Quantity_Clean]]="",tblOrders[[#This Row],[UnitPrice_Clean]]=""),0,tblOrders[[#This Row],[Quantity_Clean]]*tblOrders[[#This Row],[UnitPrice_Clean]]) -> 3066.48 | AC19: =UPPER(TRIM(tblOrders[[#This Row],[OrderID]])) -> ORD-1224 | AD19: =VALUE(RIGHT(tblOrders[[#This Row],[OrderID]],4)) -> 1224 | AE19: =TEXT(tblOrders[[#This Row],[OrderDate_Clean]],"mmm-yyyy") -> Apr-2024 | AF19: =EOMONTH(tblOrders[[#This Row],[OrderDate_Clean]],0) -> 45412 | AG19: Emily | AH19: =IF(tblOrders[[#This Row],[Discount]]="",0,IF(ISNUMBER(tblOrders[[#This Row],[Discount]]),tblOrders[[#This Row],[Discount]],VALUE(SUBSTITUTE(TRIM(tblOrders[[#This Row],[Discount]]),"%",""))/100)) -> 0.2
A20: ORD-1082 | B20: 06/07/2024 | C20: John Brown | D20: West | E20: Quetta | F20: Cloth ing | G20: Running Shoes | H20: Online | I20: 10 | J20: 227.71 | K20: 0 | L20: cash | M20: COMPLETED | N20: E. Tanaka | P20: =PROPER(TRIM(C20)) -> John Brown | Q20: =IF(OR(PROPER(TRIM(tblOrders[[#This Row],[Region]]))="Nort",PROPER(TRIM(tblOrders[[#This Row],[Region]]))="Northh"),"North",PROPER(TRIM(tblOrders[[#This Row],[Region]]))) -> West | R20: =IF(PROPER(TRIM(F20))="Cloth Ing","Clothing",IF(PROPER(TRIM(F20))="Electronic","Electronics",IF(PROPER(TRIM(F20))="Grocery","Groceries",SUBSTITUTE(PROPER(TRIM(F20)),"Stationary","Stationery")))) -> Clothing | S20: =IF(LOWER(TRIM(H20))="online","Online",IF(OR(LOWER(TRIM(H20))="in-store",LOWER(TRIM(H20))="in store",LOWER(TRIM(H20))="instore"),"In-Store",PROPER(TRIM(H20)))) -> Online | T20: =IF(UPPER(TRIM(L20))="CC","Credit Card",PROPER(TRIM(L20))) -> Cash | U20: =IF(PROPER(TRIM(M20))="Complete","Completed",IF(PROPER(TRIM(M20))="Canceled","Cancelled",PROPER(TRIM(M20)))) -> Completed | V20: =IFERROR(VALUE(TRIM(I20)),"") -> 10 | W20: =IFERROR(VALUE(SUBSTITUTE(TRIM(J20),"$","")),"") -> 227.71 | X20: =IFERROR(IF(ISNUMBER(tblOrders[[#This Row],[OrderDate]]),tblOrders[[#This Row],[OrderDate]],IFERROR(DATEVALUE(tblOrders[[#This Row],[OrderDate]]),DATE(IF(LEN(TRIM(tblOrders[[#This Row],[OrderDate]]))=8,2000+VALUE(RIGHT(TRIM(tblOrders[[#This Row],[OrderDate]]),2)),VALUE(RIGHT(TRIM(tblOrders[[#This Row],[OrderDate]]),4))),VALUE(MID(TRIM(tblOrders[[#This Row],[OrderDate]]),4,2)),VALUE(LEFT(TRIM(tblOrders[[#This Row],[OrderDate]]),2))))),"CHECK MANUALLY") -> 45450 | Y20: =IF(K20="",0,K20) -> 0 | Z20: =TRIM(CLEAN(tblOrders[[#This Row],[Notes]])) | AA20: =IF(OR(V20="",W20=""),"Review",IF(V20*W20>=1000,"High Value","Standard")) -> High Value | AB20: =IF(OR(tblOrders[[#This Row],[Quantity_Clean]]="",tblOrders[[#This Row],[UnitPrice_Clean]]=""),0,tblOrders[[#This Row],[Quantity_Clean]]*tblOrders[[#This Row],[UnitPrice_Clean]]) -> 2277.1 | AC20: =UPPER(TRIM(tblOrders[[#This Row],[OrderID]])) -> ORD-1082 | AD20: =VALUE(RIGHT(tblOrders[[#This Row],[OrderID]],4)) -> 1082 | AE20: =TEXT(tblOrders[[#This Row],[OrderDate_Clean]],"mmm-yyyy") -> Jun-2024 | AF20: =EOMONTH(tblOrders[[#This Row],[OrderDate_Clean]],0) -> 45473 | AG20: John | AH20: =IF(tblOrders[[#This Row],[Discount]]="",0,IF(ISNUMBER(tblOrders[[#This Row],[Discount]]),tblOrders[[#This Row],[Discount]],VALUE(SUBSTITUTE(TRIM(tblOrders[[#This Row],[Discount]]),"%",""))/100)) -> 0
A21: ORD-1179 | B21: 25/03/2024 | C21: DAVID ALI | D21: east | E21: Multan | F21: Cloth ing | G21: Running Shoes | H21: In-store | I21: 10 | J21: 219.66 | L21: Debit card | M21: cancelled | N21: B. Fernandes | O21: Gift wrap requested | P21: =PROPER(TRIM(C21)) -> David Ali | Q21: =IF(OR(PROPER(TRIM(tblOrders[[#This Row],[Region]]))="Nort",PROPER(TRIM(tblOrders[[#This Row],[Region]]))="Northh"),"North",PROPER(TRIM(tblOrders[[#This Row],[Region]]))) -> East | R21: =IF(PROPER(TRIM(F21))="Cloth Ing","Clothing",IF(PROPER(TRIM(F21))="Electronic","Electronics",IF(PROPER(TRIM(F21))="Grocery","Groceries",SUBSTITUTE(PROPER(TRIM(F21)),"Stationary","Stationery")))) -> Clothing | S21: =IF(LOWER(TRIM(H21))="online","Online",IF(OR(LOWER(TRIM(H21))="in-store",LOWER(TRIM(H21))="in store",LOWER(TRIM(H21))="instore"),"In-Store",PROPER(TRIM(H21)))) -> In-Store | T21: =IF(UPPER(TRIM(L21))="CC","Credit Card",PROPER(TRIM(L21))) -> Debit Card | U21: =IF(PROPER(TRIM(M21))="Complete","Completed",IF(PROPER(TRIM(M21))="Canceled","Cancelled",PROPER(TRIM(M21)))) -> Cancelled | V21: =IFERROR(VALUE(TRIM(I21)),"") -> 10 | W21: =IFERROR(VALUE(SUBSTITUTE(TRIM(J21),"$","")),"") -> 219.66 | X21: =IFERROR(IF(ISNUMBER(tblOrders[[#This Row],[OrderDate]]),tblOrders[[#This Row],[OrderDate]],IFERROR(DATEVALUE(tblOrders[[#This Row],[OrderDate]]),DATE(IF(LEN(TRIM(tblOrders[[#This Row],[OrderDate]]))=8,2000+VALUE(RIGHT(TRIM(tblOrders[[#This Row],[OrderDate]]),2)),VALUE(RIGHT(TRIM(tblOrders[[#This Row],[OrderDate]]),4))),VALUE(MID(TRIM(tblOrders[[#This Row],[OrderDate]]),4,2)),VALUE(LEFT(TRIM(tblOrders[[#This Row],[OrderDate]]),2))))),"CHECK MANUALLY") -> 45376 | Y21: =IF(K21="",0,K21) -> 0 | Z21: =TRIM(CLEAN(tblOrders[[#This Row],[Notes]])) -> Gift wrap requested | AA21: =IF(OR(V21="",W21=""),"Review",IF(V21*W21>=1000,"High Value","Standard")) -> High Value | AB21: =IF(OR(tblOrders[[#This Row],[Quantity_Clean]]="",tblOrders[[#This Row],[UnitPrice_Clean]]=""),0,tblOrders[[#This Row],[Quantity_Clean]]*tblOrders[[#This Row],[UnitPrice_Clean]]) -> 2196.6 | AC21: =UPPER(TRIM(tblOrders[[#This Row],[OrderID]])) -> ORD-1179 | AD21: =VALUE(RIGHT(tblOrders[[#This Row],[OrderID]],4)) -> 1179 | AE21: =TEXT(tblOrders[[#This Row],[OrderDate_Clean]],"mmm-yyyy") -> Mar-2024 | AF21: =EOMONTH(tblOrders[[#This Row],[OrderDate_Clean]],0) -> 45382 | AG21: DAVID | AH21: =IF(tblOrders[[#This Row],[Discount]]="",0,IF(ISNUMBER(tblOrders[[#This Row],[Discount]]),tblOrders[[#This Row],[Discount]],VALUE(SUBSTITUTE(TRIM(tblOrders[[#This Row],[Discount]]),"%",""))/100)) -> 0
A22: ORD-1002 | B22: August 23, 2024 | C22: Laura Lee | D22: East | E22: Multan | F22: Cloth ing | G22: Denim Jacket | H22: Online | I22: 6 | J22: 193.06 | L22: CC | M22: refunded | N22: A. Malik | O22: Customer called twice | P22: =PROPER(TRIM(C22)) -> Laura Lee | Q22: =IF(OR(PROPER(TRIM(tblOrders[[#This Row],[Region]]))="Nort",PROPER(TRIM(tblOrders[[#This Row],[Region]]))="Northh"),"North",PROPER(TRIM(tblOrders[[#This Row],[Region]]))) -> East | R22: =IF(PROPER(TRIM(F22))="Cloth Ing","Clothing",IF(PROPER(TRIM(F22))="Electronic","Electronics",IF(PROPER(TRIM(F22))="Grocery","Groceries",SUBSTITUTE(PROPER(TRIM(F22)),"Stationary","Stationery")))) -> Clothing | S22: =IF(LOWER(TRIM(H22))="online","Online",IF(OR(LOWER(TRIM(H22))="in-store",LOWER(TRIM(H22))="in store",LOWER(TRIM(H22))="instore"),"In-Store",PROPER(TRIM(H22)))) -> Online | T22: =IF(UPPER(TRIM(L22))="CC","Credit Card",PROPER(TRIM(L22))) -> Credit Card | U22: =IF(PROPER(TRIM(M22))="Complete","Completed",IF(PROPER(TRIM(M22))="Canceled","Cancelled",PROPER(TRIM(M22)))) -> Refunded | V22: =IFERROR(VALUE(TRIM(I22)),"") -> 6 | W22: =IFERROR(VALUE(SUBSTITUTE(TRIM(J22),"$","")),"") -> 193.06 | X22: =IFERROR(IF(ISNUMBER(tblOrders[[#This Row],[OrderDate]]),tblOrders[[#This Row],[OrderDate]],IFERROR(DATEVALUE(tblOrders[[#This Row],[OrderDate]]),DATE(IF(LEN(TRIM(tblOrders[[#This Row],[OrderDate]]))=8,2000+VALUE(RIGHT(TRIM(tblOrders[[#This Row],[OrderDate]]),2)),VALUE(RIGHT(TRIM(tblOrders[[#This Row],[OrderDate]]),4))),VALUE(MID(TRIM(tblOrders[[#This Row],[OrderDate]]),4,2)),VALUE(LEFT(TRIM(tblOrders[[#This Row],[OrderDate]]),2))))),"CHECK MANUALLY") -> 45527 | Y22: =IF(K22="",0,K22) -> 0 | Z22: =TRIM(CLEAN(tblOrders[[#This Row],[Notes]])) -> Customer called twice | AA22: =IF(OR(V22="",W22=""),"Review",IF(V22*W22>=1000,"High Value","Standard")) -> High Value | AB22: =IF(OR(tblOrders[[#This Row],[Quantity_Clean]]="",tblOrders[[#This Row],[UnitPrice_Clean]]=""),0,tblOrders[[#This Row],[Quantity_Clean]]*tblOrders[[#This Row],[UnitPrice_Clean]]) -> 1158.36 | AC22: =UPPER(TRIM(tblOrders[[#This Row],[OrderID]])) -> ORD-1002 | AD22: =VALUE(RIGHT(tblOrders[[#This Row],[OrderID]],4)) -> 1002 | AE22: =TEXT(tblOrders[[#This Row],[OrderDate_Clean]],"mmm-yyyy") -> Aug-2024 | AF22: =EOMONTH(tblOrders[[#This Row],[OrderDate_Clean]],0) -> 45535 | AG22: Laura | AH22: =IF(tblOrders[[#This Row],[Discount]]="",0,IF(ISNUMBER(tblOrders[[#This Row],[Discount]]),tblOrders[[#This Row],[Discount]],VALUE(SUBSTITUTE(TRIM(tblOrders[[#This Row],[Discount]]),"%",""))/100)) -> 0
A23: ORD-1096 | B23: 2024-12-31 | C23: maria ahmed | D23: east | E23: Sialkot | F23: Cloth ing | G23: Formal Shirt | H23: online | I23: 10 | J23: 192.95 | K23: 0.05 | L23: CC | M23: Completed | N23: C. Osei | P23: =PROPER(TRIM(C23)) -> Maria Ahmed | Q23: =IF(OR(PROPER(TRIM(tblOrders[[#This Row],[Region]]))="Nort",PROPER(TRIM(tblOrders[[#This Row],[Region]]))="Northh"),"North",PROPER(TRIM(tblOrders[[#This Row],[Region]]))) -> East | R23: =IF(PROPER(TRIM(F23))="Cloth Ing","Clothing",IF(PROPER(TRIM(F23))="Electronic","Electronics",IF(PROPER(TRIM(F23))="Grocery","Groceries",SUBSTITUTE(PROPER(TRIM(F23)),"Stationary","Stationery")))) -> Clothing | S23: =IF(LOWER(TRIM(H23))="online","Online",IF(OR(LOWER(TRIM(H23))="in-store",LOWER(TRIM(H23))="in store",LOWER(TRIM(H23))="instore"),"In-Store",PROPER(TRIM(H23)))) -> Online | T23: =IF(UPPER(TRIM(L23))="CC","Credit Card",PROPER(TRIM(L23))) -> Credit Card | U23: =IF(PROPER(TRIM(M23))="Complete","Completed",IF(PROPER(TRIM(M23))="Canceled","Cancelled",PROPER(TRIM(M23)))) -> Completed | V23: =IFERROR(VALUE(TRIM(I23)),"") -> 10 | W23: =IFERROR(VALUE(SUBSTITUTE(TRIM(J23),"$","")),"") -> 192.95 | X23: =IFERROR(IF(ISNUMBER(tblOrders[[#This Row],[OrderDate]]),tblOrders[[#This Row],[OrderDate]],IFERROR(DATEVALUE(tblOrders[[#This Row],[OrderDate]]),DATE(IF(LEN(TRIM(tblOrders[[#This Row],[OrderDate]]))=8,2000+VALUE(RIGHT(TRIM(tblOrders[[#This Row],[OrderDate]]),2)),VALUE(RIGHT(TRIM(tblOrders[[#This Row],[OrderDate]]),4))),VALUE(MID(TRIM(tblOrders[[#This Row],[OrderDate]]),4,2)),VALUE(LEFT(TRIM(tblOrders[[#This Row],[OrderDate]]),2))))),"CHECK MANUALLY") -> 45657 | Y23: =IF(K23="",0,K23) -> 0.05 | Z23: =TRIM(CLEAN(tblOrders[[#This Row],[Notes]])) | AA23: =IF(OR(V23="",W23=""),"Review",IF(V23*W23>=1000,"High Value","Standard")) -> High Value | AB23: =IF(OR(tblOrders[[#This Row],[Quantity_Clean]]="",tblOrders[[#This Row],[UnitPrice_Clean]]=""),0,tblOrders[[#This Row],[Quantity_Clean]]*tblOrders[[#This Row],[UnitPrice_Clean]]) -> 1929.5 | AC23: =UPPER(TRIM(tblOrders[[#This Row],[OrderID]])) -> ORD-1096 | AD23: =VALUE(RIGHT(tblOrders[[#This Row],[OrderID]],4)) -> 1096 | AE23: =TEXT(tblOrders[[#This Row],[OrderDate_Clean]],"mmm-yyyy") -> Dec-2024 | AF23: =EOMONTH(tblOrders[[#This Row],[OrderDate_Clean]],0) -> 45657 | AG23: maria | AH23: =IF(tblOrders[[#This Row],[Discount]]="",0,IF(ISNUMBER(tblOrders[[#This Row],[Discount]]),tblOrders[[#This Row],[Discount]],VALUE(SUBSTITUTE(TRIM(tblOrders[[#This Row],[Discount]]),"%",""))/100)) -> 0.05
A24: ORD-1049 | B24: 21-Oct-24 | C24: HINA SMITH | D24: east | E24: Multan | F24: Cloth ing | G24: Running Shoes | H24: In-Store | I24: 8 | J24: 103.61 | K24: 0.05 | L24: debit card | M24: pending | N24: C. Osei | O24: Leave at front desk | P24: =PROPER(TRIM(C24)) -> Hina Smith | Q24: =IF(OR(PROPER(TRIM(tblOrders[[#This Row],[Region]]))="Nort",PROPER(TRIM(tblOrders[[#This Row],[Region]]))="Northh"),"North",PROPER(TRIM(tblOrders[[#This Row],[Region]]))) -> East | R24: =IF(PROPER(TRIM(F24))="Cloth Ing","Clothing",IF(PROPER(TRIM(F24))="Electronic","Electronics",IF(PROPER(TRIM(F24))="Grocery","Groceries",SUBSTITUTE(PROPER(TRIM(F24)),"Stationary","Stationery")))) -> Clothing | S24: =IF(LOWER(TRIM(H24))="online","Online",IF(OR(LOWER(TRIM(H24))="in-store",LOWER(TRIM(H24))="in store",LOWER(TRIM(H24))="instore"),"In-Store",PROPER(TRIM(H24)))) -> In-Store | T24: =IF(UPPER(TRIM(L24))="CC","Credit Card",PROPER(TRIM(L24))) -> Debit Card | U24: =IF(PROPER(TRIM(M24))="Complete","Completed",IF(PROPER(TRIM(M24))="Canceled","Cancelled",PROPER(TRIM(M24)))) -> Pending | V24: =IFERROR(VALUE(TRIM(I24)),"") -> 8 | W24: =IFERROR(VALUE(SUBSTITUTE(TRIM(J24),"$","")),"") -> 103.61 | X24: =IFERROR(IF(ISNUMBER(tblOrders[[#This Row],[OrderDate]]),tblOrders[[#This Row],[OrderDate]],IFERROR(DATEVALUE(tblOrders[[#This Row],[OrderDate]]),DATE(IF(LEN(TRIM(tblOrders[[#This Row],[OrderDate]]))=8,2000+VALUE(RIGHT(TRIM(tblOrders[[#This Row],[OrderDate]]),2)),VALUE(RIGHT(TRIM(tblOrders[[#This Row],[OrderDate]]),4))),VALUE(MID(TRIM(tblOrders[[#This Row],[OrderDate]]),4,2)),VALUE(LEFT(TRIM(tblOrders[[#This Row],[OrderDate]]),2))))),"CHECK MANUALLY") -> 45586 | Y24: =IF(K24="",0,K24) -> 0.05 | Z24: =TRIM(CLEAN(tblOrders[[#This Row],[Notes]])) -> Leave at front desk | AA24: =IF(OR(V24="",W24=""),"Review",IF(V24*W24>=1000,"High Value","Standard")) -> Standard | AB24: =IF(OR(tblOrders[[#This Row],[Quantity_Clean]]="",tblOrders[[#This Row],[UnitPrice_Clean]]=""),0,tblOrders[[#This Row],[Quantity_Clean]]*tblOrders[[#This Row],[UnitPrice_Clean]]) -> 828.88 | AC24: =UPPER(TRIM(tblOrders[[#This Row],[OrderID]])) -> ORD-1049 | AD24: =VALUE(RIGHT(tblOrders[[#This Row],[OrderID]],4)) -> 1049 | AE24: =TEXT(tblOrders[[#This Row],[OrderDate_Clean]],"mmm-yyyy") -> Oct-2024 | AF24: =EOMONTH(tblOrders[[#This Row],[OrderDate_Clean]],0) -> 45596 | AG24: HINA | AH24: =IF(tblOrders[[#This Row],[Discount]]="",0,IF(ISNUMBER(tblOrders[[#This Row],[Discount]]),tblOrders[[#This Row],[Discount]],VALUE(SUBSTITUTE(TRIM(tblOrders[[#This Row],[Discount]]),"%",""))/100)) -> 0.05
A25: ORD-1226 | B25: April 30, 2024 | C25: zara taylor | D25: South | E25: Hyderabad | F25: Cloth ing | G25: Running Shoes | H25: In-Store | I25: 8 | J25: 69.91 | L25: credit card | M25: Refunded | N25: C. Osei | P25: =PROPER(TRIM(C25)) -> Zara Taylor | Q25: =IF(OR(PROPER(TRIM(tblOrders[[#This Row],[Region]]))="Nort",PROPER(TRIM(tblOrders[[#This Row],[Region]]))="Northh"),"North",PROPER(TRIM(tblOrders[[#This Row],[Region]]))) -> South | R25: =IF(PROPER(TRIM(F25))="Cloth Ing","Clothing",IF(PROPER(TRIM(F25))="Electronic","Electronics",IF(PROPER(TRIM(F25))="Grocery","Groceries",SUBSTITUTE(PROPER(TRIM(F25)),"Stationary","Stationery")))) -> Clothing | S25: =IF(LOWER(TRIM(H25))="online","Online",IF(OR(LOWER(TRIM(H25))="in-store",LOWER(TRIM(H25))="in store",LOWER(TRIM(H25))="instore"),"In-Store",PROPER(TRIM(H25)))) -> In-Store | T25: =IF(UPPER(TRIM(L25))="CC","Credit Card",PROPER(TRIM(L25))) -> Credit Card | U25: =IF(PROPER(TRIM(M25))="Complete","Completed",IF(PROPER(TRIM(M25))="Canceled","Cancelled",PROPER(TRIM(M25)))) -> Refunded | V25: =IFERROR(VALUE(TRIM(I25)),"") -> 8 | W25: =IFERROR(VALUE(SUBSTITUTE(TRIM(J25),"$","")),"") -> 69.91 | X25: =IFERROR(IF(ISNUMBER(tblOrders[[#This Row],[OrderDate]]),tblOrders[[#This Row],[OrderDate]],IFERROR(DATEVALUE(tblOrders[[#This Row],[OrderDate]]),DATE(IF(LEN(TRIM(tblOrders[[#This Row],[OrderDate]]))=8,2000+VALUE(RIGHT(TRIM(tblOrders[[#This Row],[OrderDate]]),2)),VALUE(RIGHT(TRIM(tblOrders[[#This Row],[OrderDate]]),4))),VALUE(MID(TRIM(tblOrders[[#This Row],[OrderDate]]),4,2)),VALUE(LEFT(TRIM(tblOrders[[#This Row],[OrderDate]]),2))))),"CHECK MANUALLY") -> 45412 | Y25: =IF(K25="",0,K25) -> 0 | Z25: =TRIM(CLEAN(tblOrders[[#This Row],[Notes]])) | AA25: =IF(OR(V25="",W25=""),"Review",IF(V25*W25>=1000,"High Value","Standard")) -> Standard | AB25: =IF(OR(tblOrders[[#This Row],[Quantity_Clean]]="",tblOrders[[#This Row],[UnitPrice_Clean]]=""),0,tblOrders[[#This Row],[Quantity_Clean]]*tblOrders[[#This Row],[UnitPrice_Clean]]) -> 559.28 | AC25: =UPPER(TRIM(tblOrders[[#This Row],[OrderID]])) -> ORD-1226 | AD25: =VALUE(RIGHT(tblOrders[[#This Row],[OrderID]],4)) -> 1226 | AE25: =TEXT(tblOrders[[#This Row],[OrderDate_Clean]],"mmm-yyyy") -> Apr-2024 | AF25: =EOMONTH(tblOrders[[#This Row],[OrderDate_Clean]],0) -> 45412 | AG25: zara | AH25: =IF(tblOrders[[#This Row],[Discount]]="",0,IF(ISNUMBER(tblOrders[[#This Row],[Discount]]),tblOrders[[#This Row],[Discount]],VALUE(SUBSTITUTE(TRIM(tblOrders[[#This Row],[Discount]]),"%",""))/100)) -> 0
A26: ORD-1059 | B26: January 31, 2024 | C26: ROBERT LEE | D26: West | E26: Peshawar | F26: Cloth ing | G26: Denim Jacket | H26: instore | I26: 2 | J26: 47.26 | K26: 0.1 | L26: bank transfer | M26: COMPLETED | N26: E. Tanaka | O26: Bulk order - business account | P26: =PROPER(TRIM(C26)) -> Robert Lee | Q26: =IF(OR(PROPER(TRIM(tblOrders[[#This Row],[Region]]))="Nort",PROPER(TRIM(tblOrders[[#This Row],[Region]]))="Northh"),"North",PROPER(TRIM(tblOrders[[#This Row],[Region]]))) -> West | R26: =IF(PROPER(TRIM(F26))="Cloth Ing","Clothing",IF(PROPER(TRIM(F26))="Electronic","Electronics",IF(PROPER(TRIM(F26))="Grocery","Groceries",SUBSTITUTE(PROPER(TRIM(F26)),"Stationary","Stationery")))) -> Clothing | S26: =IF(LOWER(TRIM(H26))="online","Online",IF(OR(LOWER(TRIM(H26))="in-store",LOWER(TRIM(H26))="in store",LOWER(TRIM(H26))="instore"),"In-Store",PROPER(TRIM(H26)))) -> In-Store | T26: =IF(UPPER(TRIM(L26))="CC","Credit Card",PROPER(TRIM(L26))) -> Bank Transfer | U26: =IF(PROPER(TRIM(M26))="Complete","Completed",IF(PROPER(TRIM(M26))="Canceled","Cancelled",PROPER(TRIM(M26)))) -> Completed | V26: =IFERROR(VALUE(TRIM(I26)),"") -> 2 | W26: =IFERROR(VALUE(SUBSTITUTE(TRIM(J26),"$","")),"") -> 47.26 | X26: =IFERROR(IF(ISNUMBER(tblOrders[[#This Row],[OrderDate]]),tblOrders[[#This Row],[OrderDate]],IFERROR(DATEVALUE(tblOrders[[#This Row],[OrderDate]]),DATE(IF(LEN(TRIM(tblOrders[[#This Row],[OrderDate]]))=8,2000+VALUE(RIGHT(TRIM(tblOrders[[#This Row],[OrderDate]]),2)),VALUE(RIGHT(TRIM(tblOrders[[#This Row],[OrderDate]]),4))),VALUE(MID(TRIM(tblOrders[[#This Row],[OrderDate]]),4,2)),VALUE(LEFT(TRIM(tblOrders[[#This Row],[OrderDate]]),2))))),"CHECK MANUALLY") -> 45322 | Y26: =IF(K26="",0,K26) -> 0.1 | Z26: =TRIM(CLEAN(tblOrders[[#This Row],[Notes]])) -> Bulk order - business account | AA26: =IF(OR(V26="",W26=""),"Review",IF(V26*W26>=1000,"High Value","Standard")) -> Standard | AB26: =IF(OR(tblOrders[[#This Row],[Quantity_Clean]]="",tblOrders[[#This Row],[UnitPrice_Clean]]=""),0,tblOrders[[#This Row],[Quantity_Clean]]*tblOrders[[#This Row],[UnitPrice_Clean]]) -> 94.52 | AC26: =UPPER(TRIM(tblOrders[[#This Row],[OrderID]])) -> ORD-1059 | AD26: =VALUE(RIGHT(tblOrders[[#This Row],[OrderID]],4)) -> 1059 | AE26: =TEXT(tblOrders[[#This Row],[OrderDate_Clean]],"mmm-yyyy") -> Jan-2024 | AF26: =EOMONTH(tblOrders[[#This Row],[OrderDate_Clean]],0) -> 45322 | AG26: ROBERT | AH26: =IF(tblOrders[[#This Row],[Discount]]="",0,IF(ISNUMBER(tblOrders[[#This Row],[Discount]]),tblOrders[[#This Row],[Discount]],VALUE(SUBSTITUTE(TRIM(tblOrders[[#This Row],[Discount]]),"%",""))/100)) -> 0.1
A27: ORD-1171 | B27: 04/23/2024 | C27: Fatima Iqbal | D27: west | E27: Peshawar | F27: Cloth ing | G27: Denim Jacket | H27: In-Store | I27: 12 | L27: cash | M27: refunded | N27: B. Fernandes | O27: VIP customer | P27: =PROPER(TRIM(C27)) -> Fatima Iqbal | Q27: =IF(OR(PROPER(TRIM(tblOrders[[#This Row],[Region]]))="Nort",PROPER(TRIM(tblOrders[[#This Row],[Region]]))="Northh"),"North",PROPER(TRIM(tblOrders[[#This Row],[Region]]))) -> West | R27: =IF(PROPER(TRIM(F27))="Cloth Ing","Clothing",IF(PROPER(TRIM(F27))="Electronic","Electronics",IF(PROPER(TRIM(F27))="Grocery","Groceries",SUBSTITUTE(PROPER(TRIM(F27)),"Stationary","Stationery")))) -> Clothing | S27: =IF(LOWER(TRIM(H27))="online","Online",IF(OR(LOWER(TRIM(H27))="in-store",LOWER(TRIM(H27))="in store",LOWER(TRIM(H27))="instore"),"In-Store",PROPER(TRIM(H27)))) -> In-Store | T27: =IF(UPPER(TRIM(L27))="CC","Credit Card",PROPER(TRIM(L27))) -> Cash | U27: =IF(PROPER(TRIM(M27))="Complete","Completed",IF(PROPER(TRIM(M27))="Canceled","Cancelled",PROPER(TRIM(M27)))) -> Refunded | V27: =IFERROR(VALUE(TRIM(I27)),"") -> 12 | W27: =IFERROR(VALUE(SUBSTITUTE(TRIM(J27),"$","")),"") | X27: =IFERROR(IF(ISNUMBER(tblOrders[[#This Row],[OrderDate]]),tblOrders[[#This Row],[OrderDate]],IFERROR(DATEVALUE(tblOrders[[#This Row],[OrderDate]]),DATE(IF(LEN(TRIM(tblOrders[[#This Row],[OrderDate]]))=8,2000+VALUE(RIGHT(TRIM(tblOrders[[#This Row],[OrderDate]]),2)),VALUE(RIGHT(TRIM(tblOrders[[#This Row],[OrderDate]]),4))),VALUE(MID(TRIM(tblOrders[[#This Row],[OrderDate]]),4,2)),VALUE(LEFT(TRIM(tblOrders[[#This Row],[OrderDate]]),2))))),"CHECK MANUALLY") -> 45405 | Y27: =IF(K27="",0,K27) -> 0 | Z27: =TRIM(CLEAN(tblOrders[[#This Row],[Notes]])) -> VIP customer | AA27: =IF(OR(V27="",W27=""),"Review",IF(V27*W27>=1000,"High Value","Standard")) -> Review | AB27: =IF(OR(tblOrders[[#This Row],[Quantity_Clean]]="",tblOrders[[#This Row],[UnitPrice_Clean]]=""),0,tblOrders[[#This Row],[Quantity_Clean]]*tblOrders[[#This Row],[UnitPrice_Clean]]) -> 0 | AC27: =UPPER(TRIM(tblOrders[[#This Row],[OrderID]])) -> ORD-1171 | AD27: =VALUE(RIGHT(tblOrders[[#This Row],[OrderID]],4)) -> 1171 | AE27: =TEXT(tblOrders[[#This Row],[OrderDate_Clean]],"mmm-yyyy") -> Apr-2024 | AF27: =EOMONTH(tblOrders[[#This Row],[OrderDate_Clean]],0) -> 45412 | AG27: Fatima | AH27: =IF(tblOrders[[#This Row],[Discount]]="",0,IF(ISNUMBER(tblOrders[[#This Row],[Discount]]),tblOrders[[#This Row],[Discount]],VALUE(SUBSTITUTE(TRIM(tblOrders[[#This Row],[Discount]]),"%",""))/100)) -> 0
A28: ORD-1228 | B28: October 22, 2024 | C28: sarah garcia | D28: West | E28: Peshawar | F28: Cloth ing | G28: Formal Shirt | H28: In-store | I28: 9 | L28: Cash | M28: pending | N28: B. Fernandes | O28: Bulk order - business account | P28: =PROPER(TRIM(C28)) -> Sarah Garcia | Q28: =IF(OR(PROPER(TRIM(tblOrders[[#This Row],[Region]]))="Nort",PROPER(TRIM(tblOrders[[#This Row],[Region]]))="Northh"),"North",PROPER(TRIM(tblOrders[[#This Row],[Region]]))) -> West | R28: =IF(PROPER(TRIM(F28))="Cloth Ing","Clothing",IF(PROPER(TRIM(F28))="Electronic","Electronics",IF(PROPER(TRIM(F28))="Grocery","Groceries",SUBSTITUTE(PROPER(TRIM(F28)),"Stationary","Stationery")))) -> Clothing | S28: =IF(LOWER(TRIM(H28))="online","Online",IF(OR(LOWER(TRIM(H28))="in-store",LOWER(TRIM(H28))="in store",LOWER(TRIM(H28))="instore"),"In-Store",PROPER(TRIM(H28)))) -> In-Store | T28: =IF(UPPER(TRIM(L28))="CC","Credit Card",PROPER(TRIM(L28))) -> Cash | U28: =IF(PROPER(TRIM(M28))="Complete","Completed",IF(PROPER(TRIM(M28))="Canceled","Cancelled",PROPER(TRIM(M28)))) -> Pending | V28: =IFERROR(VALUE(TRIM(I28)),"") -> 9 | W28: =IFERROR(VALUE(SUBSTITUTE(TRIM(J28),"$","")),"") | X28: =IFERROR(IF(ISNUMBER(tblOrders[[#This Row],[OrderDate]]),tblOrders[[#This Row],[OrderDate]],IFERROR(DATEVALUE(tblOrders[[#This Row],[OrderDate]]),DATE(IF(LEN(TRIM(tblOrders[[#This Row],[OrderDate]]))=8,2000+VALUE(RIGHT(TRIM(tblOrders[[#This Row],[OrderDate]]),2)),VALUE(RIGHT(TRIM(tblOrders[[#This Row],[OrderDate]]),4))),VALUE(MID(TRIM(tblOrders[[#This Row],[OrderDate]]),4,2)),VALUE(LEFT(TRIM(tblOrders[[#This Row],[OrderDate]]),2))))),"CHECK MANUALLY") -> 45587 | Y28: =IF(K28="",0,K28) -> 0 | Z28: =TRIM(CLEAN(tblOrders[[#This Row],[Notes]])) -> Bulk order - business account | AA28: =IF(OR(V28="",W28=""),"Review",IF(V28*W28>=1000,"High Value","Standard")) -> Review | AB28: =IF(OR(tblOrders[[#This Row],[Quantity_Clean]]="",tblOrders[[#This Row],[UnitPrice_Clean]]=""),0,tblOrders[[#This Row],[Quantity_Clean]]*tblOrders[[#This Row],[UnitPrice_Clean]]) -> 0 | AC28: =UPPER(TRIM(tblOrders[[#This Row],[OrderID]])) -> ORD-1228 | AD28: =VALUE(RIGHT(tblOrders[[#This Row],[OrderID]],4)) -> 1228 | AE28: =TEXT(tblOrders[[#This Row],[OrderDate_Clean]],"mmm-yyyy") -> Oct-2024 | AF28: =EOMONTH(tblOrders[[#This Row],[OrderDate_Clean]],0) -> 45596 | AG28: sarah | AH28: =IF(tblOrders[[#This Row],[Discount]]="",0,IF(ISNUMBER(tblOrders[[#This Row],[Discount]]),tblOrders[[#This Row],[Discount]],VALUE(SUBSTITUTE(TRIM(tblOrders[[#This Row],[Discount]]),"%",""))/100)) -> 0
A29: ORD-1157 | B29: 05/12/2024 | C29: Robert Qureshi | D29: SOUTH | E29: Karachi | F29: Clothing | G29: Cotton T-Shirt | H29: ONLINE | I29: 10 | J29: $75.12 | K29: 0.1 | L29: credit card | M29: cancelled | O29: Customer called twice | P29: =PROPER(TRIM(C29)) -> Robert Qureshi | Q29: =IF(OR(PROPER(TRIM(tblOrders[[#This Row],[Region]]))="Nort",PROPER(TRIM(tblOrders[[#This Row],[Region]]))="Northh"),"North",PROPER(TRIM(tblOrders[[#This Row],[Region]]))) -> South | R29: =IF(PROPER(TRIM(F29))="Cloth Ing","Clothing",IF(PROPER(TRIM(F29))="Electronic","Electronics",IF(PROPER(TRIM(F29))="Grocery","Groceries",SUBSTITUTE(PROPER(TRIM(F29)),"Stationary","Stationery")))) -> Clothing | S29: =IF(LOWER(TRIM(H29))="online","Online",IF(OR(LOWER(TRIM(H29))="in-store",LOWER(TRIM(H29))="in store",LOWER(TRIM(H29))="instore"),"In-Store",PROPER(TRIM(H29)))) -> Online | T29: =IF(UPPER(TRIM(L29))="CC","Credit Card",PROPER(TRIM(L29))) -> Credit Card | U29: =IF(PROPER(TRIM(M29))="Complete","Completed",IF(PROPER(TRIM(M29))="Canceled","Cancelled",PROPER(TRIM(M29)))) -> Cancelled | V29: =IFERROR(VALUE(TRIM(I29)),"") -> 10 | W29: =IFERROR(VALUE(SUBSTITUTE(TRIM(J29),"$","")),"") -> 75.12 | X29: =IFERROR(IF(ISNUMBER(tblOrders[[#This Row],[OrderDate]]),tblOrders[[#This Row],[OrderDate]],IFERROR(DATEVALUE(tblOrders[[#This Row],[OrderDate]]),DATE(IF(LEN(TRIM(tblOrders[[#This Row],[OrderDate]]))=8,2000+VALUE(RIGHT(TRIM(tblOrders[[#This Row],[OrderDate]]),2)),VALUE(RIGHT(TRIM(tblOrders[[#This Row],[OrderDate]]),4))),VALUE(MID(TRIM(tblOrders[[#This Row],[OrderDate]]),4,2)),VALUE(LEFT(TRIM(tblOrders[[#This Row],[OrderDate]]),2))))),"CHECK MANUALLY") -> 45424 | Y29: =IF(K29="",0,K29) -> 0.1 | Z29: =TRIM(CLEAN(tblOrders[[#This Row],[Notes]])) -> Customer called twice | AA29: =IF(OR(V29="",W29=""),"Review",IF(V29*W29>=1000,"High Value","Standard")) -> Standard | AB29: =IF(OR(tblOrders[[#This Row],[Quantity_Clean]]="",tblOrders[[#This Row],[UnitPrice_Clean]]=""),0,tblOrders[[#This Row],[Quantity_Clean]]*tblOrders[[#This Row],[UnitPrice_Clean]]) -> 751.2 | AC29: =UPPER(TRIM(tblOrders[[#This Row],[OrderID]])) -> ORD-1157 | AD29: =VALUE(RIGHT(tblOrders[[#This Row],[OrderID]],4)) -> 1157 | AE29: =TEXT(tblOrders[[#This Row],[OrderDate_Clean]],"mmm-yyyy") -> May-2024 | AF29: =EOMONTH(tblOrders[[#This Row],[OrderDate_Clean]],0) -> 45443 | AG29: Robert | AH29: =IF(tblOrders[[#This Row],[Discount]]="",0,IF(ISNUMBER(tblOrders[[#This Row],[Discount]]),tblOrders[[#This Row],[Discount]],VALUE(SUBSTITUTE(TRIM(tblOrders[[#This Row],[Discount]]),"%",""))/100)) -> 0.1
A30: ORD-1016 | B30: 07-Mar-24 | C30: James Ali | D30: SOUTH | E30: Hyderabad | F30: clothing | G30: Formal Shirt | H30: In-store | I30: 8 | J30: $454.54 | K30: 10% | L30: Credit Card | M30: Completed | N30: C. Osei | O30: Follow up needed | P30: =PROPER(TRIM(C30)) -> James Ali | Q30: =IF(OR(PROPER(TRIM(tblOrders[[#This Row],[Region]]))="Nort",PROPER(TRIM(tblOrders[[#This Row],[Region]]))="Northh"),"North",PROPER(TRIM(tblOrders[[#This Row],[Region]]))) -> South | R30: =IF(PROPER(TRIM(F30))="Cloth Ing","Clothing",IF(PROPER(TRIM(F30))="Electronic","Electronics",IF(PROPER(TRIM(F30))="Grocery","Groceries",SUBSTITUTE(PROPER(TRIM(F30)),"Stationary","Stationery")))) -> Clothing | S30: =IF(LOWER(TRIM(H30))="online","Online",IF(OR(LOWER(TRIM(H30))="in-store",LOWER(TRIM(H30))="in store",LOWER(TRIM(H30))="instore"),"In-Store",PROPER(TRIM(H30)))) -> In-Store | T30: =IF(UPPER(TRIM(L30))="CC","Credit Card",PROPER(TRIM(L30))) -> Credit Card | U30: =IF(PROPER(TRIM(M30))="Complete","Completed",IF(PROPER(TRIM(M30))="Canceled","Cancelled",PROPER(TRIM(M30)))) -> Completed | V30: =IFERROR(VALUE(TRIM(I30)),"") -> 8 | W30: =IFERROR(VALUE(SUBSTITUTE(TRIM(J30),"$","")),"") -> 454.54 | X30: =IFERROR(IF(ISNUMBER(tblOrders[[#This Row],[OrderDate]]),tblOrders[[#This Row],[OrderDate]],IFERROR(DATEVALUE(tblOrders[[#This Row],[OrderDate]]),DATE(IF(LEN(TRIM(tblOrders[[#This Row],[OrderDate]]))=8,2000+VALUE(RIGHT(TRIM(tblOrders[[#This Row],[OrderDate]]),2)),VALUE(RIGHT(TRIM(tblOrders[[#This Row],[OrderDate]]),4))),VALUE(MID(TRIM(tblOrders[[#This Row],[OrderDate]]),4,2)),VALUE(LEFT(TRIM(tblOrders[[#This Row],[OrderDate]]),2))))),"CHECK MANUALLY") -> 45358 | Y30: =IF(K30="",0,K30) -> 10% | Z30: =TRIM(CLEAN(tblOrders[[#This Row],[Notes]])) -> Follow up needed | AA30: =IF(OR(V30="",W30=""),"Review",IF(V30*W30>=1000,"High Value","Standard")) -> High Value | AB30: =IF(OR(tblOrders[[#This Row],[Quantity_Clean]]="",tblOrders[[#This Row],[UnitPrice_Clean]]=""),0,tblOrders[[#This Row],[Quantity_Clean]]*tblOrders[[#This Row],[UnitPrice_Clean]]) -> 3636.32 | AC30: =UPPER(TRIM(tblOrders[[#This Row],[OrderID]])) -> ORD-1016 | AD30: =VALUE(RIGHT(tblOrders[[#This Row],[OrderID]],4)) -> 1016 | AE30: =TEXT(tblOrders[[#This Row],[OrderDate_Clean]],"mmm-yyyy") -> Mar-2024 | AF30: =EOMONTH(tblOrders[[#This Row],[OrderDate_Clean]],0) -> 45382 | AG30: James | AH30: =IF(tblOrders[[#This Row],[Discount]]="",0,IF(ISNUMBER(tblOrders[[#This Row],[Discount]]),tblOrders[[#This Row],[Discount]],VALUE(SUBSTITUTE(TRIM(tblOrders[[#This Row],[Discount]]),"%",""))/100)) -> 0.1
A31: ORD-1047 | B31: 2024-06-15 | C31: Liam Farooq | D31: north | E31: Faisalabad | F31: clothing | G31: Cotton T-Shirt | H31: In Store | I31: 2 | J31: $353.43 | L31: CC | M31: Completed | N31: A. Malik | O31: Leave at front desk | P31: =PROPER(TRIM(C31)) -> Liam Farooq | Q31: =IF(OR(PROPER(TRIM(tblOrders[[#This Row],[Region]]))="Nort",PROPER(TRIM(tblOrders[[#This Row],[Region]]))="Northh"),"North",PROPER(TRIM(tblOrders[[#This Row],[Region]]))) -> North | R31: =IF(PROPER(TRIM(F31))="Cloth Ing","Clothing",IF(PROPER(TRIM(F31))="Electronic","Electronics",IF(PROPER(TRIM(F31))="Grocery","Groceries",SUBSTITUTE(PROPER(TRIM(F31)),"Stationary","Stationery")))) -> Clothing | S31: =IF(LOWER(TRIM(H31))="online","Online",IF(OR(LOWER(TRIM(H31))="in-store",LOWER(TRIM(H31))="in store",LOWER(TRIM(H31))="instore"),"In-Store",PROPER(TRIM(H31)))) -> In-Store | T31: =IF(UPPER(TRIM(L31))="CC","Credit Card",PROPER(TRIM(L31))) -> Credit Card | U31: =IF(PROPER(TRIM(M31))="Complete","Completed",IF(PROPER(TRIM(M31))="Canceled","Cancelled",PROPER(TRIM(M31)))) -> Completed | V31: =IFERROR(VALUE(TRIM(I31)),"") -> 2 | W31: =IFERROR(VALUE(SUBSTITUTE(TRIM(J31),"$","")),"") -> 353.43 | X31: =IFERROR(IF(ISNUMBER(tblOrders[[#This Row],[OrderDate]]),tblOrders[[#This Row],[OrderDate]],IFERROR(DATEVALUE(tblOrders[[#This Row],[OrderDate]]),DATE(IF(LEN(TRIM(tblOrders[[#This Row],[OrderDate]]))=8,2000+VALUE(RIGHT(TRIM(tblOrders[[#This Row],[OrderDate]]),2)),VALUE(RIGHT(TRIM(tblOrders[[#This Row],[OrderDate]]),4))),VALUE(MID(TRIM(tblOrders[[#This Row],[OrderDate]]),4,2)),VALUE(LEFT(TRIM(tblOrders[[#This Row],[OrderDate]]),2))))),"CHECK MANUALLY") -> 45458 | Y31: =IF(K31="",0,K31) -> 0 | Z31: =TRIM(CLEAN(tblOrders[[#This Row],[Notes]])) -> Leave at front desk | AA31: =IF(OR(V31="",W31=""),"Review",IF(V31*W31>=1000,"High Value","Standard")) -> Standard | AB31: =IF(OR(tblOrders[[#This Row],[Quantity_Clean]]="",tblOrders[[#This Row],[UnitPrice_Clean]]=""),0,tblOrders[[#This Row],[Quantity_Clean]]*tblOrders[[#This Row],[UnitPrice_Clean]]) -> 706.86 | AC31: =UPPER(TRIM(tblOrders[[#This Row],[OrderID]])) -> ORD-1047 | AD31: =VALUE(RIGHT(tblOrders[[#This Row],[OrderID]],4)) -> 1047 | AE31: =TEXT(tblOrders[[#This Row],[OrderDate_Clean]],"mmm-yyyy") -> Jun-2024 | AF31: =EOMONTH(tblOrders[[#This Row],[OrderDate_Clean]],0) -> 45473 | AG31: Liam | AH31: =IF(tblOrders[[#This Row],[Discount]]="",0,IF(ISNUMBER(tblOrders[[#This Row],[Discount]]),tblOrders[[#This Row],[Discount]],VALUE(SUBSTITUTE(TRIM(tblOrders[[#This Row],[Discount]]),"%",""))/100)) -> 0
A32: ORD-1230 | B32: 02/10/2024 | C32: Robert Raza | D32: East | E32: Sialkot | F32: CLOTHING | G32: Running Shoes | H32: ONLINE | I32: 3 | J32: 66.89 | L32: Bank Transfer | M32: Refunded | O32: Follow up needed | P32: =PROPER(TRIM(C32)) -> Robert Raza | Q32: =IF(OR(PROPER(TRIM(tblOrders[[#This Row],[Region]]))="Nort",PROPER(TRIM(tblOrders[[#This Row],[Region]]))="Northh"),"North",PROPER(TRIM(tblOrders[[#This Row],[Region]]))) -> East | R32: =IF(PROPER(TRIM(F32))="Cloth Ing","Clothing",IF(PROPER(TRIM(F32))="Electronic","Electronics",IF(PROPER(TRIM(F32))="Grocery","Groceries",SUBSTITUTE(PROPER(TRIM(F32)),"Stationary","Stationery")))) -> Clothing | S32: =IF(LOWER(TRIM(H32))="online","Online",IF(OR(LOWER(TRIM(H32))="in-store",LOWER(TRIM(H32))="in store",LOWER(TRIM(H32))="instore"),"In-Store",PROPER(TRIM(H32)))) -> Online | T32: =IF(UPPER(TRIM(L32))="CC","Credit Card",PROPER(TRIM(L32))) -> Bank Transfer | U32: =IF(PROPER(TRIM(M32))="Complete","Completed",IF(PROPER(TRIM(M32))="Canceled","Cancelled",PROPER(TRIM(M32)))) -> Refunded | V32: =IFERROR(VALUE(TRIM(I32)),"") -> 3 | W32: =IFERROR(VALUE(SUBSTITUTE(TRIM(J32),"$","")),"") -> 66.89 | X32: =IFERROR(IF(ISNUMBER(tblOrders[[#This Row],[OrderDate]]),tblOrders[[#This Row],[OrderDate]],IFERROR(DATEVALUE(tblOrders[[#This Row],[OrderDate]]),DATE(IF(LEN(TRIM(tblOrders[[#This Row],[OrderDate]]))=8,2000+VALUE(RIGHT(TRIM(tblOrders[[#This Row],[OrderDate]]),2)),VALUE(RIGHT(TRIM(tblOrders[[#This Row],[OrderDate]]),4))),VALUE(MID(TRIM(tblOrders[[#This Row],[OrderDate]]),4,2)),VALUE(LEFT(TRIM(tblOrders[[#This Row],[OrderDate]]),2))))),"CHECK MANUALLY") -> 45332 | Y32: =IF(K32="",0,K32) -> 0 | Z32: =TRIM(CLEAN(tblOrders[[#This Row],[Notes]])) -> Follow up needed | AA32: =IF(OR(V32="",W32=""),"Review",IF(V32*W32>=1000,"High Value","Standard")) -> Standard | AB32: =IF(OR(tblOrders[[#This Row],[Quantity_Clean]]="",tblOrders[[#This Row],[UnitPrice_Clean]]=""),0,tblOrders[[#This Row],[Quantity_Clean]]*tblOrders[[#This Row],[UnitPrice_Clean]]) -> 200.67 | AC32: =UPPER(TRIM(tblOrders[[#This Row],[OrderID]])) -> ORD-1230 | AD32: =VALUE(RIGHT(tblOrders[[#This Row],[OrderID]],4)) -> 1230 | AE32: =TEXT(tblOrders[[#This Row],[OrderDate_Clean]],"mmm-yyyy") -> Feb-2024 | AF32: =EOMONTH(tblOrders[[#This Row],[OrderDate_Clean]],0) -> 45351 | AG32: Robert | AH32: =IF(tblOrders[[#This Row],[Discount]]="",0,IF(ISNUMBER(tblOrders[[#This Row],[Discount]]),tblOrders[[#This Row],[Discount]],VALUE(SUBSTITUTE(TRIM(tblOrders[[#This Row],[Discount]]),"%",""))/100)) -> 0
A33: ORD-1103 | B33: 02/29/2024 | C33: Nida Garcia | D33: North | E33: Lahore | F33: Clothing | G33: Winter Coat | H33: online | I33: 1 | J33: 451.93 | K33: 0.05 | L33: Debit Card | M33: Pending | N33: D. Iqbal | O33: Damaged on arrival - replaced | P33: =PROPER(TRIM(C33)) -> Nida Garcia | Q33: =IF(OR(PROPER(TRIM(tblOrders[[#This Row],[Region]]))="Nort",PROPER(TRIM(tblOrders[[#This Row],[Region]]))="Northh"),"North",PROPER(TRIM(tblOrders[[#This Row],[Region]]))) -> North | R33: =IF(PROPER(TRIM(F33))="Cloth Ing","Clothing",IF(PROPER(TRIM(F33))="Electronic","Electronics",IF(PROPER(TRIM(F33))="Grocery","Groceries",SUBSTITUTE(PROPER(TRIM(F33)),"Stationary","Stationery")))) -> Clothing | S33: =IF(LOWER(TRIM(H33))="online","Online",IF(OR(LOWER(TRIM(H33))="in-store",LOWER(TRIM(H33))="in store",LOWER(TRIM(H33))="instore"),"In-Store",PROPER(TRIM(H33)))) -> Online | T33: =IF(UPPER(TRIM(L33))="CC","Credit Card",PROPER(TRIM(L33))) -> Debit Card | U33: =IF(PROPER(TRIM(M33))="Complete","Completed",IF(PROPER(TRIM(M33))="Canceled","Cancelled",PROPER(TRIM(M33)))) -> Pending | V33: =IFERROR(VALUE(TRIM(I33)),"") -> 1 | W33: =IFERROR(VALUE(SUBSTITUTE(TRIM(J33),"$","")),"") -> 451.93 | X33: =IFERROR(IF(ISNUMBER(tblOrders[[#This Row],[OrderDate]]),tblOrders[[#This Row],[OrderDate]],IFERROR(DATEVALUE(tblOrders[[#This Row],[OrderDate]]),DATE(IF(LEN(TRIM(tblOrders[[#This Row],[OrderDate]]))=8,2000+VALUE(RIGHT(TRIM(tblOrders[[#This Row],[OrderDate]]),2)),VALUE(RIGHT(TRIM(tblOrders[[#This Row],[OrderDate]]),4))),VALUE(MID(TRIM(tblOrders[[#This Row],[OrderDate]]),4,2)),VALUE(LEFT(TRIM(tblOrders[[#This Row],[OrderDate]]),2))))),"CHECK MANUALLY") -> 45351 | Y33: =IF(K33="",0,K33) -> 0.05 | Z33: =TRIM(CLEAN(tblOrders[[#This Row],[Notes]])) -> Damaged on arrival - replaced | AA33: =IF(OR(V33="",W33=""),"Review",IF(V33*W33>=1000,"High Value","Standard")) -> Standard | AB33: =IF(OR(tblOrders[[#This Row],[Quantity_Clean]]="",tblOrders[[#This Row],[UnitPrice_Clean]]=""),0,tblOrders[[#This Row],[Quantity_Clean]]*tblOrders[[#This Row],[UnitPrice_Clean]]) -> 451.93 | AC33: =UPPER(TRIM(tblOrders[[#This Row],[OrderID]])) -> ORD-1103 | AD33: =VALUE(RIGHT(tblOrders[[#This Row],[OrderID]],4)) -> 1103 | AE33: =TEXT(tblOrders[[#This Row],[OrderDate_Clean]],"mmm-yyyy") -> Feb-2024 | AF33: =EOMONTH(tblOrders[[#This Row],[OrderDate_Clean]],0) -> 45351 | AG33: Nida | AH33: =IF(tblOrders[[#This Row],[Discount]]="",0,IF(ISNUMBER(tblOrders[[#This Row],[Discount]]),tblOrders[[#This Row],[Discount]],VALUE(SUBSTITUTE(TRIM(tblOrders[[#This Row],[Discount]]),"%",""))/100)) -> 0.05
A34: ORD-1093 | B34: December 01, 2024 | C34: Chen Qureshi | D34: EAST | E34: Sialkot | F34: CLOTHING | G34: Cotton T-Shirt | H34: in-store | I34: 6 | J34: 490.05 | K34: 0 | L34: cash | M34: CANCELLED | N34: C. Osei | O34: VIP customer | P34: =PROPER(TRIM(C34)) -> Chen Qureshi | Q34: =IF(OR(PROPER(TRIM(tblOrders[[#This Row],[Region]]))="Nort",PROPER(TRIM(tblOrders[[#This Row],[Region]]))="Northh"),"North",PROPER(TRIM(tblOrders[[#This Row],[Region]]))) -> East | R34: =IF(PROPER(TRIM(F34))="Cloth Ing","Clothing",IF(PROPER(TRIM(F34))="Electronic","Electronics",IF(PROPER(TRIM(F34))="Grocery","Groceries",SUBSTITUTE(PROPER(TRIM(F34)),"Stationary","Stationery")))) -> Clothing | S34: =IF(LOWER(TRIM(H34))="online","Online",IF(OR(LOWER(TRIM(H34))="in-store",LOWER(TRIM(H34))="in store",LOWER(TRIM(H34))="instore"),"In-Store",PROPER(TRIM(H34)))) -> In-Store | T34: =IF(UPPER(TRIM(L34))="CC","Credit Card",PROPER(TRIM(L34))) -> Cash | U34: =IF(PROPER(TRIM(M34))="Complete","Completed",IF(PROPER(TRIM(M34))="Canceled","Cancelled",PROPER(TRIM(M34)))) -> Cancelled | V34: =IFERROR(VALUE(TRIM(I34)),"") -> 6 | W34: =IFERROR(VALUE(SUBSTITUTE(TRIM(J34),"$","")),"") -> 490.05 | X34: =IFERROR(IF(ISNUMBER(tblOrders[[#This Row],[OrderDate]]),tblOrders[[#This Row],[OrderDate]],IFERROR(DATEVALUE(tblOrders[[#This Row],[OrderDate]]),DATE(IF(LEN(TRIM(tblOrders[[#This Row],[OrderDate]]))=8,2000+VALUE(RIGHT(TRIM(tblOrders[[#This Row],[OrderDate]]),2)),VALUE(RIGHT(TRIM(tblOrders[[#This Row],[OrderDate]]),4))),VALUE(MID(TRIM(tblOrders[[#This Row],[OrderDate]]),4,2)),VALUE(LEFT(TRIM(tblOrders[[#This Row],[OrderDate]]),2))))),"CHECK MANUALLY") -> 45627 | Y34: =IF(K34="",0,K34) -> 0 | Z34: =TRIM(CLEAN(tblOrders[[#This Row],[Notes]])) -> VIP customer | AA34: =IF(OR(V34="",W34=""),"Review",IF(V34*W34>=1000,"High Value","Standard")) -> High Value | AB34: =IF(OR(tblOrders[[#This Row],[Quantity_Clean]]="",tblOrders[[#This Row],[UnitPrice_Clean]]=""),0,tblOrders[[#This Row],[Quantity_Clean]]*tblOrders[[#This Row],[UnitPrice_Clean]]) -> 2940.3 | AC34: =UPPER(TRIM(tblOrders[[#This Row],[OrderID]])) -> ORD-1093 | AD34: =VALUE(RIGHT(tblOrders[[#This Row],[OrderID]],4)) -> 1093 | AE34: =TEXT(tblOrders[[#This Row],[OrderDate_Clean]],"mmm-yyyy") -> Dec-2024 | AF34: =EOMONTH(tblOrders[[#This Row],[OrderDate_Clean]],0) -> 45657 | AG34: Chen | AH34: =IF(tblOrders[[#This Row],[Discount]]="",0,IF(ISNUMBER(tblOrders[[#This Row],[Discount]]),tblOrders[[#This Row],[Discount]],VALUE(SUBSTITUTE(TRIM(tblOrders[[#This Row],[Discount]]),"%",""))/100)) -> 0
A35: ORD-1102 | B35: 08/10/2024 | C35: HINA ALI | D35: east | E35: Sialkot | F35: Clothing | G35: Formal Shirt | H35: in-store | I35: 10 | J35: 478.89 | K35: 0.2 | L35: Debit Card | M35: Canceled | O35: Bulk order - business account | P35: =PROPER(TRIM(C35)) -> Hina Ali | Q35: =IF(OR(PROPER(TRIM(tblOrders[[#This Row],[Region]]))="Nort",PROPER(TRIM(tblOrders[[#This Row],[Region]]))="Northh"),"North",PROPER(TRIM(tblOrders[[#This Row],[Region]]))) -> East | R35: =IF(PROPER(TRIM(F35))="Cloth Ing","Clothing",IF(PROPER(TRIM(F35))="Electronic","Electronics",IF(PROPER(TRIM(F35))="Grocery","Groceries",SUBSTITUTE(PROPER(TRIM(F35)),"Stationary","Stationery")))) -> Clothing | S35: =IF(LOWER(TRIM(H35))="online","Online",IF(OR(LOWER(TRIM(H35))="in-store",LOWER(TRIM(H35))="in store",LOWER(TRIM(H35))="instore"),"In-Store",PROPER(TRIM(H35)))) -> In-Store | T35: =IF(UPPER(TRIM(L35))="CC","Credit Card",PROPER(TRIM(L35))) -> Debit Card | U35: =IF(PROPER(TRIM(M35))="Complete","Completed",IF(PROPER(TRIM(M35))="Canceled","Cancelled",PROPER(TRIM(M35)))) -> Cancelled | V35: =IFERROR(VALUE(TRIM(I35)),"") -> 10 | W35: =IFERROR(VALUE(SUBSTITUTE(TRIM(J35),"$","")),"") -> 478.89 | X35: =IFERROR(IF(ISNUMBER(tblOrders[[#This Row],[OrderDate]]),tblOrders[[#This Row],[OrderDate]],IFERROR(DATEVALUE(tblOrders[[#This Row],[OrderDate]]),DATE(IF(LEN(TRIM(tblOrders[[#This Row],[OrderDate]]))=8,2000+VALUE(RIGHT(TRIM(tblOrders[[#This Row],[OrderDate]]),2)),VALUE(RIGHT(TRIM(tblOrders[[#This Row],[OrderDate]]),4))),VALUE(MID(TRIM(tblOrders[[#This Row],[OrderDate]]),4,2)),VALUE(LEFT(TRIM(tblOrders[[#This Row],[OrderDate]]),2))))),"CHECK MANUALLY") -> 45514 | Y35: =IF(K35="",0,K35) -> 0.2 | Z35: =TRIM(CLEAN(tblOrders[[#This Row],[Notes]])) -> Bulk order - business account | AA35: =IF(OR(V35="",W35=""),"Review",IF(V35*W35>=1000,"High Value","Standard")) -> High Value | AB35: =IF(OR(tblOrders[[#This Row],[Quantity_Clean]]="",tblOrders[[#This Row],[UnitPrice_Clean]]=""),0,tblOrders[[#This Row],[Quantity_Clean]]*tblOrders[[#This Row],[UnitPrice_Clean]]) -> 4788.9 | AC35: =UPPER(TRIM(tblOrders[[#This Row],[OrderID]])) -> ORD-1102 | AD35: =VALUE(RIGHT(tblOrders[[#This Row],[OrderID]],4)) -> 1102 | AE35: =TEXT(tblOrders[[#This Row],[OrderDate_Clean]],"mmm-yyyy") -> Aug-2024 | AF35: =EOMONTH(tblOrders[[#This Row],[OrderDate_Clean]],0) -> 45535 | AG35: HINA | AH35: =IF(tblOrders[[#This Row],[Discount]]="",0,IF(ISNUMBER(tblOrders[[#This Row],[Discount]]),tblOrders[[#This Row],[Discount]],VALUE(SUBSTITUTE(TRIM(tblOrders[[#This Row],[Discount]]),"%",""))/100)) -> 0.2
A36: ORD-1102 | B36: 08/10/2024 | C36: HINA ALI | D36: east | E36: Sialkot | F36: Clothing | G36: Formal Shirt | H36: in-store | I36: 10 | J36: 478.89 | K36: 0.2 | L36: Debit Card | M36: Canceled | O36: Bulk order - business account | P36: =PROPER(TRIM(C36)) -> Hina Ali | Q36: =IF(OR(PROPER(TRIM(tblOrders[[#This Row],[Region]]))="Nort",PROPER(TRIM(tblOrders[[#This Row],[Region]]))="Northh"),"North",PROPER(TRIM(tblOrders[[#This Row],[Region]]))) -> East | R36: =IF(PROPER(TRIM(F36))="Cloth Ing","Clothing",IF(PROPER(TRIM(F36))="Electronic","Electronics",IF(PROPER(TRIM(F36))="Grocery","Groceries",SUBSTITUTE(PROPER(TRIM(F36)),"Stationary","Stationery")))) -> Clothing | S36: =IF(LOWER(TRIM(H36))="online","Online",IF(OR(LOWER(TRIM(H36))="in-store",LOWER(TRIM(H36))="in store",LOWER(TRIM(H36))="instore"),"In-Store",PROPER(TRIM(H36)))) -> In-Store | T36: =IF(UPPER(TRIM(L36))="CC","Credit Card",PROPER(TRIM(L36))) -> Debit Card | U36: =IF(PROPER(TRIM(M36))="Complete","Completed",IF(PROPER(TRIM(M36))="Canceled","Cancelled",PROPER(TRIM(M36)))) -> Cancelled | V36: =IFERROR(VALUE(TRIM(I36)),"") -> 10 | W36: =IFERROR(VALUE(SUBSTITUTE(TRIM(J36),"$","")),"") -> 478.89 | X36: =IFERROR(IF(ISNUMBER(tblOrders[[#This Row],[OrderDate]]),tblOrders[[#This Row],[OrderDate]],IFERROR(DATEVALUE(tblOrders[[#This Row],[OrderDate]]),DATE(IF(LEN(TRIM(tblOrders[[#This Row],[OrderDate]]))=8,2000+VALUE(RIGHT(TRIM(tblOrders[[#This Row],[OrderDate]]),2)),VALUE(RIGHT(TRIM(tblOrders[[#This Row],[OrderDate]]),4))),VALUE(MID(TRIM(tblOrders[[#This Row],[OrderDate]]),4,2)),VALUE(LEFT(TRIM(tblOrders[[#This Row],[OrderDate]]),2))))),"CHECK MANUALLY") -> 45514 | Y36: =IF(K36="",0,K36) -> 0.2 | Z36: =TRIM(CLEAN(tblOrders[[#This Row],[Notes]])) -> Bulk order - business account | AA36: =IF(OR(V36="",W36=""),"Review",IF(V36*W36>=1000,"High Value","Standard")) -> High Value | AB36: =IF(OR(tblOrders[[#This Row],[Quantity_Clean]]="",tblOrders[[#This Row],[UnitPrice_Clean]]=""),0,tblOrders[[#This Row],[Quantity_Clean]]*tblOrders[[#This Row],[UnitPrice_Clean]]) -> 4788.9 | AC36: =UPPER(TRIM(tblOrders[[#This Row],[OrderID]])) -> ORD-1102 | AD36: =VALUE(RIGHT(tblOrders[[#This Row],[OrderID]],4)) -> 1102 | AE36: =TEXT(tblOrders[[#This Row],[OrderDate_Clean]],"mmm-yyyy") -> Aug-2024 | AF36: =EOMONTH(tblOrders[[#This Row],[OrderDate_Clean]],0) -> 45535 | AG36: HINA | AH36: =IF(tblOrders[[#This Row],[Discount]]="",0,IF(ISNUMBER(tblOrders[[#This Row],[Discount]]),tblOrders[[#This Row],[Discount]],VALUE(SUBSTITUTE(TRIM(tblOrders[[#This Row],[Discount]]),"%",""))/100)) -> 0.2
A37: ORD-1102 | B37: 08/10/2024 | C37: HINA ALI | D37: east | E37: Sialkot | F37: Clothing | G37: Formal Shirt | H37: in-store | I37: 10 | J37: 478.89 | K37: 0.2 | L37: Debit Card | M37: Canceled | O37: Bulk order - business account | P37: =PROPER(TRIM(C37)) -> Hina Ali | Q37: =IF(OR(PROPER(TRIM(tblOrders[[#This Row],[Region]]))="Nort",PROPER(TRIM(tblOrders[[#This Row],[Region]]))="Northh"),"North",PROPER(TRIM(tblOrders[[#This Row],[Region]]))) -> East | R37: =IF(PROPER(TRIM(F37))="Cloth Ing","Clothing",IF(PROPER(TRIM(F37))="Electronic","Electronics",IF(PROPER(TRIM(F37))="Grocery","Groceries",SUBSTITUTE(PROPER(TRIM(F37)),"Stationary","Stationery")))) -> Clothing | S37: =IF(LOWER(TRIM(H37))="online","Online",IF(OR(LOWER(TRIM(H37))="in-store",LOWER(TRIM(H37))="in store",LOWER(TRIM(H37))="instore"),"In-Store",PROPER(TRIM(H37)))) -> In-Store | T37: =IF(UPPER(TRIM(L37))="CC","Credit Card",PROPER(TRIM(L37))) -> Debit Card | U37: =IF(PROPER(TRIM(M37))="Complete","Completed",IF(PROPER(TRIM(M37))="Canceled","Cancelled",PROPER(TRIM(M37)))) -> Cancelled | V37: =IFERROR(VALUE(TRIM(I37)),"") -> 10 | W37: =IFERROR(VALUE(SUBSTITUTE(TRIM(J37),"$","")),"") -> 478.89 | X37: =IFERROR(IF(ISNUMBER(tblOrders[[#This Row],[OrderDate]]),tblOrders[[#This Row],[OrderDate]],IFERROR(DATEVALUE(tblOrders[[#This Row],[OrderDate]]),DATE(IF(LEN(TRIM(tblOrders[[#This Row],[OrderDate]]))=8,2000+VALUE(RIGHT(TRIM(tblOrders[[#This Row],[OrderDate]]),2)),VALUE(RIGHT(TRIM(tblOrders[[#This Row],[OrderDate]]),4))),VALUE(MID(TRIM(tblOrders[[#This Row],[OrderDate]]),4,2)),VALUE(LEFT(TRIM(tblOrders[[#This Row],[OrderDate]]),2))))),"CHECK MANUALLY") -> 45514 | Y37: =IF(K37="",0,K37) -> 0.2 | Z37: =TRIM(CLEAN(tblOrders[[#This Row],[Notes]])) -> Bulk order - business account | AA37: =IF(OR(V37="",W37=""),"Review",IF(V37*W37>=1000,"High Value","Standard")) -> High Value | AB37: =IF(OR(tblOrders[[#This Row],[Quantity_Clean]]="",tblOrders[[#This Row],[UnitPrice_Clean]]=""),0,tblOrders[[#This Row],[Quantity_Clean]]*tblOrders[[#This Row],[UnitPrice_Clean]]) -> 4788.9 | AC37: =UPPER(TRIM(tblOrders[[#This Row],[OrderID]])) -> ORD-1102 | AD37: =VALUE(RIGHT(tblOrders[[#This Row],[OrderID]],4)) -> 1102 | AE37: =TEXT(tblOrders[[#This Row],[OrderDate_Clean]],"mmm-yyyy") -> Aug-2024 | AF37: =EOMONTH(tblOrders[[#This Row],[OrderDate_Clean]],0) -> 45535 | AG37: HINA | AH37: =IF(tblOrders[[#This Row],[Discount]]="",0,IF(ISNUMBER(tblOrders[[#This Row],[Discount]]),tblOrders[[#This Row],[Discount]],VALUE(SUBSTITUTE(TRIM(tblOrders[[#This Row],[Discount]]),"%",""))/100)) -> 0.2
A38: ORD-1089 | B38: 06/09/2024 | C38: David Sheikh | D38: NORTH | E38: Islamabad | F38: CLOTHING | G38: Denim Jacket | H38: ONLINE | J38: 472.97 | K38: 0.05 | L38: Debit Card | M38: pending | O38: Follow up needed | P38: =PROPER(TRIM(C38)) -> David Sheikh | Q38: =IF(OR(PROPER(TRIM(tblOrders[[#This Row],[Region]]))="Nort",PROPER(TRIM(tblOrders[[#This Row],[Region]]))="Northh"),"North",PROPER(TRIM(tblOrders[[#This Row],[Region]]))) -> North | R38: =IF(PROPER(TRIM(F38))="Cloth Ing","Clothing",IF(PROPER(TRIM(F38))="Electronic","Electronics",IF(PROPER(TRIM(F38))="Grocery","Groceries",SUBSTITUTE(PROPER(TRIM(F38)),"Stationary","Stationery")))) -> Clothing | S38: =IF(LOWER(TRIM(H38))="online","Online",IF(OR(LOWER(TRIM(H38))="in-store",LOWER(TRIM(H38))="in store",LOWER(TRIM(H38))="instore"),"In-Store",PROPER(TRIM(H38)))) -> Online | T38: =IF(UPPER(TRIM(L38))="CC","Credit Card",PROPER(TRIM(L38))) -> Debit Card | U38: =IF(PROPER(TRIM(M38))="Complete","Completed",IF(PROPER(TRIM(M38))="Canceled","Cancelled",PROPER(TRIM(M38)))) -> Pending | V38: =IFERROR(VALUE(TRIM(I38)),"") | W38: =IFERROR(VALUE(SUBSTITUTE(TRIM(J38),"$","")),"") -> 472.97 | X38: =IFERROR(IF(ISNUMBER(tblOrders[[#This Row],[OrderDate]]),tblOrders[[#This Row],[OrderDate]],IFERROR(DATEVALUE(tblOrders[[#This Row],[OrderDate]]),DATE(IF(LEN(TRIM(tblOrders[[#This Row],[OrderDate]]))=8,2000+VALUE(RIGHT(TRIM(tblOrders[[#This Row],[OrderDate]]),2)),VALUE(RIGHT(TRIM(tblOrders[[#This Row],[OrderDate]]),4))),VALUE(MID(TRIM(tblOrders[[#This Row],[OrderDate]]),4,2)),VALUE(LEFT(TRIM(tblOrders[[#This Row],[OrderDate]]),2))))),"CHECK MANUALLY") -> 45452 | Y38: =IF(K38="",0,K38) -> 0.05 | Z38: =TRIM(CLEAN(tblOrders[[#This Row],[Notes]])) -> Follow up needed | AA38: =IF(OR(V38="",W38=""),"Review",IF(V38*W38>=1000,"High Value","Standard")) -> Review | AB38: =IF(OR(tblOrders[[#This Row],[Quantity_Clean]]="",tblOrders[[#This Row],[UnitPrice_Clean]]=""),0,tblOrders[[#This Row],[Quantity_Clean]]*tblOrders[[#This Row],[UnitPrice_Clean]]) -> 0 | AC38: =UPPER(TRIM(tblOrders[[#This Row],[OrderID]])) -> ORD-1089 | AD38: =VALUE(RIGHT(tblOrders[[#This Row],[OrderID]],4)) -> 1089 | AE38: =TEXT(tblOrders[[#This Row],[OrderDate_Clean]],"mmm-yyyy") -> Jun-2024 | AF38: =EOMONTH(tblOrders[[#This Row],[OrderDate_Clean]],0) -> 45473 | AG38: David | AH38: =IF(tblOrders[[#This Row],[Discount]]="",0,IF(ISNUMBER(tblOrders[[#This Row],[Discount]]),tblOrders[[#This Row],[Discount]],VALUE(SUBSTITUTE(TRIM(tblOrders[[#This Row],[Discount]]),"%",""))/100)) -> 0.05
A39: ORD-1117 | B39: 18/06/2024 | C39: Yusuf Johnson | D39: East | E39: Multan | F39: Clothing | G39: Denim Jacket | H39: ONLINE | I39: 12 | J39: 464.79 | K39: 20% | L39: debit card | M39: PENDING | N39: E. Tanaka | O39: Follow up needed | P39: =PROPER(TRIM(C39)) -> Yusuf Johnson | Q39: =IF(OR(PROPER(TRIM(tblOrders[[#This Row],[Region]]))="Nort",PROPER(TRIM(tblOrders[[#This Row],[Region]]))="Northh"),"North",PROPER(TRIM(tblOrders[[#This Row],[Region]]))) -> East | R39: =IF(PROPER(TRIM(F39))="Cloth Ing","Clothing",IF(PROPER(TRIM(F39))="Electronic","Electronics",IF(PROPER(TRIM(F39))="Grocery","Groceries",SUBSTITUTE(PROPER(TRIM(F39)),"Stationary","Stationery")))) -> Clothing | S39: =IF(LOWER(TRIM(H39))="online","Online",IF(OR(LOWER(TRIM(H39))="in-store",LOWER(TRIM(H39))="in store",LOWER(TRIM(H39))="instore"),"In-Store",PROPER(TRIM(H39)))) -> Online | T39: =IF(UPPER(TRIM(L39))="CC","Credit Card",PROPER(TRIM(L39))) -> Debit Card | U39: =IF(PROPER(TRIM(M39))="Complete","Completed",IF(PROPER(TRIM(M39))="Canceled","Cancelled",PROPER(TRIM(M39)))) -> Pending | V39: =IFERROR(VALUE(TRIM(I39)),"") -> 12 | W39: =IFERROR(VALUE(SUBSTITUTE(TRIM(J39),"$","")),"") -> 464.79 | X39: =IFERROR(IF(ISNUMBER(tblOrders[[#This Row],[OrderDate]]),tblOrders[[#This Row],[OrderDate]],IFERROR(DATEVALUE(tblOrders[[#This Row],[OrderDate]]),DATE(IF(LEN(TRIM(tblOrders[[#This Row],[OrderDate]]))=8,2000+VALUE(RIGHT(TRIM(tblOrders[[#This Row],[OrderDate]]),2)),VALUE(RIGHT(TRIM(tblOrders[[#This Row],[OrderDate]]),4))),VALUE(MID(TRIM(tblOrders[[#This Row],[OrderDate]]),4,2)),VALUE(LEFT(TRIM(tblOrders[[#This Row],[OrderDate]]),2))))),"CHECK MANUALLY") -> 45461 | Y39: =IF(K39="",0,K39) -> 20% | Z39: =TRIM(CLEAN(tblOrders[[#This Row],[Notes]])) -> Follow up needed | AA39: =IF(OR(V39="",W39=""),"Review",IF(V39*W39>=1000,"High Value","Standard")) -> High Value | AB39: =IF(OR(tblOrders[[#This Row],[Quantity_Clean]]="",tblOrders[[#This Row],[UnitPrice_Clean]]=""),0,tblOrders[[#This Row],[Quantity_Clean]]*tblOrders[[#This Row],[UnitPrice_Clean]]) -> 5577.48 | AC39: =UPPER(TRIM(tblOrders[[#This Row],[OrderID]])) -> ORD-1117 | AD39: =VALUE(RIGHT(tblOrders[[#This Row],[OrderID]],4)) -> 1117 | AE39: =TEXT(tblOrders[[#This Row],[OrderDate_Clean]],"mmm-yyyy") -> Jun-2024 | AF39: =EOMONTH(tblOrders[[#This Row],[OrderDate_Clean]],0) -> 45473 | AG39: Yusuf | AH39: =IF(tblOrders[[#This Row],[Discount]]="",0,IF(ISNUMBER(tblOrders[[#This Row],[Discount]]),tblOrders[[#This Row],[Discount]],VALUE(SUBSTITUTE(TRIM(tblOrders[[#This Row],[Discount]]),"%",""))/100)) -> 0.2
A40: ORD-1061 | B40: 2024-07-24 | C40: Nida Hussain | D40: North | E40: Faisalabad | F40: Clothing | G40: Denim Jacket | H40: In-Store | I40: 12 | J40: 461.16 | L40: CREDIT CARD | M40: pending | O40: Follow up needed | P40: =PROPER(TRIM(C40)) -> Nida Hussain | Q40: =IF(OR(PROPER(TRIM(tblOrders[[#This Row],[Region]]))="Nort",PROPER(TRIM(tblOrders[[#This Row],[Region]]))="Northh"),"North",PROPER(TRIM(tblOrders[[#This Row],[Region]]))) -> North | R40: =IF(PROPER(TRIM(F40))="Cloth Ing","Clothing",IF(PROPER(TRIM(F40))="Electronic","Electronics",IF(PROPER(TRIM(F40))="Grocery","Groceries",SUBSTITUTE(PROPER(TRIM(F40)),"Stationary","Stationery")))) -> Clothing | S40: =IF(LOWER(TRIM(H40))="online","Online",IF(OR(LOWER(TRIM(H40))="in-store",LOWER(TRIM(H40))="in store",LOWER(TRIM(H40))="instore"),"In-Store",PROPER(TRIM(H40)))) -> In-Store | T40: =IF(UPPER(TRIM(L40))="CC","Credit Card",PROPER(TRIM(L40))) -> Credit Card | U40: =IF(PROPER(TRIM(M40))="Complete","Completed",IF(PROPER(TRIM(M40))="Canceled","Cancelled",PROPER(TRIM(M40)))) -> Pending | V40: =IFERROR(VALUE(TRIM(I40)),"") -> 12 | W40: =IFERROR(VALUE(SUBSTITUTE(TRIM(J40),"$","")),"") -> 461.16 | X40: =IFERROR(IF(ISNUMBER(tblOrders[[#This Row],[OrderDate]]),tblOrders[[#This Row],[OrderDate]],IFERROR(DATEVALUE(tblOrders[[#This Row],[OrderDate]]),DATE(IF(LEN(TRIM(tblOrders[[#This Row],[OrderDate]]))=8,2000+VALUE(RIGHT(TRIM(tblOrders[[#This Row],[OrderDate]]),2)),VALUE(RIGHT(TRIM(tblOrders[[#This Row],[OrderDate]]),4))),VALUE(MID(TRIM(tblOrders[[#This Row],[OrderDate]]),4,2)),VALUE(LEFT(TRIM(tblOrders[[#This Row],[OrderDate]]),2))))),"CHECK MANUALLY") -> 45497 | Y40: =IF(K40="",0,K40) -> 0 | Z40: =TRIM(CLEAN(tblOrders[[#This Row],[Notes]])) -> Follow up needed | AA40: =IF(OR(V40="",W40=""),"Review",IF(V40*W40>=1000,"High Value","Standard")) -> High Value | AB40: =IF(OR(tblOrders[[#This Row],[Quantity_Clean]]="",tblOrders[[#This Row],[UnitPrice_Clean]]=""),0,tblOrders[[#This Row],[Quantity_Clean]]*tblOrders[[#This Row],[UnitPrice_Clean]]) -> 5533.92 | AC40: =UPPER(TRIM(tblOrders[[#This Row],[OrderID]])) -> ORD-1061 | AD40: =VALUE(RIGHT(tblOrders[[#This Row],[OrderID]],4)) -> 1061 | AE40: =TEXT(tblOrders[[#This Row],[OrderDate_Clean]],"mmm-yyyy") -> Jul-2024 | AF40: =EOMONTH(tblOrders[[#This Row],[OrderDate_Clean]],0) -> 45504 | AG40: Nida | AH40: =IF(tblOrders[[#This Row],[Discount]]="",0,IF(ISNUMBER(tblOrders[[#This Row],[Discount]]),tblOrders[[#This Row],[Discount]],VALUE(SUBSTITUTE(TRIM(tblOrders[[#This Row],[Discount]]),"%",""))/100)) -> 0
A41: ORD-1075 | B41: 2024-02-10 | C41: Kevin Sheikh | D41: West | E41: Peshawar | F41: Clothing | G41: Formal Shirt | H41: ONLINE | J41: 459.11 | K41: 0.15 | L41: Debit card | M41: pending | N41: A. Malik | O41: Leave at front desk | P41: =PROPER(TRIM(C41)) -> Kevin Sheikh | Q41: =IF(OR(PROPER(TRIM(tblOrders[[#This Row],[Region]]))="Nort",PROPER(TRIM(tblOrders[[#This Row],[Region]]))="Northh"),"North",PROPER(TRIM(tblOrders[[#This Row],[Region]]))) -> West | R41: =IF(PROPER(TRIM(F41))="Cloth Ing","Clothing",IF(PROPER(TRIM(F41))="Electronic","Electronics",IF(PROPER(TRIM(F41))="Grocery","Groceries",SUBSTITUTE(PROPER(TRIM(F41)),"Stationary","Stationery")))) -> Clothing | S41: =IF(LOWER(TRIM(H41))="online","Online",IF(OR(LOWER(TRIM(H41))="in-store",LOWER(TRIM(H41))="in store",LOWER(TRIM(H41))="instore"),"In-Store",PROPER(TRIM(H41)))) -> Online | T41: =IF(UPPER(TRIM(L41))="CC","Credit Card",PROPER(TRIM(L41))) -> Debit Card | U41: =IF(PROPER(TRIM(M41))="Complete","Completed",IF(PROPER(TRIM(M41))="Canceled","Cancelled",PROPER(TRIM(M41)))) -> Pending | V41: =IFERROR(VALUE(TRIM(I41)),"") | W41: =IFERROR(VALUE(SUBSTITUTE(TRIM(J41),"$","")),"") -> 459.11 | X41: =IFERROR(IF(ISNUMBER(tblOrders[[#This Row],[OrderDate]]),tblOrders[[#This Row],[OrderDate]],IFERROR(DATEVALUE(tblOrders[[#This Row],[OrderDate]]),DATE(IF(LEN(TRIM(tblOrders[[#This Row],[OrderDate]]))=8,2000+VALUE(RIGHT(TRIM(tblOrders[[#This Row],[OrderDate]]),2)),VALUE(RIGHT(TRIM(tblOrders[[#This Row],[OrderDate]]),4))),VALUE(MID(TRIM(tblOrders[[#This Row],[OrderDate]]),4,2)),VALUE(LEFT(TRIM(tblOrders[[#This Row],[OrderDate]]),2))))),"CHECK MANUALLY") -> 45332 | Y41: =IF(K41="",0,K41) -> 0.15 | Z41: =TRIM(CLEAN(tblOrders[[#This Row],[Notes]])) -> Leave at front desk | AA41: =IF(OR(V41="",W41=""),"Review",IF(V41*W41>=1000,"High Value","Standard")) -> Review | AB41: =IF(OR(tblOrders[[#This Row],[Quantity_Clean]]="",tblOrders[[#This Row],[UnitPrice_Clean]]=""),0,tblOrders[[#This Row],[Quantity_Clean]]*tblOrders[[#This Row],[UnitPrice_Clean]]) -> 0 | AC41: =UPPER(TRIM(tblOrders[[#This Row],[OrderID]])) -> ORD-1075 | AD41: =VALUE(RIGHT(tblOrders[[#This Row],[OrderID]],4)) -> 1075 | AE41: =TEXT(tblOrders[[#This Row],[OrderDate_Clean]],"mmm-yyyy") -> Feb-2024 | AF41: =EOMONTH(tblOrders[[#This Row],[OrderDate_Clean]],0) -> 45351 | AG41: Kevin | AH41: =IF(tblOrders[[#This Row],[Discount]]="",0,IF(ISNUMBER(tblOrders[[#This Row],[Discount]]),tblOrders[[#This Row],[Discount]],VALUE(SUBSTITUTE(TRIM(tblOrders[[#This Row],[Discount]]),"%",""))/100)) -> 0.15
A42: ORD-1051 | B42: 31-May-24 | C42: Nida Lee | D42: east | E42: Multan | F42: CLOTHING | G42: Denim Jacket | H42: Online | I42: 3 | J42: 438.85 | K42: 0.1 | L42: CREDIT CARD | M42: Cancelled | N42: D. Iqbal | O42: Customer called twice | P42: =PROPER(TRIM(C42)) -> Nida Lee | Q42: =IF(OR(PROPER(TRIM(tblOrders[[#This Row],[Region]]))="Nort",PROPER(TRIM(tblOrders[[#This Row],[Region]]))="Northh"),"North",PROPER(TRIM(tblOrders[[#This Row],[Region]]))) -> East | R42: =IF(PROPER(TRIM(F42))="Cloth Ing","Clothing",IF(PROPER(TRIM(F42))="Electronic","Electronics",IF(PROPER(TRIM(F42))="Grocery","Groceries",SUBSTITUTE(PROPER(TRIM(F42)),"Stationary","Stationery")))) -> Clothing | S42: =IF(LOWER(TRIM(H42))="online","Online",IF(OR(LOWER(TRIM(H42))="in-store",LOWER(TRIM(H42))="in store",LOWER(TRIM(H42))="instore"),"In-Store",PROPER(TRIM(H42)))) -> Online | T42: =IF(UPPER(TRIM(L42))="CC","Credit Card",PROPER(TRIM(L42))) -> Credit Card | U42: =IF(PROPER(TRIM(M42))="Complete","Completed",IF(PROPER(TRIM(M42))="Canceled","Cancelled",PROPER(TRIM(M42)))) -> Cancelled | V42: =IFERROR(VALUE(TRIM(I42)),"") -> 3 | W42: =IFERROR(VALUE(SUBSTITUTE(TRIM(J42),"$","")),"") -> 438.85 | X42: =IFERROR(IF(ISNUMBER(tblOrders[[#This Row],[OrderDate]]),tblOrders[[#This Row],[OrderDate]],IFERROR(DATEVALUE(tblOrders[[#This Row],[OrderDate]]),DATE(IF(LEN(TRIM(tblOrders[[#This Row],[OrderDate]]))=8,2000+VALUE(RIGHT(TRIM(tblOrders[[#This Row],[OrderDate]]),2)),VALUE(RIGHT(TRIM(tblOrders[[#This Row],[OrderDate]]),4))),VALUE(MID(TRIM(tblOrders[[#This Row],[OrderDate]]),4,2)),VALUE(LEFT(TRIM(tblOrders[[#This Row],[OrderDate]]),2))))),"CHECK MANUALLY") -> 45443 | Y42: =IF(K42="",0,K42) -> 0.1 | Z42: =TRIM(CLEAN(tblOrders[[#This Row],[Notes]])) -> Customer called twice | AA42: =IF(OR(V42="",W42=""),"Review",IF(V42*W42>=1000,"High Value","Standard")) -> High Value | AB42: =IF(OR(tblOrders[[#This Row],[Quantity_Clean]]="",tblOrders[[#This Row],[UnitPrice_Clean]]=""),0,tblOrders[[#This Row],[Quantity_Clean]]*tblOrders[[#This Row],[UnitPrice_Clean]]) -> 1316.55 | AC42: =UPPER(TRIM(tblOrders[[#This Row],[OrderID]])) -> ORD-1051 | AD42: =VALUE(RIGHT(tblOrders[[#This Row],[OrderID]],4)) -> 1051 | AE42: =TEXT(tblOrders[[#This Row],[OrderDate_Clean]],"mmm-yyyy") -> May-2024 | AF42: =EOMONTH(tblOrders[[#This Row],[OrderDate_Clean]],0) -> 45443 | AG42: Nida | AH42: =IF(tblOrders[[#This Row],[Discount]]="",0,IF(ISNUMBER(tblOrders[[#This Row],[Discount]]),tblOrders[[#This Row],[Discount]],VALUE(SUBSTITUTE(TRIM(tblOrders[[#This Row],[Discount]]),"%",""))/100)) -> 0.1
A43: ORD-1223 | B43: 07/01/2024 | C43: YUSUF MALIK | D43: EAST | E43: Multan | F43: clothing | G43: Denim Jacket | H43: instore | I43: 12 | J43: 369.04 | L43: Credit card | M43: Complete | N43: E. Tanaka | O43: Customer called twice | P43: =PROPER(TRIM(C43)) -> Yusuf Malik | Q43: =IF(OR(PROPER(TRIM(tblOrders[[#This Row],[Region]]))="Nort",PROPER(TRIM(tblOrders[[#This Row],[Region]]))="Northh"),"North",PROPER(TRIM(tblOrders[[#This Row],[Region]]))) -> East | R43: =IF(PROPER(TRIM(F43))="Cloth Ing","Clothing",IF(PROPER(TRIM(F43))="Electronic","Electronics",IF(PROPER(TRIM(F43))="Grocery","Groceries",SUBSTITUTE(PROPER(TRIM(F43)),"Stationary","Stationery")))) -> Clothing | S43: =IF(LOWER(TRIM(H43))="online","Online",IF(OR(LOWER(TRIM(H43))="in-store",LOWER(TRIM(H43))="in store",LOWER(TRIM(H43))="instore"),"In-Store",PROPER(TRIM(H43)))) -> In-Store | T43: =IF(UPPER(TRIM(L43))="CC","Credit Card",PROPER(TRIM(L43))) -> Credit Card | U43: =IF(PROPER(TRIM(M43))="Complete","Completed",IF(PROPER(TRIM(M43))="Canceled","Cancelled",PROPER(TRIM(M43)))) -> Completed | V43: =IFERROR(VALUE(TRIM(I43)),"") -> 12 | W43: =IFERROR(VALUE(SUBSTITUTE(TRIM(J43),"$","")),"") -> 369.04 | X43: =IFERROR(IF(ISNUMBER(tblOrders[[#This Row],[OrderDate]]),tblOrders[[#This Row],[OrderDate]],IFERROR(DATEVALUE(tblOrders[[#This Row],[OrderDate]]),DATE(IF(LEN(TRIM(tblOrders[[#This Row],[OrderDate]]))=8,2000+VALUE(RIGHT(TRIM(tblOrders[[#This Row],[OrderDate]]),2)),VALUE(RIGHT(TRIM(tblOrders[[#This Row],[OrderDate]]),4))),VALUE(MID(TRIM(tblOrders[[#This Row],[OrderDate]]),4,2)),VALUE(LEFT(TRIM(tblOrders[[#This Row],[OrderDate]]),2))))),"CHECK MANUALLY") -> 45474 | Y43: =IF(K43="",0,K43) -> 0 | Z43: =TRIM(CLEAN(tblOrders[[#This Row],[Notes]])) -> Customer called twice | AA43: =IF(OR(V43="",W43=""),"Review",IF(V43*W43>=1000,"High Value","Standard")) -> High Value | AB43: =IF(OR(tblOrders[[#This Row],[Quantity_Clean]]="",tblOrders[[#This Row],[UnitPrice_Clean]]=""),0,tblOrders[[#This Row],[Quantity_Clean]]*tblOrders[[#This Row],[UnitPrice_Clean]]) -> 4428.48 | AC43: =UPPER(TRIM(tblOrders[[#This Row],[OrderID]])) -> ORD-1223 | AD43: =VALUE(RIGHT(tblOrders[[#This Row],[OrderID]],4)) -> 1223 | AE43: =TEXT(tblOrders[[#This Row],[OrderDate_Clean]],"mmm-yyyy") -> Jul-2024 | AF43: =EOMONTH(tblOrders[[#This Row],[OrderDate_Clean]],0) -> 45504 | AG43: YUSUF | AH43: =IF(tblOrders[[#This Row],[Discount]]="",0,IF(ISNUMBER(tblOrders[[#This Row],[Discount]]),tblOrders[[#This Row],[Discount]],VALUE(SUBSTITUTE(TRIM(tblOrders[[#This Row],[Discount]]),"%",""))/100)) -> 0
A44: ORD-1197 | B44: 22/03/2024 | C44: sarah brown | D44: North | E44: Faisalabad | F44: CLOTHING | G44: Winter Coat | H44: In-store | I44: 6 | J44: 355.3 | K44: 0.2 | L44: credit card | M44: refunded | N44: E. Tanaka | O44: Bulk order - business account | P44: =PROPER(TRIM(C44)) -> Sarah Brown | Q44: =IF(OR(PROPER(TRIM(tblOrders[[#This Row],[Region]]))="Nort",PROPER(TRIM(tblOrders[[#This Row],[Region]]))="Northh"),"North",PROPER(TRIM(tblOrders[[#This Row],[Region]]))) -> North | R44: =IF(PROPER(TRIM(F44))="Cloth Ing","Clothing",IF(PROPER(TRIM(F44))="Electronic","Electronics",IF(PROPER(TRIM(F44))="Grocery","Groceries",SUBSTITUTE(PROPER(TRIM(F44)),"Stationary","Stationery")))) -> Clothing | S44: =IF(LOWER(TRIM(H44))="online","Online",IF(OR(LOWER(TRIM(H44))="in-store",LOWER(TRIM(H44))="in store",LOWER(TRIM(H44))="instore"),"In-Store",PROPER(TRIM(H44)))) -> In-Store | T44: =IF(UPPER(TRIM(L44))="CC","Credit Card",PROPER(TRIM(L44))) -> Credit Card | U44: =IF(PROPER(TRIM(M44))="Complete","Completed",IF(PROPER(TRIM(M44))="Canceled","Cancelled",PROPER(TRIM(M44)))) -> Refunded | V44: =IFERROR(VALUE(TRIM(I44)),"") -> 6 | W44: =IFERROR(VALUE(SUBSTITUTE(TRIM(J44),"$","")),"") -> 355.3 | X44: =IFERROR(IF(ISNUMBER(tblOrders[[#This Row],[OrderDate]]),tblOrders[[#This Row],[OrderDate]],IFERROR(DATEVALUE(tblOrders[[#This Row],[OrderDate]]),DATE(IF(LEN(TRIM(tblOrders[[#This Row],[OrderDate]]))=8,2000+VALUE(RIGHT(TRIM(tblOrders[[#This Row],[OrderDate]]),2)),VALUE(RIGHT(TRIM(tblOrders[[#This Row],[OrderDate]]),4))),VALUE(MID(TRIM(tblOrders[[#This Row],[OrderDate]]),4,2)),VALUE(LEFT(TRIM(tblOrders[[#This Row],[OrderDate]]),2))))),"CHECK MANUALLY") -> 45373 | Y44: =IF(K44="",0,K44) -> 0.2 | Z44: =TRIM(CLEAN(tblOrders[[#This Row],[Notes]])) -> Bulk order - business account | AA44: =IF(OR(V44="",W44=""),"Review",IF(V44*W44>=1000,"High Value","Standard")) -> High Value | AB44: =IF(OR(tblOrders[[#This Row],[Quantity_Clean]]="",tblOrders[[#This Row],[UnitPrice_Clean]]=""),0,tblOrders[[#This Row],[Quantity_Clean]]*tblOrders[[#This Row],[UnitPrice_Clean]]) -> 2131.8 | AC44: =UPPER(TRIM(tblOrders[[#This Row],[OrderID]])) -> ORD-1197 | AD44: =VALUE(RIGHT(tblOrders[[#This Row],[OrderID]],4)) -> 1197 | AE44: =TEXT(tblOrders[[#This Row],[OrderDate_Clean]],"mmm-yyyy") -> Mar-2024 | AF44: =EOMONTH(tblOrders[[#This Row],[OrderDate_Clean]],0) -> 45382 | AG44: sarah | AH44: =IF(tblOrders[[#This Row],[Discount]]="",0,IF(ISNUMBER(tblOrders[[#This Row],[Discount]]),tblOrders[[#This Row],[Discount]],VALUE(SUBSTITUTE(TRIM(tblOrders[[#This Row],[Discount]]),"%",""))/100)) -> 0.2
A45: ORD-1034 | B45: May 21, 2024 | C45: Fatima Hussain | D45: EAST | E45: Sialkot | F45: clothing | G45: Cotton T-Shirt | H45: Online | I45: 6 | J45: 270.25 | L45: Credit card | M45: Refunded | N45: D. Iqbal | O45: Bulk order - business account | P45: =PROPER(TRIM(C45)) -> Fatima Hussain | Q45: =IF(OR(PROPER(TRIM(tblOrders[[#This Row],[Region]]))="Nort",PROPER(TRIM(tblOrders[[#This Row],[Region]]))="Northh"),"North",PROPER(TRIM(tblOrders[[#This Row],[Region]]))) -> East | R45: =IF(PROPER(TRIM(F45))="Cloth Ing","Clothing",IF(PROPER(TRIM(F45))="Electronic","Electronics",IF(PROPER(TRIM(F45))="Grocery","Groceries",SUBSTITUTE(PROPER(TRIM(F45)),"Stationary","Stationery")))) -> Clothing | S45: =IF(LOWER(TRIM(H45))="online","Online",IF(OR(LOWER(TRIM(H45))="in-store",LOWER(TRIM(H45))="in store",LOWER(TRIM(H45))="instore"),"In-Store",PROPER(TRIM(H45)))) -> Online | T45: =IF(UPPER(TRIM(L45))="CC","Credit Card",PROPER(TRIM(L45))) -> Credit Card | U45: =IF(PROPER(TRIM(M45))="Complete","Completed",IF(PROPER(TRIM(M45))="Canceled","Cancelled",PROPER(TRIM(M45)))) -> Refunded | V45: =IFERROR(VALUE(TRIM(I45)),"") -> 6 | W45: =IFERROR(VALUE(SUBSTITUTE(TRIM(J45),"$","")),"") -> 270.25 | X45: =IFERROR(IF(ISNUMBER(tblOrders[[#This Row],[OrderDate]]),tblOrders[[#This Row],[OrderDate]],IFERROR(DATEVALUE(tblOrders[[#This Row],[OrderDate]]),DATE(IF(LEN(TRIM(tblOrders[[#This Row],[OrderDate]]))=8,2000+VALUE(RIGHT(TRIM(tblOrders[[#This Row],[OrderDate]]),2)),VALUE(RIGHT(TRIM(tblOrders[[#This Row],[OrderDate]]),4))),VALUE(MID(TRIM(tblOrders[[#This Row],[OrderDate]]),4,2)),VALUE(LEFT(TRIM(tblOrders[[#This Row],[OrderDate]]),2))))),"CHECK MANUALLY") -> 45433 | Y45: =IF(K45="",0,K45) -> 0 | Z45: =TRIM(CLEAN(tblOrders[[#This Row],[Notes]])) -> Bulk order - business account | AA45: =IF(OR(V45="",W45=""),"Review",IF(V45*W45>=1000,"High Value","Standard")) -> High Value | AB45: =IF(OR(tblOrders[[#This Row],[Quantity_Clean]]="",tblOrders[[#This Row],[UnitPrice_Clean]]=""),0,tblOrders[[#This Row],[Quantity_Clean]]*tblOrders[[#This Row],[UnitPrice_Clean]]) -> 1621.5 | AC45: =UPPER(TRIM(tblOrders[[#This Row],[OrderID]])) -> ORD-1034 | AD45: =VALUE(RIGHT(tblOrders[[#This Row],[OrderID]],4)) -> 1034 | AE45: =TEXT(tblOrders[[#This Row],[OrderDate_Clean]],"mmm-yyyy") -> May-2024 | AF45: =EOMONTH(tblOrders[[#This Row],[OrderDate_Clean]],0) -> 45443 | AG45: Fatima | AH45: =IF(tblOrders[[#This Row],[Discount]]="",0,IF(ISNUMBER(tblOrders[[#This Row],[Discount]]),tblOrders[[#This Row],[Discount]],VALUE(SUBSTITUTE(TRIM(tblOrders[[#This Row],[Discount]]),"%",""))/100)) -> 0
A46: ORD-1218 | B46: 01/30/2024 | C46: Chen Smith | D46: South | E46: Hyderabad | F46: clothing | G46: Formal Shirt | H46: online | J46: 195.24 | K46: 20% | L46: CC | M46: Refunded | N46: E. Tanaka | O46: Damaged on arrival - replaced | P46: =PROPER(TRIM(C46)) -> Chen Smith | Q46: =IF(OR(PROPER(TRIM(tblOrders[[#This Row],[Region]]))="Nort",PROPER(TRIM(tblOrders[[#This Row],[Region]]))="Northh"),"North",PROPER(TRIM(tblOrders[[#This Row],[Region]]))) -> South | R46: =IF(PROPER(TRIM(F46))="Cloth Ing","Clothing",IF(PROPER(TRIM(F46))="Electronic","Electronics",IF(PROPER(TRIM(F46))="Grocery","Groceries",SUBSTITUTE(PROPER(TRIM(F46)),"Stationary","Stationery")))) -> Clothing | S46: =IF(LOWER(TRIM(H46))="online","Online",IF(OR(LOWER(TRIM(H46))="in-store",LOWER(TRIM(H46))="in store",LOWER(TRIM(H46))="instore"),"In-Store",PROPER(TRIM(H46)))) -> Online | T46: =IF(UPPER(TRIM(L46))="CC","Credit Card",PROPER(TRIM(L46))) -> Credit Card | U46: =IF(PROPER(TRIM(M46))="Complete","Completed",IF(PROPER(TRIM(M46))="Canceled","Cancelled",PROPER(TRIM(M46)))) -> Refunded | V46: =IFERROR(VALUE(TRIM(I46)),"") | W46: =IFERROR(VALUE(SUBSTITUTE(TRIM(J46),"$","")),"") -> 195.24 | X46: =IFERROR(IF(ISNUMBER(tblOrders[[#This Row],[OrderDate]]),tblOrders[[#This Row],[OrderDate]],IFERROR(DATEVALUE(tblOrders[[#This Row],[OrderDate]]),DATE(IF(LEN(TRIM(tblOrders[[#This Row],[OrderDate]]))=8,2000+VALUE(RIGHT(TRIM(tblOrders[[#This Row],[OrderDate]]),2)),VALUE(RIGHT(TRIM(tblOrders[[#This Row],[OrderDate]]),4))),VALUE(MID(TRIM(tblOrders[[#This Row],[OrderDate]]),4,2)),VALUE(LEFT(TRIM(tblOrders[[#This Row],[OrderDate]]),2))))),"CHECK MANUALLY") -> 45321 | Y46: =IF(K46="",0,K46) -> 20% | Z46: =TRIM(CLEAN(tblOrders[[#This Row],[Notes]])) -> Damaged on arrival - replaced | AA46: =IF(OR(V46="",W46=""),"Review",IF(V46*W46>=1000,"High Value","Standard")) -> Review | AB46: =IF(OR(tblOrders[[#This Row],[Quantity_Clean]]="",tblOrders[[#This Row],[UnitPrice_Clean]]=""),0,tblOrders[[#This Row],[Quantity_Clean]]*tblOrders[[#This Row],[UnitPrice_Clean]]) -> 0 | AC46: =UPPER(TRIM(tblOrders[[#This Row],[OrderID]])) -> ORD-1218 | AD46: =VALUE(RIGHT(tblOrders[[#This Row],[OrderID]],4)) -> 1218 | AE46: =TEXT(tblOrders[[#This Row],[OrderDate_Clean]],"mmm-yyyy") -> Jan-2024 | AF46: =EOMONTH(tblOrders[[#This Row],[OrderDate_Clean]],0) -> 45322 | AG46: Chen | AH46: =IF(tblOrders[[#This Row],[Discount]]="",0,IF(ISNUMBER(tblOrders[[#This Row],[Discount]]),tblOrders[[#This Row],[Discount]],VALUE(SUBSTITUTE(TRIM(tblOrders[[#This Row],[Discount]]),"%",""))/100)) -> 0.2
A47: ORD-1028 | B47: 2024-10-03 | C47: Michael Hussain | D47: west | E47: Quetta | F47: clothing | G47: Running Shoes | H47: in-store | I47: 6 | J47: 192.67 | K47: 0.1 | L47: credit card | M47: CANCELLED | N47: A. Malik | P47: =PROPER(TRIM(C47)) -> Michael Hussain | Q47: =IF(OR(PROPER(TRIM(tblOrders[[#This Row],[Region]]))="Nort",PROPER(TRIM(tblOrders[[#This Row],[Region]]))="Northh"),"North",PROPER(TRIM(tblOrders[[#This Row],[Region]]))) -> West | R47: =IF(PROPER(TRIM(F47))="Cloth Ing","Clothing",IF(PROPER(TRIM(F47))="Electronic","Electronics",IF(PROPER(TRIM(F47))="Grocery","Groceries",SUBSTITUTE(PROPER(TRIM(F47)),"Stationary","Stationery")))) -> Clothing | S47: =IF(LOWER(TRIM(H47))="online","Online",IF(OR(LOWER(TRIM(H47))="in-store",LOWER(TRIM(H47))="in store",LOWER(TRIM(H47))="instore"),"In-Store",PROPER(TRIM(H47)))) -> In-Store | T47: =IF(UPPER(TRIM(L47))="CC","Credit Card",PROPER(TRIM(L47))) -> Credit Card | U47: =IF(PROPER(TRIM(M47))="Complete","Completed",IF(PROPER(TRIM(M47))="Canceled","Cancelled",PROPER(TRIM(M47)))) -> Cancelled | V47: =IFERROR(VALUE(TRIM(I47)),"") -> 6 | W47: =IFERROR(VALUE(SUBSTITUTE(TRIM(J47),"$","")),"") -> 192.67 | X47: =IFERROR(IF(ISNUMBER(tblOrders[[#This Row],[OrderDate]]),tblOrders[[#This Row],[OrderDate]],IFERROR(DATEVALUE(tblOrders[[#This Row],[OrderDate]]),DATE(IF(LEN(TRIM(tblOrders[[#This Row],[OrderDate]]))=8,2000+VALUE(RIGHT(TRIM(tblOrders[[#This Row],[OrderDate]]),2)),VALUE(RIGHT(TRIM(tblOrders[[#This Row],[OrderDate]]),4))),VALUE(MID(TRIM(tblOrders[[#This Row],[OrderDate]]),4,2)),VALUE(LEFT(TRIM(tblOrders[[#This Row],[OrderDate]]),2))))),"CHECK MANUALLY") -> 45568 | Y47: =IF(K47="",0,K47) -> 0.1 | Z47: =TRIM(CLEAN(tblOrders[[#This Row],[Notes]])) | AA47: =IF(OR(V47="",W47=""),"Review",IF(V47*W47>=1000,"High Value","Standard")) -> High Value | AB47: =IF(OR(tblOrders[[#This Row],[Quantity_Clean]]="",tblOrders[[#This Row],[UnitPrice_Clean]]=""),0,tblOrders[[#This Row],[Quantity_Clean]]*tblOrders[[#This Row],[UnitPrice_Clean]]) -> 1156.02 | AC47: =UPPER(TRIM(tblOrders[[#This Row],[OrderID]])) -> ORD-1028 | AD47: =VALUE(RIGHT(tblOrders[[#This Row],[OrderID]],4)) -> 1028 | AE47: =TEXT(tblOrders[[#This Row],[OrderDate_Clean]],"mmm-yyyy") -> Oct-2024 | AF47: =EOMONTH(tblOrders[[#This Row],[OrderDate_Clean]],0) -> 45596 | AG47: Michael | AH47: =IF(tblOrders[[#This Row],[Discount]]="",0,IF(ISNUMBER(tblOrders[[#This Row],[Discount]]),tblOrders[[#This Row],[Discount]],VALUE(SUBSTITUTE(TRIM(tblOrders[[#This Row],[Discount]]),"%",""))/100)) -> 0.1
A48: ORD-1071 | B48: 2024-05-31 | C48: Chen Taylor | D48: North | E48: Faisalabad | F48: Clothing | G48: Formal Shirt | H48: In-Store | I48: 3 | J48: 174.16 | L48: CREDIT CARD | M48: COMPLETED | N48: A. Malik | O48: Bulk order - business account | P48: =PROPER(TRIM(C48)) -> Chen Taylor | Q48: =IF(OR(PROPER(TRIM(tblOrders[[#This Row],[Region]]))="Nort",PROPER(TRIM(tblOrders[[#This Row],[Region]]))="Northh"),"North",PROPER(TRIM(tblOrders[[#This Row],[Region]]))) -> North | R48: =IF(PROPER(TRIM(F48))="Cloth Ing","Clothing",IF(PROPER(TRIM(F48))="Electronic","Electronics",IF(PROPER(TRIM(F48))="Grocery","Groceries",SUBSTITUTE(PROPER(TRIM(F48)),"Stationary","Stationery")))) -> Clothing | S48: =IF(LOWER(TRIM(H48))="online","Online",IF(OR(LOWER(TRIM(H48))="in-store",LOWER(TRIM(H48))="in store",LOWER(TRIM(H48))="instore"),"In-Store",PROPER(TRIM(H48)))) -> In-Store | T48: =IF(UPPER(TRIM(L48))="CC","Credit Card",PROPER(TRIM(L48))) -> Credit Card | U48: =IF(PROPER(TRIM(M48))="Complete","Completed",IF(PROPER(TRIM(M48))="Canceled","Cancelled",PROPER(TRIM(M48)))) -> Completed | V48: =IFERROR(VALUE(TRIM(I48)),"") -> 3 | W48: =IFERROR(VALUE(SUBSTITUTE(TRIM(J48),"$","")),"") -> 174.16 | X48: =IFERROR(IF(ISNUMBER(tblOrders[[#This Row],[OrderDate]]),tblOrders[[#This Row],[OrderDate]],IFERROR(DATEVALUE(tblOrders[[#This Row],[OrderDate]]),DATE(IF(LEN(TRIM(tblOrders[[#This Row],[OrderDate]]))=8,2000+VALUE(RIGHT(TRIM(tblOrders[[#This Row],[OrderDate]]),2)),VALUE(RIGHT(TRIM(tblOrders[[#This Row],[OrderDate]]),4))),VALUE(MID(TRIM(tblOrders[[#This Row],[OrderDate]]),4,2)),VALUE(LEFT(TRIM(tblOrders[[#This Row],[OrderDate]]),2))))),"CHECK MANUALLY") -> 45443 | Y48: =IF(K48="",0,K48) -> 0 | Z48: =TRIM(CLEAN(tblOrders[[#This Row],[Notes]])) -> Bulk order - business account | AA48: =IF(OR(V48="",W48=""),"Review",IF(V48*W48>=1000,"High Value","Standard")) -> Standard | AB48: =IF(OR(tblOrders[[#This Row],[Quantity_Clean]]="",tblOrders[[#This Row],[UnitPrice_Clean]]=""),0,tblOrders[[#This Row],[Quantity_Clean]]*tblOrders[[#This Row],[UnitPrice_Clean]]) -> 522.48 | AC48: =UPPER(TRIM(tblOrders[[#This Row],[OrderID]])) -> ORD-1071 | AD48: =VALUE(RIGHT(tblOrders[[#This Row],[OrderID]],4)) -> 1071 | AE48: =TEXT(tblOrders[[#This Row],[OrderDate_Clean]],"mmm-yyyy") -> May-2024 | AF48: =EOMONTH(tblOrders[[#This Row],[OrderDate_Clean]],0) -> 45443 | AG48: Chen | AH48: =IF(tblOrders[[#This Row],[Discount]]="",0,IF(ISNUMBER(tblOrders[[#This Row],[Discount]]),tblOrders[[#This Row],[Discount]],VALUE(SUBSTITUTE(TRIM(tblOrders[[#This Row],[Discount]]),"%",""))/100)) -> 0
A49: ORD-1053 | B49: 20-Aug-24 | C49: Robert Qureshi | D49: North | E49: Lahore | F49: CLOTHING | G49: Cotton T-Shirt | H49: ONLINE | I49: 1 | J49: 155.66 | L49: Cash | M49: COMPLETED | N49: D. Iqbal | O49: Bulk order - business account | P49: =PROPER(TRIM(C49)) -> Robert Qureshi | Q49: =IF(OR(PROPER(TRIM(tblOrders[[#This Row],[Region]]))="Nort",PROPER(TRIM(tblOrders[[#This Row],[Region]]))="Northh"),"North",PROPER(TRIM(tblOrders[[#This Row],[Region]]))) -> North | R49: =IF(PROPER(TRIM(F49))="Cloth Ing","Clothing",IF(PROPER(TRIM(F49))="Electronic","Electronics",IF(PROPER(TRIM(F49))="Grocery","Groceries",SUBSTITUTE(PROPER(TRIM(F49)),"Stationary","Stationery")))) -> Clothing | S49: =IF(LOWER(TRIM(H49))="online","Online",IF(OR(LOWER(TRIM(H49))="in-store",LOWER(TRIM(H49))="in store",LOWER(TRIM(H49))="instore"),"In-Store",PROPER(TRIM(H49)))) -> Online | T49: =IF(UPPER(TRIM(L49))="CC","Credit Card",PROPER(TRIM(L49))) -> Cash | U49: =IF(PROPER(TRIM(M49))="Complete","Completed",IF(PROPER(TRIM(M49))="Canceled","Cancelled",PROPER(TRIM(M49)))) -> Completed | V49: =IFERROR(VALUE(TRIM(I49)),"") -> 1 | W49: =IFERROR(VALUE(SUBSTITUTE(TRIM(J49),"$","")),"") -> 155.66 | X49: =IFERROR(IF(ISNUMBER(tblOrders[[#This Row],[OrderDate]]),tblOrders[[#This Row],[OrderDate]],IFERROR(DATEVALUE(tblOrders[[#This Row],[OrderDate]]),DATE(IF(LEN(TRIM(tblOrders[[#This Row],[OrderDate]]))=8,2000+VALUE(RIGHT(TRIM(tblOrders[[#This Row],[OrderDate]]),2)),VALUE(RIGHT(TRIM(tblOrders[[#This Row],[OrderDate]]),4))),VALUE(MID(TRIM(tblOrders[[#This Row],[OrderDate]]),4,2)),VALUE(LEFT(TRIM(tblOrders[[#This Row],[OrderDate]]),2))))),"CHECK MANUALLY") -> 45524 | Y49: =IF(K49="",0,K49) -> 0 | Z49: =TRIM(CLEAN(tblOrders[[#This Row],[Notes]])) -> Bulk order - business account | AA49: =IF(OR(V49="",W49=""),"Review",IF(V49*W49>=1000,"High Value","Standard")) -> Standard | AB49: =IF(OR(tblOrders[[#This Row],[Quantity_Clean]]="",tblOrders[[#This Row],[UnitPrice_Clean]]=""),0,tblOrders[[#This Row],[Quantity_Clean]]*tblOrders[[#This Row],[UnitPrice_Clean]]) -> 155.66 | AC49: =UPPER(TRIM(tblOrders[[#This Row],[OrderID]])) -> ORD-1053 | AD49: =VALUE(RIGHT(tblOrders[[#This Row],[OrderID]],4)) -> 1053 | AE49: =TEXT(tblOrders[[#This Row],[OrderDate_Clean]],"mmm-yyyy") -> Aug-2024 | AF49: =EOMONTH(tblOrders[[#This Row],[OrderDate_Clean]],0) -> 45535 | AG49: Robert | AH49: =IF(tblOrders[[#This Row],[Discount]]="",0,IF(ISNUMBER(tblOrders[[#This Row],[Discount]]),tblOrders[[#This Row],[Discount]],VALUE(SUBSTITUTE(TRIM(tblOrders[[#This Row],[Discount]]),"%",""))/100)) -> 0
A50: ORD-1014 | B50: 2024-10-15 | C50: ZARA JOHNSON | D50: EAST | E50: Multan | F50: clothing | G50: Formal Shirt | H50: In Store | I50: 3 | J50: 153.5 | K50: 0 | L50: Credit Card | M50: CANCELLED | N50: E. Tanaka | O50: Customer called twice | P50: =PROPER(TRIM(C50)) -> Zara Johnson | Q50: =IF(OR(PROPER(TRIM(tblOrders[[#This Row],[Region]]))="Nort",PROPER(TRIM(tblOrders[[#This Row],[Region]]))="Northh"),"North",PROPER(TRIM(tblOrders[[#This Row],[Region]]))) -> East | R50: =IF(PROPER(TRIM(F50))="Cloth Ing","Clothing",IF(PROPER(TRIM(F50))="Electronic","Electronics",IF(PROPER(TRIM(F50))="Grocery","Groceries",SUBSTITUTE(PROPER(TRIM(F50)),"Stationary","Stationery")))) -> Clothing | S50: =IF(LOWER(TRIM(H50))="online","Online",IF(OR(LOWER(TRIM(H50))="in-store",LOWER(TRIM(H50))="in store",LOWER(TRIM(H50))="instore"),"In-Store",PROPER(TRIM(H50)))) -> In-Store | T50: =IF(UPPER(TRIM(L50))="CC","Credit Card",PROPER(TRIM(L50))) -> Credit Card | U50: =IF(PROPER(TRIM(M50))="Complete","Completed",IF(PROPER(TRIM(M50))="Canceled","Cancelled",PROPER(TRIM(M50)))) -> Cancelled | V50: =IFERROR(VALUE(TRIM(I50)),"") -> 3 | W50: =IFERROR(VALUE(SUBSTITUTE(TRIM(J50),"$","")),"") -> 153.5 | X50: =IFERROR(IF(ISNUMBER(tblOrders[[#This Row],[OrderDate]]),tblOrders[[#This Row],[OrderDate]],IFERROR(DATEVALUE(tblOrders[[#This Row],[OrderDate]]),DATE(IF(LEN(TRIM(tblOrders[[#This Row],[OrderDate]]))=8,2000+VALUE(RIGHT(TRIM(tblOrders[[#This Row],[OrderDate]]),2)),VALUE(RIGHT(TRIM(tblOrders[[#This Row],[OrderDate]]),4))),VALUE(MID(TRIM(tblOrders[[#This Row],[OrderDate]]),4,2)),VALUE(LEFT(TRIM(tblOrders[[#This Row],[OrderDate]]),2))))),"CHECK MANUALLY") -> 45580 | Y50: =IF(K50="",0,K50) -> 0 | Z50: =TRIM(CLEAN(tblOrders[[#This Row],[Notes]])) -> Customer called twice | AA50: =IF(OR(V50="",W50=""),"Review",IF(V50*W50>=1000,"High Value","Standard")) -> Standard | AB50: =IF(OR(tblOrders[[#This Row],[Quantity_Clean]]="",tblOrders[[#This Row],[UnitPrice_Clean]]=""),0,tblOrders[[#This Row],[Quantity_Clean]]*tblOrders[[#This Row],[UnitPrice_Clean]]) -> 460.5 | AC50: =UPPER(TRIM(tblOrders[[#This Row],[OrderID]])) -> ORD-1014 | AD50: =VALUE(RIGHT(tblOrders[[#This Row],[OrderID]],4)) -> 1014 | AE50: =TEXT(tblOrders[[#This Row],[OrderDate_Clean]],"mmm-yyyy") -> Oct-2024 | AF50: =EOMONTH(tblOrders[[#This Row],[OrderDate_Clean]],0) -> 45596 | AG50: ZARA | AH50: =IF(tblOrders[[#This Row],[Discount]]="",0,IF(ISNUMBER(tblOrders[[#This Row],[Discount]]),tblOrders[[#This Row],[Discount]],VALUE(SUBSTITUTE(TRIM(tblOrders[[#This Row],[Discount]]),"%",""))/100)) -> 0
A51: ORD-1014 | B51: 2024-10-15 | C51: ZARA JOHNSON | D51: EAST | E51: Multan | F51: clothing | G51: Formal Shirt | H51: In Store | I51: 3 | J51: 153.5 | K51: 0 | L51: Credit Card | M51: CANCELLED | N51: E. Tanaka | O51: Customer called twice | P51: =PROPER(TRIM(C51)) -> Zara Johnson | Q51: =IF(OR(PROPER(TRIM(tblOrders[[#This Row],[Region]]))="Nort",PROPER(TRIM(tblOrders[[#This Row],[Region]]))="Northh"),"North",PROPER(TRIM(tblOrders[[#This Row],[Region]]))) -> East | R51: =IF(PROPER(TRIM(F51))="Cloth Ing","Clothing",IF(PROPER(TRIM(F51))="Electronic","Electronics",IF(PROPER(TRIM(F51))="Grocery","Groceries",SUBSTITUTE(PROPER(TRIM(F51)),"Stationary","Stationery")))) -> Clothing | S51: =IF(LOWER(TRIM(H51))="online","Online",IF(OR(LOWER(TRIM(H51))="in-store",LOWER(TRIM(H51))="in store",LOWER(TRIM(H51))="instore"),"In-Store",PROPER(TRIM(H51)))) -> In-Store | T51: =IF(UPPER(TRIM(L51))="CC","Credit Card",PROPER(TRIM(L51))) -> Credit Card | U51: =IF(PROPER(TRIM(M51))="Complete","Completed",IF(PROPER(TRIM(M51))="Canceled","Cancelled",PROPER(TRIM(M51)))) -> Cancelled | V51: =IFERROR(VALUE(TRIM(I51)),"") -> 3 | W51: =IFERROR(VALUE(SUBSTITUTE(TRIM(J51),"$","")),"") -> 153.5 | X51: =IFERROR(IF(ISNUMBER(tblOrders[[#This Row],[OrderDate]]),tblOrders[[#This Row],[OrderDate]],IFERROR(DATEVALUE(tblOrders[[#This Row],[OrderDate]]),DATE(IF(LEN(TRIM(tblOrders[[#This Row],[OrderDate]]))=8,2000+VALUE(RIGHT(TRIM(tblOrders[[#This Row],[OrderDate]]),2)),VALUE(RIGHT(TRIM(tblOrders[[#This Row],[OrderDate]]),4))),VALUE(MID(TRIM(tblOrders[[#This Row],[OrderDate]]),4,2)),VALUE(LEFT(TRIM(tblOrders[[#This Row],[OrderDate]]),2))))),"CHECK MANUALLY") -> 45580 | Y51: =IF(K51="",0,K51) -> 0 | Z51: =TRIM(CLEAN(tblOrders[[#This Row],[Notes]])) -> Customer called twice | AA51: =IF(OR(V51="",W51=""),"Review",IF(V51*W51>=1000,"High Value","Standard")) -> Standard | AB51: =IF(OR(tblOrders[[#This Row],[Quantity_Clean]]="",tblOrders[[#This Row],[UnitPrice_Clean]]=""),0,tblOrders[[#This Row],[Quantity_Clean]]*tblOrders[[#This Row],[UnitPrice_Clean]]) -> 460.5 | AC51: =UPPER(TRIM(tblOrders[[#This Row],[OrderID]])) -> ORD-1014 | AD51: =VALUE(RIGHT(tblOrders[[#This Row],[OrderID]],4)) -> 1014 | AE51: =TEXT(tblOrders[[#This Row],[OrderDate_Clean]],"mmm-yyyy") -> Oct-2024 | AF51: =EOMONTH(tblOrders[[#This Row],[OrderDate_Clean]],0) -> 45596 | AG51: ZARA | AH51: =IF(tblOrders[[#This Row],[Discount]]="",0,IF(ISNUMBER(tblOrders[[#This Row],[Discount]]),tblOrders[[#This Row],[Discount]],VALUE(SUBSTITUTE(TRIM(tblOrders[[#This Row],[Discount]]),"%",""))/100)) -> 0
A52: ORD-1025 | B52: 03/18/2024 | C52: Sofia Malik | D52: West | E52: Peshawar | F52: CLOTHING | G52: Denim Jacket | H52: In-Store | I52: 8 | J52: 146.44 | L52: Cash | M52: completed | N52: B. Fernandes | P52: =PROPER(TRIM(C52)) -> Sofia Malik | Q52: =IF(OR(PROPER(TRIM(tblOrders[[#This Row],[Region]]))="Nort",PROPER(TRIM(tblOrders[[#This Row],[Region]]))="Northh"),"North",PROPER(TRIM(tblOrders[[#This Row],[Region]]))) -> West | R52: =IF(PROPER(TRIM(F52))="Cloth Ing","Clothing",IF(PROPER(TRIM(F52))="Electronic","Electronics",IF(PROPER(TRIM(F52))="Grocery","Groceries",SUBSTITUTE(PROPER(TRIM(F52)),"Stationary","Stationery")))) -> Clothing | S52: =IF(LOWER(TRIM(H52))="online","Online",IF(OR(LOWER(TRIM(H52))="in-store",LOWER(TRIM(H52))="in store",LOWER(TRIM(H52))="instore"),"In-Store",PROPER(TRIM(H52)))) -> In-Store | T52: =IF(UPPER(TRIM(L52))="CC","Credit Card",PROPER(TRIM(L52))) -> Cash | U52: =IF(PROPER(TRIM(M52))="Complete","Completed",IF(PROPER(TRIM(M52))="Canceled","Cancelled",PROPER(TRIM(M52)))) -> Completed | V52: =IFERROR(VALUE(TRIM(I52)),"") -> 8 | W52: =IFERROR(VALUE(SUBSTITUTE(TRIM(J52),"$","")),"") -> 146.44 | X52: =IFERROR(IF(ISNUMBER(tblOrders[[#This Row],[OrderDate]]),tblOrders[[#This Row],[OrderDate]],IFERROR(DATEVALUE(tblOrders[[#This Row],[OrderDate]]),DATE(IF(LEN(TRIM(tblOrders[[#This Row],[OrderDate]]))=8,2000+VALUE(RIGHT(TRIM(tblOrders[[#This Row],[OrderDate]]),2)),VALUE(RIGHT(TRIM(tblOrders[[#This Row],[OrderDate]]),4))),VALUE(MID(TRIM(tblOrders[[#This Row],[OrderDate]]),4,2)),VALUE(LEFT(TRIM(tblOrders[[#This Row],[OrderDate]]),2))))),"CHECK MANUALLY") -> 45369 | Y52: =IF(K52="",0,K52) -> 0 | Z52: =TRIM(CLEAN(tblOrders[[#This Row],[Notes]])) | AA52: =IF(OR(V52="",W52=""),"Review",IF(V52*W52>=1000,"High Value","Standard")) -> High Value | AB52: =IF(OR(tblOrders[[#This Row],[Quantity_Clean]]="",tblOrders[[#This Row],[UnitPrice_Clean]]=""),0,tblOrders[[#This Row],[Quantity_Clean]]*tblOrders[[#This Row],[UnitPrice_Clean]]) -> 1171.52 | AC52: =UPPER(TRIM(tblOrders[[#This Row],[OrderID]])) -> ORD-1025 | AD52: =VALUE(RIGHT(tblOrders[[#This Row],[OrderID]],4)) -> 1025 | AE52: =TEXT(tblOrders[[#This Row],[OrderDate_Clean]],"mmm-yyyy") -> Mar-2024 | AF52: =EOMONTH(tblOrders[[#This Row],[OrderDate_Clean]],0) -> 45382 | AG52: Sofia | AH52: =IF(tblOrders[[#This Row],[Discount]]="",0,IF(ISNUMBER(tblOrders[[#This Row],[Discount]]),tblOrders[[#This Row],[Discount]],VALUE(SUBSTITUTE(TRIM(tblOrders[[#This Row],[Discount]]),"%",""))/100)) -> 0
A53: ORD-1025 | B53: 03/18/2024 | C53: Sofia Malik | D53: West | E53: Peshawar | F53: CLOTHING | G53: Denim Jacket | H53: In-Store | I53: 8 | J53: 146.44 | L53: Cash | M53: completed | N53: B. Fernandes | P53: =PROPER(TRIM(C53)) -> Sofia Malik | Q53: =IF(OR(PROPER(TRIM(tblOrders[[#This Row],[Region]]))="Nort",PROPER(TRIM(tblOrders[[#This Row],[Region]]))="Northh"),"North",PROPER(TRIM(tblOrders[[#This Row],[Region]]))) -> West | R53: =IF(PROPER(TRIM(F53))="Cloth Ing","Clothing",IF(PROPER(TRIM(F53))="Electronic","Electronics",IF(PROPER(TRIM(F53))="Grocery","Groceries",SUBSTITUTE(PROPER(TRIM(F53)),"Stationary","Stationery")))) -> Clothing | S53: =IF(LOWER(TRIM(H53))="online","Online",IF(OR(LOWER(TRIM(H53))="in-store",LOWER(TRIM(H53))="in store",LOWER(TRIM(H53))="instore"),"In-Store",PROPER(TRIM(H53)))) -> In-Store | T53: =IF(UPPER(TRIM(L53))="CC","Credit Card",PROPER(TRIM(L53))) -> Cash | U53: =IF(PROPER(TRIM(M53))="Complete","Completed",IF(PROPER(TRIM(M53))="Canceled","Cancelled",PROPER(TRIM(M53)))) -> Completed | V53: =IFERROR(VALUE(TRIM(I53)),"") -> 8 | W53: =IFERROR(VALUE(SUBSTITUTE(TRIM(J53),"$","")),"") -> 146.44 | X53: =IFERROR(IF(ISNUMBER(tblOrders[[#This Row],[OrderDate]]),tblOrders[[#This Row],[OrderDate]],IFERROR(DATEVALUE(tblOrders[[#This Row],[OrderDate]]),DATE(IF(LEN(TRIM(tblOrders[[#This Row],[OrderDate]]))=8,2000+VALUE(RIGHT(TRIM(tblOrders[[#This Row],[OrderDate]]),2)),VALUE(RIGHT(TRIM(tblOrders[[#This Row],[OrderDate]]),4))),VALUE(MID(TRIM(tblOrders[[#This Row],[OrderDate]]),4,2)),VALUE(LEFT(TRIM(tblOrders[[#This Row],[OrderDate]]),2))))),"CHECK MANUALLY") -> 45369 | Y53: =IF(K53="",0,K53) -> 0 | Z53: =TRIM(CLEAN(tblOrders[[#This Row],[Notes]])) | AA53: =IF(OR(V53="",W53=""),"Review",IF(V53*W53>=1000,"High Value","Standard")) -> High Value | AB53: =IF(OR(tblOrders[[#This Row],[Quantity_Clean]]="",tblOrders[[#This Row],[UnitPrice_Clean]]=""),0,tblOrders[[#This Row],[Quantity_Clean]]*tblOrders[[#This Row],[UnitPrice_Clean]]) -> 1171.52 | AC53: =UPPER(TRIM(tblOrders[[#This Row],[OrderID]])) -> ORD-1025 | AD53: =VALUE(RIGHT(tblOrders[[#This Row],[OrderID]],4)) -> 1025 | AE53: =TEXT(tblOrders[[#This Row],[OrderDate_Clean]],"mmm-yyyy") -> Mar-2024 | AF53: =EOMONTH(tblOrders[[#This Row],[OrderDate_Clean]],0) -> 45382 | AG53: Sofia | AH53: =IF(tblOrders[[#This Row],[Discount]]="",0,IF(ISNUMBER(tblOrders[[#This Row],[Discount]]),tblOrders[[#This Row],[Discount]],VALUE(SUBSTITUTE(TRIM(tblOrders[[#This Row],[Discount]]),"%",""))/100)) -> 0
A54: ORD-1081 | B54: July 05, 2024 | C54: hina raza | D54: West | E54: Quetta | F54: CLOTHING | G54: Cotton T-Shirt | H54: in-store | I54: 10 | J54: 140.9 | K54: 0 | L54: Cash | M54: PENDING | N54: D. Iqbal | O54: Follow up needed | P54: =PROPER(TRIM(C54)) -> Hina Raza | Q54: =IF(OR(PROPER(TRIM(tblOrders[[#This Row],[Region]]))="Nort",PROPER(TRIM(tblOrders[[#This Row],[Region]]))="Northh"),"North",PROPER(TRIM(tblOrders[[#This Row],[Region]]))) -> West | R54: =IF(PROPER(TRIM(F54))="Cloth Ing","Clothing",IF(PROPER(TRIM(F54))="Electronic","Electronics",IF(PROPER(TRIM(F54))="Grocery","Groceries",SUBSTITUTE(PROPER(TRIM(F54)),"Stationary","Stationery")))) -> Clothing | S54: =IF(LOWER(TRIM(H54))="online","Online",IF(OR(LOWER(TRIM(H54))="in-store",LOWER(TRIM(H54))="in store",LOWER(TRIM(H54))="instore"),"In-Store",PROPER(TRIM(H54)))) -> In-Store | T54: =IF(UPPER(TRIM(L54))="CC","Credit Card",PROPER(TRIM(L54))) -> Cash | U54: =IF(PROPER(TRIM(M54))="Complete","Completed",IF(PROPER(TRIM(M54))="Canceled","Cancelled",PROPER(TRIM(M54)))) -> Pending | V54: =IFERROR(VALUE(TRIM(I54)),"") -> 10 | W54: =IFERROR(VALUE(SUBSTITUTE(TRIM(J54),"$","")),"") -> 140.9 | X54: =IFERROR(IF(ISNUMBER(tblOrders[[#This Row],[OrderDate]]),tblOrders[[#This Row],[OrderDate]],IFERROR(DATEVALUE(tblOrders[[#This Row],[OrderDate]]),DATE(IF(LEN(TRIM(tblOrders[[#This Row],[OrderDate]]))=8,2000+VALUE(RIGHT(TRIM(tblOrders[[#This Row],[OrderDate]]),2)),VALUE(RIGHT(TRIM(tblOrders[[#This Row],[OrderDate]]),4))),VALUE(MID(TRIM(tblOrders[[#This Row],[OrderDate]]),4,2)),VALUE(LEFT(TRIM(tblOrders[[#This Row],[OrderDate]]),2))))),"CHECK MANUALLY") -> 45478 | Y54: =IF(K54="",0,K54) -> 0 | Z54: =TRIM(CLEAN(tblOrders[[#This Row],[Notes]])) -> Follow up needed | AA54: =IF(OR(V54="",W54=""),"Review",IF(V54*W54>=1000,"High Value","Standard")) -> High Value | AB54: =IF(OR(tblOrders[[#This Row],[Quantity_Clean]]="",tblOrders[[#This Row],[UnitPrice_Clean]]=""),0,tblOrders[[#This Row],[Quantity_Clean]]*tblOrders[[#This Row],[UnitPrice_Clean]]) -> 1409 | AC54: =UPPER(TRIM(tblOrders[[#This Row],[OrderID]])) -> ORD-1081 | AD54: =VALUE(RIGHT(tblOrders[[#This Row],[OrderID]],4)) -> 1081 | AE54: =TEXT(tblOrders[[#This Row],[OrderDate_Clean]],"mmm-yyyy") -> Jul-2024 | AF54: =EOMONTH(tblOrders[[#This Row],[OrderDate_Clean]],0) -> 45504 | AG54: hina | AH54: =IF(tblOrders[[#This Row],[Discount]]="",0,IF(ISNUMBER(tblOrders[[#This Row],[Discount]]),tblOrders[[#This Row],[Discount]],VALUE(SUBSTITUTE(TRIM(tblOrders[[#This Row],[Discount]]),"%",""))/100)) -> 0
A55: ORD-1134 | B55: 22-May-24 | C55: Umar Hussain | D55: east | E55: Multan | F55: clothing | G55: Running Shoes | H55: instore | I55: 3 | J55: 138.01 | K55: 0 | L55: debit card | M55: Pending | O55: Damaged on arrival - replaced | P55: =PROPER(TRIM(C55)) -> Umar Hussain | Q55: =IF(OR(PROPER(TRIM(tblOrders[[#This Row],[Region]]))="Nort",PROPER(TRIM(tblOrders[[#This Row],[Region]]))="Northh"),"North",PROPER(TRIM(tblOrders[[#This Row],[Region]]))) -> East | R55: =IF(PROPER(TRIM(F55))="Cloth Ing","Clothing",IF(PROPER(TRIM(F55))="Electronic","Electronics",IF(PROPER(TRIM(F55))="Grocery","Groceries",SUBSTITUTE(PROPER(TRIM(F55)),"Stationary","Stationery")))) -> Clothing | S55: =IF(LOWER(TRIM(H55))="online","Online",IF(OR(LOWER(TRIM(H55))="in-store",LOWER(TRIM(H55))="in store",LOWER(TRIM(H55))="instore"),"In-Store",PROPER(TRIM(H55)))) -> In-Store | T55: =IF(UPPER(TRIM(L55))="CC","Credit Card",PROPER(TRIM(L55))) -> Debit Card | U55: =IF(PROPER(TRIM(M55))="Complete","Completed",IF(PROPER(TRIM(M55))="Canceled","Cancelled",PROPER(TRIM(M55)))) -> Pending | V55: =IFERROR(VALUE(TRIM(I55)),"") -> 3 | W55: =IFERROR(VALUE(SUBSTITUTE(TRIM(J55),"$","")),"") -> 138.01 | X55: =IFERROR(IF(ISNUMBER(tblOrders[[#This Row],[OrderDate]]),tblOrders[[#This Row],[OrderDate]],IFERROR(DATEVALUE(tblOrders[[#This Row],[OrderDate]]),DATE(IF(LEN(TRIM(tblOrders[[#This Row],[OrderDate]]))=8,2000+VALUE(RIGHT(TRIM(tblOrders[[#This Row],[OrderDate]]),2)),VALUE(RIGHT(TRIM(tblOrders[[#This Row],[OrderDate]]),4))),VALUE(MID(TRIM(tblOrders[[#This Row],[OrderDate]]),4,2)),VALUE(LEFT(TRIM(tblOrders[[#This Row],[OrderDate]]),2))))),"CHECK MANUALLY") -> 45434 | Y55: =IF(K55="",0,K55) -> 0 | Z55: =TRIM(CLEAN(tblOrders[[#This Row],[Notes]])) -> Damaged on arrival - replaced | AA55: =IF(OR(V55="",W55=""),"Review",IF(V55*W55>=1000,"High Value","Standard")) -> Standard | AB55: =IF(OR(tblOrders[[#This Row],[Quantity_Clean]]="",tblOrders[[#This Row],[UnitPrice_Clean]]=""),0,tblOrders[[#This Row],[Quantity_Clean]]*tblOrders[[#This Row],[UnitPrice_Clean]]) -> 414.03 | AC55: =UPPER(TRIM(tblOrders[[#This Row],[OrderID]])) -> ORD-1134 | AD55: =VALUE(RIGHT(tblOrders[[#This Row],[OrderID]],4)) -> 1134 | AE55: =TEXT(tblOrders[[#This Row],[OrderDate_Clean]],"mmm-yyyy") -> May-2024 | AF55: =EOMONTH(tblOrders[[#This Row],[OrderDate_Clean]],0) -> 45443 | AG55: Umar | AH55: =IF(tblOrders[[#This Row],[Discount]]="",0,IF(ISNUMBER(tblOrders[[#This Row],[Discount]]),tblOrders[[#This Row],[Discount]],VALUE(SUBSTITUTE(TRIM(tblOrders[[#This Row],[Discount]]),"%",""))/100)) -> 0
A56: ORD-1111 | B56: 06/12/2024 | C56: Yusuf Ahmed | D56: South | E56: Karachi | F56: CLOTHING | G56: Running Shoes | H56: In-store | I56: 11 | J56: 134.47 | K56: 0 | L56: bank transfer | M56: Refunded | N56: D. Iqbal | P56: =PROPER(TRIM(C56)) -> Yusuf Ahmed | Q56: =IF(OR(PROPER(TRIM(tblOrders[[#This Row],[Region]]))="Nort",PROPER(TRIM(tblOrders[[#This Row],[Region]]))="Northh"),"North",PROPER(TRIM(tblOrders[[#This Row],[Region]]))) -> South | R56: =IF(PROPER(TRIM(F56))="Cloth Ing","Clothing",IF(PROPER(TRIM(F56))="Electronic","Electronics",IF(PROPER(TRIM(F56))="Grocery","Groceries",SUBSTITUTE(PROPER(TRIM(F56)),"Stationary","Stationery")))) -> Clothing | S56: =IF(LOWER(TRIM(H56))="online","Online",IF(OR(LOWER(TRIM(H56))="in-store",LOWER(TRIM(H56))="in store",LOWER(TRIM(H56))="instore"),"In-Store",PROPER(TRIM(H56)))) -> In-Store | T56: =IF(UPPER(TRIM(L56))="CC","Credit Card",PROPER(TRIM(L56))) -> Bank Transfer | U56: =IF(PROPER(TRIM(M56))="Complete","Completed",IF(PROPER(TRIM(M56))="Canceled","Cancelled",PROPER(TRIM(M56)))) -> Refunded | V56: =IFERROR(VALUE(TRIM(I56)),"") -> 11 | W56: =IFERROR(VALUE(SUBSTITUTE(TRIM(J56),"$","")),"") -> 134.47 | X56: =IFERROR(IF(ISNUMBER(tblOrders[[#This Row],[OrderDate]]),tblOrders[[#This Row],[OrderDate]],IFERROR(DATEVALUE(tblOrders[[#This Row],[OrderDate]]),DATE(IF(LEN(TRIM(tblOrders[[#This Row],[OrderDate]]))=8,2000+VALUE(RIGHT(TRIM(tblOrders[[#This Row],[OrderDate]]),2)),VALUE(RIGHT(TRIM(tblOrders[[#This Row],[OrderDate]]),4))),VALUE(MID(TRIM(tblOrders[[#This Row],[OrderDate]]),4,2)),VALUE(LEFT(TRIM(tblOrders[[#This Row],[OrderDate]]),2))))),"CHECK MANUALLY") -> 45455 | Y56: =IF(K56="",0,K56) -> 0 | Z56: =TRIM(CLEAN(tblOrders[[#This Row],[Notes]])) | AA56: =IF(OR(V56="",W56=""),"Review",IF(V56*W56>=1000,"High Value","Standard")) -> High Value | AB56: =IF(OR(tblOrders[[#This Row],[Quantity_Clean]]="",tblOrders[[#This Row],[UnitPrice_Clean]]=""),0,tblOrders[[#This Row],[Quantity_Clean]]*tblOrders[[#This Row],[UnitPrice_Clean]]) -> 1479.17 | AC56: =UPPER(TRIM(tblOrders[[#This Row],[OrderID]])) -> ORD-1111 | AD56: =VALUE(RIGHT(tblOrders[[#This Row],[OrderID]],4)) -> 1111 | AE56: =TEXT(tblOrders[[#This Row],[OrderDate_Clean]],"mmm-yyyy") -> Jun-2024 | AF56: =EOMONTH(tblOrders[[#This Row],[OrderDate_Clean]],0) -> 45473 | AG56: Yusuf | AH56: =IF(tblOrders[[#This Row],[Discount]]="",0,IF(ISNUMBER(tblOrders[[#This Row],[Discount]]),tblOrders[[#This Row],[Discount]],VALUE(SUBSTITUTE(TRIM(tblOrders[[#This Row],[Discount]]),"%",""))/100)) -> 0
A57: ORD-1150 | B57: 17-Dec-24 | C57: Umar Lewis | D57: South | E57: Karachi | F57: CLOTHING | G57: Cotton T-Shirt | H57: In-store | I57: 6 | J57: 107.78 | L57: credit card | M57: completed | N57: B. Fernandes | O57: Gift wrap requested | P57: =PROPER(TRIM(C57)) -> Umar Lewis | Q57: =IF(OR(PROPER(TRIM(tblOrders[[#This Row],[Region]]))="Nort",PROPER(TRIM(tblOrders[[#This Row],[Region]]))="Northh"),"North",PROPER(TRIM(tblOrders[[#This Row],[Region]]))) -> South | R57: =IF(PROPER(TRIM(F57))="Cloth Ing","Clothing",IF(PROPER(TRIM(F57))="Electronic","Electronics",IF(PROPER(TRIM(F57))="Grocery","Groceries",SUBSTITUTE(PROPER(TRIM(F57)),"Stationary","Stationery")))) -> Clothing | S57: =IF(LOWER(TRIM(H57))="online","Online",IF(OR(LOWER(TRIM(H57))="in-store",LOWER(TRIM(H57))="in store",LOWER(TRIM(H57))="instore"),"In-Store",PROPER(TRIM(H57)))) -> In-Store | T57: =IF(UPPER(TRIM(L57))="CC","Credit Card",PROPER(TRIM(L57))) -> Credit Card | U57: =IF(PROPER(TRIM(M57))="Complete","Completed",IF(PROPER(TRIM(M57))="Canceled","Cancelled",PROPER(TRIM(M57)))) -> Completed | V57: =IFERROR(VALUE(TRIM(I57)),"") -> 6 | W57: =IFERROR(VALUE(SUBSTITUTE(TRIM(J57),"$","")),"") -> 107.78 | X57: =IFERROR(IF(ISNUMBER(tblOrders[[#This Row],[OrderDate]]),tblOrders[[#This Row],[OrderDate]],IFERROR(DATEVALUE(tblOrders[[#This Row],[OrderDate]]),DATE(IF(LEN(TRIM(tblOrders[[#This Row],[OrderDate]]))=8,2000+VALUE(RIGHT(TRIM(tblOrders[[#This Row],[OrderDate]]),2)),VALUE(RIGHT(TRIM(tblOrders[[#This Row],[OrderDate]]),4))),VALUE(MID(TRIM(tblOrders[[#This Row],[OrderDate]]),4,2)),VALUE(LEFT(TRIM(tblOrders[[#This Row],[OrderDate]]),2))))),"CHECK MANUALLY") -> 45643 | Y57: =IF(K57="",0,K57) -> 0 | Z57: =TRIM(CLEAN(tblOrders[[#This Row],[Notes]])) -> Gift wrap requested | AA57: =IF(OR(V57="",W57=""),"Review",IF(V57*W57>=1000,"High Value","Standard")) -> Standard | AB57: =IF(OR(tblOrders[[#This Row],[Quantity_Clean]]="",tblOrders[[#This Row],[UnitPrice_Clean]]=""),0,tblOrders[[#This Row],[Quantity_Clean]]*tblOrders[[#This Row],[UnitPrice_Clean]]) -> 646.68 | AC57: =UPPER(TRIM(tblOrders[[#This Row],[OrderID]])) -> ORD-1150 | AD57: =VALUE(RIGHT(tblOrders[[#This Row],[OrderID]],4)) -> 1150 | AE57: =TEXT(tblOrders[[#This Row],[OrderDate_Clean]],"mmm-yyyy") -> Dec-2024 | AF57: =EOMONTH(tblOrders[[#This Row],[OrderDate_Clean]],0) -> 45657 | AG57: Umar | AH57: =IF(tblOrders[[#This Row],[Discount]]="",0,IF(ISNUMBER(tblOrders[[#This Row],[Discount]]),tblOrders[[#This Row],[Discount]],VALUE(SUBSTITUTE(TRIM(tblOrders[[#This Row],[Discount]]),"%",""))/100)) -> 0
A58: ORD-1074 | B58: 2024-07-31 | C58: tom iqbal | D58: North | E58: Faisalabad | F58: Clothing | G58: Denim Jacket | H58: In-Store | I58: 8 | J58: 77.94 | K58: 0.05 | L58: Debit card | M58: cancelled | N58: A. Malik | P58: =PROPER(TRIM(C58)) -> Tom Iqbal | Q58: =IF(OR(PROPER(TRIM(tblOrders[[#This Row],[Region]]))="Nort",PROPER(TRIM(tblOrders[[#This Row],[Region]]))="Northh"),"North",PROPER(TRIM(tblOrders[[#This Row],[Region]]))) -> North | R58: =IF(PROPER(TRIM(F58))="Cloth Ing","Clothing",IF(PROPER(TRIM(F58))="Electronic","Electronics",IF(PROPER(TRIM(F58))="Grocery","Groceries",SUBSTITUTE(PROPER(TRIM(F58)),"Stationary","Stationery")))) -> Clothing | S58: =IF(LOWER(TRIM(H58))="online","Online",IF(OR(LOWER(TRIM(H58))="in-store",LOWER(TRIM(H58))="in store",LOWER(TRIM(H58))="instore"),"In-Store",PROPER(TRIM(H58)))) -> In-Store | T58: =IF(UPPER(TRIM(L58))="CC","Credit Card",PROPER(TRIM(L58))) -> Debit Card | U58: =IF(PROPER(TRIM(M58))="Complete","Completed",IF(PROPER(TRIM(M58))="Canceled","Cancelled",PROPER(TRIM(M58)))) -> Cancelled | V58: =IFERROR(VALUE(TRIM(I58)),"") -> 8 | W58: =IFERROR(VALUE(SUBSTITUTE(TRIM(J58),"$","")),"") -> 77.94 | X58: =IFERROR(IF(ISNUMBER(tblOrders[[#This Row],[OrderDate]]),tblOrders[[#This Row],[OrderDate]],IFERROR(DATEVALUE(tblOrders[[#This Row],[OrderDate]]),DATE(IF(LEN(TRIM(tblOrders[[#This Row],[OrderDate]]))=8,2000+VALUE(RIGHT(TRIM(tblOrders[[#This Row],[OrderDate]]),2)),VALUE(RIGHT(TRIM(tblOrders[[#This Row],[OrderDate]]),4))),VALUE(MID(TRIM(tblOrders[[#This Row],[OrderDate]]),4,2)),VALUE(LEFT(TRIM(tblOrders[[#This Row],[OrderDate]]),2))))),"CHECK MANUALLY") -> 45504 | Y58: =IF(K58="",0,K58) -> 0.05 | Z58: =TRIM(CLEAN(tblOrders[[#This Row],[Notes]])) | AA58: =IF(OR(V58="",W58=""),"Review",IF(V58*W58>=1000,"High Value","Standard")) -> Standard | AB58: =IF(OR(tblOrders[[#This Row],[Quantity_Clean]]="",tblOrders[[#This Row],[UnitPrice_Clean]]=""),0,tblOrders[[#This Row],[Quantity_Clean]]*tblOrders[[#This Row],[UnitPrice_Clean]]) -> 623.52 | AC58: =UPPER(TRIM(tblOrders[[#This Row],[OrderID]])) -> ORD-1074 | AD58: =VALUE(RIGHT(tblOrders[[#This Row],[OrderID]],4)) -> 1074 | AE58: =TEXT(tblOrders[[#This Row],[OrderDate_Clean]],"mmm-yyyy") -> Jul-2024 | AF58: =EOMONTH(tblOrders[[#This Row],[OrderDate_Clean]],0) -> 45504 | AG58: tom | AH58: =IF(tblOrders[[#This Row],[Discount]]="",0,IF(ISNUMBER(tblOrders[[#This Row],[Discount]]),tblOrders[[#This Row],[Discount]],VALUE(SUBSTITUTE(TRIM(tblOrders[[#This Row],[Discount]]),"%",""))/100)) -> 0.05
A59: ORD-1065 | B59: 10/02/2024 | C59: Noah Anderson | D59: WEST | E59: Quetta | F59: clothing | G59: Winter Coat | H59: instore | I59: 12 | J59: 48.62 | L59: cash | M59: Canceled | N59: E. Tanaka | O59: Leave at front desk | P59: =PROPER(TRIM(C59)) -> Noah Anderson | Q59: =IF(OR(PROPER(TRIM(tblOrders[[#This Row],[Region]]))="Nort",PROPER(TRIM(tblOrders[[#This Row],[Region]]))="Northh"),"North",PROPER(TRIM(tblOrders[[#This Row],[Region]]))) -> West | R59: =IF(PROPER(TRIM(F59))="Cloth Ing","Clothing",IF(PROPER(TRIM(F59))="Electronic","Electronics",IF(PROPER(TRIM(F59))="Grocery","Groceries",SUBSTITUTE(PROPER(TRIM(F59)),"Stationary","Stationery")))) -> Clothing | S59: =IF(LOWER(TRIM(H59))="online","Online",IF(OR(LOWER(TRIM(H59))="in-store",LOWER(TRIM(H59))="in store",LOWER(TRIM(H59))="instore"),"In-Store",PROPER(TRIM(H59)))) -> In-Store | T59: =IF(UPPER(TRIM(L59))="CC","Credit Card",PROPER(TRIM(L59))) -> Cash | U59: =IF(PROPER(TRIM(M59))="Complete","Completed",IF(PROPER(TRIM(M59))="Canceled","Cancelled",PROPER(TRIM(M59)))) -> Cancelled | V59: =IFERROR(VALUE(TRIM(I59)),"") -> 12 | W59: =IFERROR(VALUE(SUBSTITUTE(TRIM(J59),"$","")),"") -> 48.62 | X59: =IFERROR(IF(ISNUMBER(tblOrders[[#This Row],[OrderDate]]),tblOrders[[#This Row],[OrderDate]],IFERROR(DATEVALUE(tblOrders[[#This Row],[OrderDate]]),DATE(IF(LEN(TRIM(tblOrders[[#This Row],[OrderDate]]))=8,2000+VALUE(RIGHT(TRIM(tblOrders[[#This Row],[OrderDate]]),2)),VALUE(RIGHT(TRIM(tblOrders[[#This Row],[OrderDate]]),4))),VALUE(MID(TRIM(tblOrders[[#This Row],[OrderDate]]),4,2)),VALUE(LEFT(TRIM(tblOrders[[#This Row],[OrderDate]]),2))))),"CHECK MANUALLY") -> 45567 | Y59: =IF(K59="",0,K59) -> 0 | Z59: =TRIM(CLEAN(tblOrders[[#This Row],[Notes]])) -> Leave at front desk | AA59: =IF(OR(V59="",W59=""),"Review",IF(V59*W59>=1000,"High Value","Standard")) -> Standard | AB59: =IF(OR(tblOrders[[#This Row],[Quantity_Clean]]="",tblOrders[[#This Row],[UnitPrice_Clean]]=""),0,tblOrders[[#This Row],[Quantity_Clean]]*tblOrders[[#This Row],[UnitPrice_Clean]]) -> 583.44 | AC59: =UPPER(TRIM(tblOrders[[#This Row],[OrderID]])) -> ORD-1065 | AD59: =VALUE(RIGHT(tblOrders[[#This Row],[OrderID]],4)) -> 1065 | AE59: =TEXT(tblOrders[[#This Row],[OrderDate_Clean]],"mmm-yyyy") -> Oct-2024 | AF59: =EOMONTH(tblOrders[[#This Row],[OrderDate_Clean]],0) -> 45596 | AG59: Noah | AH59: =IF(tblOrders[[#This Row],[Discount]]="",0,IF(ISNUMBER(tblOrders[[#This Row],[Discount]]),tblOrders[[#This Row],[Discount]],VALUE(SUBSTITUTE(TRIM(tblOrders[[#This Row],[Discount]]),"%",""))/100)) -> 0
A60: ORD-1144 | B60: 2024-07-03 | C60: Kevin Clark | D60: east | E60: Sialkot | F60: Clothing | G60: Cotton T-Shirt | H60: in-store | I60: 7 | J60: 36.62 | K60: 0% | L60: Debit card | M60: CANCELLED | N60: E. Tanaka | O60: Damaged on arrival - replaced | P60: =PROPER(TRIM(C60)) -> Kevin Clark | Q60: =IF(OR(PROPER(TRIM(tblOrders[[#This Row],[Region]]))="Nort",PROPER(TRIM(tblOrders[[#This Row],[Region]]))="Northh"),"North",PROPER(TRIM(tblOrders[[#This Row],[Region]]))) -> East | R60: =IF(PROPER(TRIM(F60))="Cloth Ing","Clothing",IF(PROPER(TRIM(F60))="Electronic","Electronics",IF(PROPER(TRIM(F60))="Grocery","Groceries",SUBSTITUTE(PROPER(TRIM(F60)),"Stationary","Stationery")))) -> Clothing | S60: =IF(LOWER(TRIM(H60))="online","Online",IF(OR(LOWER(TRIM(H60))="in-store",LOWER(TRIM(H60))="in store",LOWER(TRIM(H60))="instore"),"In-Store",PROPER(TRIM(H60)))) -> In-Store | T60: =IF(UPPER(TRIM(L60))="CC","Credit Card",PROPER(TRIM(L60))) -> Debit Card | U60: =IF(PROPER(TRIM(M60))="Complete","Completed",IF(PROPER(TRIM(M60))="Canceled","Cancelled",PROPER(TRIM(M60)))) -> Cancelled | V60: =IFERROR(VALUE(TRIM(I60)),"") -> 7 | W60: =IFERROR(VALUE(SUBSTITUTE(TRIM(J60),"$","")),"") -> 36.62 | X60: =IFERROR(IF(ISNUMBER(tblOrders[[#This Row],[OrderDate]]),tblOrders[[#This Row],[OrderDate]],IFERROR(DATEVALUE(tblOrders[[#This Row],[OrderDate]]),DATE(IF(LEN(TRIM(tblOrders[[#This Row],[OrderDate]]))=8,2000+VALUE(RIGHT(TRIM(tblOrders[[#This Row],[OrderDate]]),2)),VALUE(RIGHT(TRIM(tblOrders[[#This Row],[OrderDate]]),4))),VALUE(MID(TRIM(tblOrders[[#This Row],[OrderDate]]),4,2)),VALUE(LEFT(TRIM(tblOrders[[#This Row],[OrderDate]]),2))))),"CHECK MANUALLY") -> 45476 | Y60: =IF(K60="",0,K60) -> 0% | Z60: =TRIM(CLEAN(tblOrders[[#This Row],[Notes]])) -> Damaged on arrival - replaced | AA60: =IF(OR(V60="",W60=""),"Review",IF(V60*W60>=1000,"High Value","Standard")) -> Standard | AB60: =IF(OR(tblOrders[[#This Row],[Quantity_Clean]]="",tblOrders[[#This Row],[UnitPrice_Clean]]=""),0,tblOrders[[#This Row],[Quantity_Clean]]*tblOrders[[#This Row],[UnitPrice_Clean]]) -> 256.34 | AC60: =UPPER(TRIM(tblOrders[[#This Row],[OrderID]])) -> ORD-1144 | AD60: =VALUE(RIGHT(tblOrders[[#This Row],[OrderID]],4)) -> 1144 | AE60: =TEXT(tblOrders[[#This Row],[OrderDate_Clean]],"mmm-yyyy") -> Jul-2024 | AF60: =EOMONTH(tblOrders[[#This Row],[OrderDate_Clean]],0) -> 45504 | AG60: Kevin | AH60: =IF(tblOrders[[#This Row],[Discount]]="",0,IF(ISNUMBER(tblOrders[[#This Row],[Discount]]),tblOrders[[#This Row],[Discount]],VALUE(SUBSTITUTE(TRIM(tblOrders[[#This Row],[Discount]]),"%",""))/100)) -> 0
A61: ORD-1035 | B61: 25/05/2024 | C61: Zara Raza | D61: SOUTH | E61: Karachi | F61: Clothing | G61: Winter Coat | H61: ONLINE | J61: 31.99 | K61: 0.15 | L61: credit card | M61: Completed | N61: E. Tanaka | O61: Damaged on arrival - replaced | P61: =PROPER(TRIM(C61)) -> Zara Raza | Q61: =IF(OR(PROPER(TRIM(tblOrders[[#This Row],[Region]]))="Nort",PROPER(TRIM(tblOrders[[#This Row],[Region]]))="Northh"),"North",PROPER(TRIM(tblOrders[[#This Row],[Region]]))) -> South | R61: =IF(PROPER(TRIM(F61))="Cloth Ing","Clothing",IF(PROPER(TRIM(F61))="Electronic","Electronics",IF(PROPER(TRIM(F61))="Grocery","Groceries",SUBSTITUTE(PROPER(TRIM(F61)),"Stationary","Stationery")))) -> Clothing | S61: =IF(LOWER(TRIM(H61))="online","Online",IF(OR(LOWER(TRIM(H61))="in-store",LOWER(TRIM(H61))="in store",LOWER(TRIM(H61))="instore"),"In-Store",PROPER(TRIM(H61)))) -> Online | T61: =IF(UPPER(TRIM(L61))="CC","Credit Card",PROPER(TRIM(L61))) -> Credit Card | U61: =IF(PROPER(TRIM(M61))="Complete","Completed",IF(PROPER(TRIM(M61))="Canceled","Cancelled",PROPER(TRIM(M61)))) -> Completed | V61: =IFERROR(VALUE(TRIM(I61)),"") | W61: =IFERROR(VALUE(SUBSTITUTE(TRIM(J61),"$","")),"") -> 31.99 | X61: =IFERROR(IF(ISNUMBER(tblOrders[[#This Row],[OrderDate]]),tblOrders[[#This Row],[OrderDate]],IFERROR(DATEVALUE(tblOrders[[#This Row],[OrderDate]]),DATE(IF(LEN(TRIM(tblOrders[[#This Row],[OrderDate]]))=8,2000+VALUE(RIGHT(TRIM(tblOrders[[#This Row],[OrderDate]]),2)),VALUE(RIGHT(TRIM(tblOrders[[#This Row],[OrderDate]]),4))),VALUE(MID(TRIM(tblOrders[[#This Row],[OrderDate]]),4,2)),VALUE(LEFT(TRIM(tblOrders[[#This Row],[OrderDate]]),2))))),"CHECK MANUALLY") -> 45437 | Y61: =IF(K61="",0,K61) -> 0.15 | Z61: =TRIM(CLEAN(tblOrders[[#This Row],[Notes]])) -> Damaged on arrival - replaced | AA61: =IF(OR(V61="",W61=""),"Review",IF(V61*W61>=1000,"High Value","Standard")) -> Review | AB61: =IF(OR(tblOrders[[#This Row],[Quantity_Clean]]="",tblOrders[[#This Row],[UnitPrice_Clean]]=""),0,tblOrders[[#This Row],[Quantity_Clean]]*tblOrders[[#This Row],[UnitPrice_Clean]]) -> 0 | AC61: =UPPER(TRIM(tblOrders[[#This Row],[OrderID]])) -> ORD-1035 | AD61: =VALUE(RIGHT(tblOrders[[#This Row],[OrderID]],4)) -> 1035 | AE61: =TEXT(tblOrders[[#This Row],[OrderDate_Clean]],"mmm-yyyy") -> May-2024 | AF61: =EOMONTH(tblOrders[[#This Row],[OrderDate_Clean]],0) -> 45443 | AG61: Zara | AH61: =IF(tblOrders[[#This Row],[Discount]]="",0,IF(ISNUMBER(tblOrders[[#This Row],[Discount]]),tblOrders[[#This Row],[Discount]],VALUE(SUBSTITUTE(TRIM(tblOrders[[#This Row],[Discount]]),"%",""))/100)) -> 0.15
A62: ORD-1168 | B62: 2024-12-16 | C62: sarah malik | D62: west | F62: clothing | G62: Cotton T-Shirt | H62: instore | I62: 5 | J62: 15.02 | L62: CC | M62: CANCELLED | O62: VIP customer | P62: =PROPER(TRIM(C62)) -> Sarah Malik | Q62: =IF(OR(PROPER(TRIM(tblOrders[[#This Row],[Region]]))="Nort",PROPER(TRIM(tblOrders[[#This Row],[Region]]))="Northh"),"North",PROPER(TRIM(tblOrders[[#This Row],[Region]]))) -> West | R62: =IF(PROPER(TRIM(F62))="Cloth Ing","Clothing",IF(PROPER(TRIM(F62))="Electronic","Electronics",IF(PROPER(TRIM(F62))="Grocery","Groceries",SUBSTITUTE(PROPER(TRIM(F62)),"Stationary","Stationery")))) -> Clothing | S62: =IF(LOWER(TRIM(H62))="online","Online",IF(OR(LOWER(TRIM(H62))="in-store",LOWER(TRIM(H62))="in store",LOWER(TRIM(H62))="instore"),"In-Store",PROPER(TRIM(H62)))) -> In-Store | T62: =IF(UPPER(TRIM(L62))="CC","Credit Card",PROPER(TRIM(L62))) -> Credit Card | U62: =IF(PROPER(TRIM(M62))="Complete","Completed",IF(PROPER(TRIM(M62))="Canceled","Cancelled",PROPER(TRIM(M62)))) -> Cancelled | V62: =IFERROR(VALUE(TRIM(I62)),"") -> 5 | W62: =IFERROR(VALUE(SUBSTITUTE(TRIM(J62),"$","")),"") -> 15.02 | X62: =IFERROR(IF(ISNUMBER(tblOrders[[#This Row],[OrderDate]]),tblOrders[[#This Row],[OrderDate]],IFERROR(DATEVALUE(tblOrders[[#This Row],[OrderDate]]),DATE(IF(LEN(TRIM(tblOrders[[#This Row],[OrderDate]]))=8,2000+VALUE(RIGHT(TRIM(tblOrders[[#This Row],[OrderDate]]),2)),VALUE(RIGHT(TRIM(tblOrders[[#This Row],[OrderDate]]),4))),VALUE(MID(TRIM(tblOrders[[#This Row],[OrderDate]]),4,2)),VALUE(LEFT(TRIM(tblOrders[[#This Row],[OrderDate]]),2))))),"CHECK MANUALLY") -> 45642 | Y62: =IF(K62="",0,K62) -> 0 | Z62: =TRIM(CLEAN(tblOrders[[#This Row],[Notes]])) -> VIP customer | AA62: =IF(OR(V62="",W62=""),"Review",IF(V62*W62>=1000,"High Value","Standard")) -> Standard | AB62: =IF(OR(tblOrders[[#This Row],[Quantity_Clean]]="",tblOrders[[#This Row],[UnitPrice_Clean]]=""),0,tblOrders[[#This Row],[Quantity_Clean]]*tblOrders[[#This Row],[UnitPrice_Clean]]) -> 75.1 | AC62: =UPPER(TRIM(tblOrders[[#This Row],[OrderID]])) -> ORD-1168 | AD62: =VALUE(RIGHT(tblOrders[[#This Row],[OrderID]],4)) -> 1168 | AE62: =TEXT(tblOrders[[#This Row],[OrderDate_Clean]],"mmm-yyyy") -> Dec-2024 | AF62: =EOMONTH(tblOrders[[#This Row],[OrderDate_Clean]],0) -> 45657 | AG62: sarah | AH62: =IF(tblOrders[[#This Row],[Discount]]="",0,IF(ISNUMBER(tblOrders[[#This Row],[Discount]]),tblOrders[[#This Row],[Discount]],VALUE(SUBSTITUTE(TRIM(tblOrders[[#This Row],[Discount]]),"%",""))/100)) -> 0
A63: ORD-1156 | B63: 26/09/2024 | C63: Priya Ahmed | D63: EAST | E63: Multan | F63: clothing | G63: Winter Coat | H63: Online | I63: 8 | L63: cash | M63: Complete | N63: A. Malik | O63: Gift wrap requested | P63: =PROPER(TRIM(C63)) -> Priya Ahmed | Q63: =IF(OR(PROPER(TRIM(tblOrders[[#This Row],[Region]]))="Nort",PROPER(TRIM(tblOrders[[#This Row],[Region]]))="Northh"),"North",PROPER(TRIM(tblOrders[[#This Row],[Region]]))) -> East | R63: =IF(PROPER(TRIM(F63))="Cloth Ing","Clothing",IF(PROPER(TRIM(F63))="Electronic","Electronics",IF(PROPER(TRIM(F63))="Grocery","Groceries",SUBSTITUTE(PROPER(TRIM(F63)),"Stationary","Stationery")))) -> Clothing | S63: =IF(LOWER(TRIM(H63))="online","Online",IF(OR(LOWER(TRIM(H63))="in-store",LOWER(TRIM(H63))="in store",LOWER(TRIM(H63))="instore"),"In-Store",PROPER(TRIM(H63)))) -> Online | T63: =IF(UPPER(TRIM(L63))="CC","Credit Card",PROPER(TRIM(L63))) -> Cash | U63: =IF(PROPER(TRIM(M63))="Complete","Completed",IF(PROPER(TRIM(M63))="Canceled","Cancelled",PROPER(TRIM(M63)))) -> Completed | V63: =IFERROR(VALUE(TRIM(I63)),"") -> 8 | W63: =IFERROR(VALUE(SUBSTITUTE(TRIM(J63),"$","")),"") | X63: =IFERROR(IF(ISNUMBER(tblOrders[[#This Row],[OrderDate]]),tblOrders[[#This Row],[OrderDate]],IFERROR(DATEVALUE(tblOrders[[#This Row],[OrderDate]]),DATE(IF(LEN(TRIM(tblOrders[[#This Row],[OrderDate]]))=8,2000+VALUE(RIGHT(TRIM(tblOrders[[#This Row],[OrderDate]]),2)),VALUE(RIGHT(TRIM(tblOrders[[#This Row],[OrderDate]]),4))),VALUE(MID(TRIM(tblOrders[[#This Row],[OrderDate]]),4,2)),VALUE(LEFT(TRIM(tblOrders[[#This Row],[OrderDate]]),2))))),"CHECK MANUALLY") -> 45561 | Y63: =IF(K63="",0,K63) -> 0 | Z63: =TRIM(CLEAN(tblOrders[[#This Row],[Notes]])) -> Gift wrap requested | AA63: =IF(OR(V63="",W63=""),"Review",IF(V63*W63>=1000,"High Value","Standard")) -> Review | AB63: =IF(OR(tblOrders[[#This Row],[Quantity_Clean]]="",tblOrders[[#This Row],[UnitPrice_Clean]]=""),0,tblOrders[[#This Row],[Quantity_Clean]]*tblOrders[[#This Row],[UnitPrice_Clean]]) -> 0 | AC63: =UPPER(TRIM(tblOrders[[#This Row],[OrderID]])) -> ORD-1156 | AD63: =VALUE(RIGHT(tblOrders[[#This Row],[OrderID]],4)) -> 1156 | AE63: =TEXT(tblOrders[[#This Row],[OrderDate_Clean]],"mmm-yyyy") -> Sep-2024 | AF63: =EOMONTH(tblOrders[[#This Row],[OrderDate_Clean]],0) -> 45565 | AG63: Priya | AH63: =IF(tblOrders[[#This Row],[Discount]]="",0,IF(ISNUMBER(tblOrders[[#This Row],[Discount]]),tblOrders[[#This Row],[Discount]],VALUE(SUBSTITUTE(TRIM(tblOrders[[#This Row],[Discount]]),"%",""))/100)) -> 0
A64: ORD-1213 | B64: 2024-11-06 | C64: Zara Brown | D64: South | E64: Hyderabad | F64: CLOTHING | G64: Winter Coat | H64: online | I64: 4 | K64: 0.2 | L64: Cash | M64: Canceled | N64: B. Fernandes | O64: Follow up needed | P64: =PROPER(TRIM(C64)) -> Zara Brown | Q64: =IF(OR(PROPER(TRIM(tblOrders[[#This Row],[Region]]))="Nort",PROPER(TRIM(tblOrders[[#This Row],[Region]]))="Northh"),"North",PROPER(TRIM(tblOrders[[#This Row],[Region]]))) -> South | R64: =IF(PROPER(TRIM(F64))="Cloth Ing","Clothing",IF(PROPER(TRIM(F64))="Electronic","Electronics",IF(PROPER(TRIM(F64))="Grocery","Groceries",SUBSTITUTE(PROPER(TRIM(F64)),"Stationary","Stationery")))) -> Clothing | S64: =IF(LOWER(TRIM(H64))="online","Online",IF(OR(LOWER(TRIM(H64))="in-store",LOWER(TRIM(H64))="in store",LOWER(TRIM(H64))="instore"),"In-Store",PROPER(TRIM(H64)))) -> Online | T64: =IF(UPPER(TRIM(L64))="CC","Credit Card",PROPER(TRIM(L64))) -> Cash | U64: =IF(PROPER(TRIM(M64))="Complete","Completed",IF(PROPER(TRIM(M64))="Canceled","Cancelled",PROPER(TRIM(M64)))) -> Cancelled | V64: =IFERROR(VALUE(TRIM(I64)),"") -> 4 | W64: =IFERROR(VALUE(SUBSTITUTE(TRIM(J64),"$","")),"") | X64: =IFERROR(IF(ISNUMBER(tblOrders[[#This Row],[OrderDate]]),tblOrders[[#This Row],[OrderDate]],IFERROR(DATEVALUE(tblOrders[[#This Row],[OrderDate]]),DATE(IF(LEN(TRIM(tblOrders[[#This Row],[OrderDate]]))=8,2000+VALUE(RIGHT(TRIM(tblOrders[[#This Row],[OrderDate]]),2)),VALUE(RIGHT(TRIM(tblOrders[[#This Row],[OrderDate]]),4))),VALUE(MID(TRIM(tblOrders[[#This Row],[OrderDate]]),4,2)),VALUE(LEFT(TRIM(tblOrders[[#This Row],[OrderDate]]),2))))),"CHECK MANUALLY") -> 45602 | Y64: =IF(K64="",0,K64) -> 0.2 | Z64: =TRIM(CLEAN(tblOrders[[#This Row],[Notes]])) -> Follow up needed | AA64: =IF(OR(V64="",W64=""),"Review",IF(V64*W64>=1000,"High Value","Standard")) -> Review | AB64: =IF(OR(tblOrders[[#This Row],[Quantity_Clean]]="",tblOrders[[#This Row],[UnitPrice_Clean]]=""),0,tblOrders[[#This Row],[Quantity_Clean]]*tblOrders[[#This Row],[UnitPrice_Clean]]) -> 0 | AC64: =UPPER(TRIM(tblOrders[[#This Row],[OrderID]])) -> ORD-1213 | AD64: =VALUE(RIGHT(tblOrders[[#This Row],[OrderID]],4)) -> 1213 | AE64: =TEXT(tblOrders[[#This Row],[OrderDate_Clean]],"mmm-yyyy") -> Nov-2024 | AF64: =EOMONTH(tblOrders[[#This Row],[OrderDate_Clean]],0) -> 45626 | AG64: Zara | AH64: =IF(tblOrders[[#This Row],[Discount]]="",0,IF(ISNUMBER(tblOrders[[#This Row],[Discount]]),tblOrders[[#This Row],[Discount]],VALUE(SUBSTITUTE(TRIM(tblOrders[[#This Row],[Discount]]),"%",""))/100)) -> 0.2
